Workbook
Name ActiveDecisionQueueIDs: '[1]Lists & Controls'!$P$3:$P$150
Name ActiveDecisionQueueIDs: 'Lists & Controls'!$P$3:$P$150

Sheet 5-Minute Summary
A1: SLT Tracker — 5-Minute Executive Summary
A2: Purpose: a fast read of the workbook’s main topics, risk highlights, and executive action items as of Jul 22, 2026.
A3: Summary date | B3: =DATE(2026,7,22) -> 46225
A4: Story in Brief
A5: This workbook is a board-ready SLT action and decision tracker. The immediate management focus is six active action records, especially overdue compensation/HR items, critical ASP Go-Live readiness, CFO governance controls, and items requiring CEO/CFO escalation. The dashboards and board summaries show the same executive metrics, while the Action Register and Decision Queue hold the working detail. The Decision Register is structured for permanent records but does not yet contain logged decision details.
A7: Open Actions | C7: Overdue | E7: Critical Priority | G7: High Risk
A8: =COUNTIFS('Action Register'!$B:$B,"<>",'Action Register'!$G:$G,"<>Completed",'Action Register'!$T:$T,"ACTIVE") -> 29 | C8: {=SUMPRODUCT(('Action Register'!$B$5:$B$104<>"")*('Action Register'!$G$5:$G$104<>"Completed")*('Action Register'!$T$5:$T$104="ACTIVE")*(IFERROR(--'Action Register'!$F$5:$F$104,DATEVALUE('Action Register'!$F$5:$F$104))<$B$3))} -> 0 | E8: =COUNTIFS('Action Register'!$B:$B,"<>",'Action Register'!$H:$H,"Critical",'Action Register'!$T:$T,"ACTIVE") -> 0 | G8: =COUNTIFS('Action Register'!$B:$B,"<>",'Action Register'!$J:$J,"High",'Action Register'!$T:$T,"ACTIVE") -> 6
A9: Active, non-completed records | C9: Due before summary date | E9: Priority = Critical | G9: Risk Impact = High
A11: Escalations | C11: ASP Go-Live Items | E11: Active Decisions | G11: Logged Decisions
A12: =COUNTIFS('Action Register'!$B:$B,"<>",'Action Register'!$L:$L,"Yes",'Action Register'!$T:$T,"ACTIVE") -> 3 | C12: =COUNTIFS('Action Register'!$B:$B,"<>",'Action Register'!$K:$K,"ASP Go-Live",'Action Register'!$T:$T,"ACTIVE") -> 5 | E12: =COUNTIFS('Decision Queue_Bak'!$B:$B,"<>",'Decision Queue_Bak'!$W:$W,"ACTIVE") -> 3 | G12: =MAX(0,COUNTA('Decision Register_Bak'!$C:$C)-1) -> 2
A13: Escalation Required = Yes | C13: Strategic Objective = ASP Go-Live | E13: Decision Queue items with detail | G13: Decision summaries recorded
A15: Main Topics Covered
A16: Topic | B16: What it means | C16: Where to read | E16: # | F16: Highlight
A17: SLT action tracking | B17: The central register tracks owners, due dates, next actions, status, priority, risk, escalation, financial impact, and strategic alignment. | C17: Action Register | E17: 1 | F17: The active action set is small but executive-heavy: six open actions, five escalation flags, three high-risk items, and two critical-priority items.
A18: Board / SLT summary | B18: Board-ready snapshot of open, overdue, critical, high-risk, escalation, and ASP Go-Live items. | C18: Board Summary (2) | E18: 2 | F18: Gene owns two open actions and both overdue items; the compensation/wage item is already past due and needs status confirmation.
A19: Executive dashboard | B19: Owner and strategic-objective views that show where attention is concentrated. | C19: Executive Dashboard (2) | E19: 3 | F19: ASP Go-Live is the clearest strategic risk: it is critical, high-risk, escalated, financially material (>$250K), and requires cross-functional inputs.
A20: ASP Go-Live readiness | B20: A dedicated executive workstream for licensing, construction, operations readiness, HR, training, ERP, capital spend, customer transition, and risk register inputs. | C20: Action Register / Decision Queue | E20: 4 | F20: CFO Governance & Controls is also critical/high-risk/escalated and is intended to become a live control register.
A21: Governance & controls | B21: CFO-led visibility for DOA, contracts, AI governance, incident management, audit findings, grants, legal review, and controls. | C21: Action Register / Enhancement Log | E21: 5 | F21: The Decision Queue has two active CEO/CFO attention items: tracker governance structure due Jul 22 and separate ASP Go-Live executive section due Jul 24.
A22: Decision queue and register | B22: Pending decisions are queued for CEO/CFO/SLT alignment; the permanent decision log is prepared but not yet populated with real decision details. | C22: Decision Queue / Decision Register | E22: 6 | F22: There are duplicate Board Summary and Executive Dashboard sheets; the “(2)” versions appear cleaner and more board-readable than the older versions.
A23: Controls and dropdowns | B23: Standard lists define status, priority, risk, financial impact, decision type, workstream, and ASP readiness streams. | C23: Lists & Controls
A25: Action Items for You / Executive Reviewer
A26: Priority | B26: Action item | C26: Owner / source | D26: Timing | E26: Minute | F26: Read this | G26: Why
A27: 1 | B27: Confirm whether to adopt the enhanced tracker governance model, required fields, and dashboard structure. | C27: Decision Queue: DEC-0001 / Sandy | D27: 46225 | E27: 1 | F27: KPI tiles on this sheet | G27: Know the scale and urgency immediately.
A28: 2 | B28: Resolve overdue Gene-owned items, especially wage increase review and payroll advance policy follow-through. | C28: Action Register: SLT-0001, SLT-0002 / Gene | D28: Immediate | E28: 2 | F28: Top Highlights | G28: Understand the executive storyline.
A29: 3 | B29: Treat ASP Go-Live as a separate executive workstream and confirm owner, cadence, and readiness sub-stream reporting. | C29: Decision Queue: DEC-0002 / Maurizio | D29: 46227 | E29: 3 | F29: Action Items | G29: Decide what you need to approve, escalate, or ask for.
A30: 4 | B30: Review critical/high-risk escalations first: ASP Go-Live readiness, CFO Governance & Controls, and financial impact classification. | C30: Action Register: SLT-0003, SLT-0004, SLT-0005 | D30: Next SLT review | E30: 4 | F30: Board Summary (2) | G30: Review board-facing items requiring attention.
A31: 5 | B31: Require missing financial materiality details where marked Unknown / TBD before board discussion. | C31: Action Register / Decision Queue | D31: Before board review | E31: 5 | F31: Decision Queue | G31: Confirm what needs CEO/CFO/SLT direction.
A32: 6 | B32: After decisions are made, move outcomes into the permanent Decision Register with decision maker, rationale, follow-up owner, and due date. | C32: Decision Register | D32: After each decision
A33: 7 | B33: Consolidate duplicate dashboard/summary versions so the workbook has one authoritative board view. | C33: Board Summary / Executive Dashboard | D33: Before circulation
A35: Important workbook notes
A36: 1
A37: 2
A38: 3

Sheet Board Summary (2)
A1: SLT Action Tracker - Board Summary
A2: Prepared for executive review. Focus areas: overdue decisions, critical/high-risk items, escalation points, ASP Go-Live readiness, and governance controls.
A4: Prepared for | B4: SLT / Board Review | D4: Prepared by | G4: Version | J4: Date | K4: 46219
A6: Open Actions | C6: Overdue | E6: Critical Priority | G6: High Risk | I6: Escalations | J6: ASP Go-Live Items
A7: ='Executive Dashboard'!A5 -> 29 | C7: ='Executive Dashboard'!C5 -> 10 | E7: ='Executive Dashboard'!F5 -> 0 | G7: ='Executive Dashboard'!K5 -> 6 | I7: 5 | J7: 1
A10: Items Requiring Executive Attention
A11: ID | B11: Item | C11: Owner | D11: Due Date | E11: Status | F11: Priority | G11: Risk | H11: Escalation | I11: Strategic Objective | J11: Board Note
A12: {=_xlfn.LET( _xlpm.ids,'Action Register'!$A$5:$A$104, _xlpm.items,'Action Register'!$B$5:$B$104, _xlpm.owners,'Action Register'!$D$5:$D$104, _xlpm.due,'Action Register'!$F$5:$F$104, _xlpm.dueNum,IFERROR(--_xlpm.due,DATEVALUE(_xlpm.due)), _xlpm.status,'Action Register'!$G$5:$G$104, _xlpm.pri,'Action Register'!$H$5:$H$104, _xlpm.risk,'Action Register'!$J$5:$J$104, _xlpm.obj,'Action Register'!$K$5:$K$104, _xlpm.esc,'Action Register'!$L$5:$L$104, _xlpm.note,'Action Register'!$P$5:$P$104, _xlpm.active,'Action Register'!$T$5:$T$104, _xlpm.include,(_xlpm.items<>"")*(_xlpm.active="ACTIVE")*((_xlpm.pri="Critical")+(_xlpm.pri="High")+(_xlpm.risk="High")+(_xlpm.esc="Yes")), _xlpm.data,CHOOSE({1,2,3,4,5,6,7,8,9,10},_xlpm.ids,_xlpm.items,_xlpm.owners,_xlpm.due,_xlpm.status,_xlpm.pri,_xlpm.risk,_xlpm.esc,_xlpm.obj,_xlpm.note), _xlpm.prioritySort,_xlfn._xlws.FILTER(_xlfn.SWITCH(_xlpm.pri,"Critical",1,"High",2,"Medium",3,"Low",4,9),_xlpm.include), _xlpm.overdueSort,_xlfn._xlws.FILTER(--(_xlpm.dueNum<TODAY()),_xlpm.include), _xlpm.escalationSort,_xlfn._xlws.FILTER(--(_xlpm.esc="Yes"),_xlpm.include), _xlpm.riskSort,_xlfn._xlws.FILTER(_xlfn.SWITCH(_xlpm.risk,"High",1,"Medium",2,"Low",3,9),_xlpm.include), _xlfn.TAKE(_xlfn.SORTBY(_xlfn._xlws.FILTER(_xlpm.data,_xlpm.include),_xlpm.prioritySort,1,_xlpm.overdueSort,-1,_xlpm.escalationSort,-1,_xlpm.riskSort,1),5) )} -> SLT-0051 | B12: Customer Invoice Pricing Discrepancies - London Drugs | C12: Dave | D12: 46311 | E12: In Progress | F12: High | G12: High | H12: No | I12: Other | J12: 0
A13: SLT-0035 | B13: Review December salary and pay-band alignment strategy in Q4 | C13: Gene | D13: 46308 | E13: In Progress | F13: High | G13: Medium | H13: No | I13: People & Culture | J13: 0
A14: SLT-0036 | B14: RTRI Funding Application - Reapplication | C14: Dave | D14: 46307 | E14: In Progress | F14: High | G14: Medium | H14: No | I14: Cost Reduction | J14: 0
A15: SLT-0054 | B15: Vacation and Blackout Period Planning | C15: Gene | D15: 46304 | E15: In Progress | F15: High | G15: Medium | H15: No | I15: People & Culture | J15: 0
A16: SLT-0042 | B16: $700K Risk - Maple Leaf Insurance Claim Risk | C16: Dave | D16: 46321 | E16: In Progress | F16: High | G16: High | H16: Yes | I16: Other | J16: 0
A19: Recommended Review Sequence | G19: Board-Ready Controls Added
A20: 1. Review overdue, critical, high-risk and escalation items first. | G20: • Priority and risk rating
A21: 2. Review ASP Go-Live as a stand-alone executive workstream. | G21: • Strategic objective alignment
A22: 3. Review Governance & Controls as a CFO-led control register. | G22: • Financial impact classification
A23: 4. Confirm decision queue items needing CEO/CFO/SLT direction. | G23: • CEO/CFO escalation flag
A24: 5. Confirm owners, due dates, blockers and follow-up evidence. | G24: • ASP readiness stream
G25: • Decision queue and permanent register

Sheet Executive Dashboard (2)
A1: Executive Dashboard
A2: Board-ready view of open actions, overdue items, risk, escalation, ASP Go-Live, and owner accountability.
A4: Open Actions | C4: Overdue | E4: Critical Priority | G4: High Risk | I4: Escalations | K4: ASP Go-Live Items
A5: =COUNTIFS('Action Register'!$T:$T,"ACTIVE",'Action Register'!$B:$B,"<>",'Action Register'!$G:$G,"<>Completed",'Action Register'!$G:$G,"<>Cancelled") -> 29 | C5: =COUNTIFS('Action Register'!$F:$F,"<"&TODAY(),'Action Register'!$B:$B,"<>",'Action Register'!$G:$G,"<>Completed",'Action Register'!$G:$G,"<>Cancelled",'Action Register'!$G:$G,"<>Deferred") -> 10 | E5: =COUNTIFS('Action Register'!$H:$H,"Critical",'Action Register'!$B:$B,"<>") -> 0 | G5: =COUNTIFS('Action Register'!$J:$J,"High",'Action Register'!$B:$B,"<>") -> 14 | I5: =COUNTIFS('Action Register'!$L:$L,"Yes",'Action Register'!$B:$B,"<>") -> 10 | K5: =COUNTIFS('Action Register'!$K:$K,"ASP Go-Live",'Action Register'!$B:$B,"<>") -> 9
A9: Owner | B9: Open | C9: Overdue | D9: At Risk / Stuck | E9: High Risk | F9: Escalations | H9: Strategic Objective | I9: Open Items | J9: High Risk | K9: Escalations
A10: Gene | B10: =COUNTIFS('Action Register'!$D:$D,$A10,'Action Register'!$B:$B,"<>",'Action Register'!$G:$G,"<>Completed",'Action Register'!$G:$G,"<>Cancelled") -> 4 | C10: =COUNTIFS('Action Register'!$D:$D,$A10,'Action Register'!$F:$F,"<"&TODAY(),'Action Register'!$B:$B,"<>",'Action Register'!$G:$G,"<>Completed",'Action Register'!$G:$G,"<>Cancelled",'Action Register'!$G:$G,"<>Deferred") -> 4 | D10: =COUNTIFS('Action Register'!$D:$D,$A10,'Action Register'!$G:$G,"At Risk")+COUNTIFS('Action Register'!$D:$D,$A10,'Action Register'!$G:$G,"Stuck") -> 0 | E10: =COUNTIFS('Action Register'!$D:$D,$A10,'Action Register'!$J:$J,"High") -> 1 | F10: =COUNTIFS('Action Register'!$D:$D,$A10,'Action Register'!$L:$L,"Yes") -> 2 | H10: ASP Go-Live | I10: =COUNTIFS('Action Register'!$K:$K,$H10,'Action Register'!$B:$B,"<>",'Action Register'!$G:$G,"<>Completed",'Action Register'!$G:$G,"<>Cancelled") -> 5 | J10: =COUNTIFS('Action Register'!$K:$K,$H10,'Action Register'!$J:$J,"High") -> 4 | K10: =COUNTIFS('Action Register'!$K:$K,$H10,'Action Register'!$L:$L,"Yes") -> 2
A11: Dave | B11: =COUNTIFS('Action Register'!$D:$D,$A11,'Action Register'!$B:$B,"<>",'Action Register'!$G:$G,"<>Completed",'Action Register'!$G:$G,"<>Cancelled") -> 7 | C11: =COUNTIFS('Action Register'!$D:$D,$A11,'Action Register'!$F:$F,"<"&TODAY(),'Action Register'!$B:$B,"<>",'Action Register'!$G:$G,"<>Completed",'Action Register'!$G:$G,"<>Cancelled",'Action Register'!$G:$G,"<>Deferred") -> 4 | D11: =COUNTIFS('Action Register'!$D:$D,$A11,'Action Register'!$G:$G,"At Risk")+COUNTIFS('Action Register'!$D:$D,$A11,'Action Register'!$G:$G,"Stuck") -> 0 | E11: =COUNTIFS('Action Register'!$D:$D,$A11,'Action Register'!$J:$J,"High") -> 7 | F11: =COUNTIFS('Action Register'!$D:$D,$A11,'Action Register'!$L:$L,"Yes") -> 2 | H11: Governance | I11: =COUNTIFS('Action Register'!$K:$K,$H11,'Action Register'!$B:$B,"<>",'Action Register'!$G:$G,"<>Completed",'Action Register'!$G:$G,"<>Cancelled") -> 6 | J11: =COUNTIFS('Action Register'!$K:$K,$H11,'Action Register'!$J:$J,"High") -> 1 | K11: =COUNTIFS('Action Register'!$K:$K,$H11,'Action Register'!$L:$L,"Yes") -> 2
A12: Maurizio | B12: =COUNTIFS('Action Register'!$D:$D,$A12,'Action Register'!$B:$B,"<>",'Action Register'!$G:$G,"<>Completed",'Action Register'!$G:$G,"<>Cancelled") -> 1 | C12: =COUNTIFS('Action Register'!$D:$D,$A12,'Action Register'!$F:$F,"<"&TODAY(),'Action Register'!$B:$B,"<>",'Action Register'!$G:$G,"<>Completed",'Action Register'!$G:$G,"<>Cancelled",'Action Register'!$G:$G,"<>Deferred") -> 0 | D12: =COUNTIFS('Action Register'!$D:$D,$A12,'Action Register'!$G:$G,"At Risk")+COUNTIFS('Action Register'!$D:$D,$A12,'Action Register'!$G:$G,"Stuck") -> 0 | E12: =COUNTIFS('Action Register'!$D:$D,$A12,'Action Register'!$J:$J,"High") -> 1 | F12: =COUNTIFS('Action Register'!$D:$D,$A12,'Action Register'!$L:$L,"Yes") -> 2 | H12: Cost Reduction | I12: =COUNTIFS('Action Register'!$K:$K,$H12,'Action Register'!$B:$B,"<>",'Action Register'!$G:$G,"<>Completed",'Action Register'!$G:$G,"<>Cancelled") -> 2 | J12: =COUNTIFS('Action Register'!$K:$K,$H12,'Action Register'!$J:$J,"High") -> 1 | K12: =COUNTIFS('Action Register'!$K:$K,$H12,'Action Register'!$L:$L,"Yes") -> 2
A13: Tom | B13: =COUNTIFS('Action Register'!$D:$D,$A13,'Action Register'!$B:$B,"<>",'Action Register'!$G:$G,"<>Completed",'Action Register'!$G:$G,"<>Cancelled") -> 5 | C13: =COUNTIFS('Action Register'!$D:$D,$A13,'Action Register'!$F:$F,"<"&TODAY(),'Action Register'!$B:$B,"<>",'Action Register'!$G:$G,"<>Completed",'Action Register'!$G:$G,"<>Cancelled",'Action Register'!$G:$G,"<>Deferred") -> 0 | D13: =COUNTIFS('Action Register'!$D:$D,$A13,'Action Register'!$G:$G,"At Risk")+COUNTIFS('Action Register'!$D:$D,$A13,'Action Register'!$G:$G,"Stuck") -> 0 | E13: =COUNTIFS('Action Register'!$D:$D,$A13,'Action Register'!$J:$J,"High") -> 2 | F13: =COUNTIFS('Action Register'!$D:$D,$A13,'Action Register'!$L:$L,"Yes") -> 1 | H13: People & Culture | I13: =COUNTIFS('Action Register'!$K:$K,$H13,'Action Register'!$B:$B,"<>",'Action Register'!$G:$G,"<>Completed",'Action Register'!$G:$G,"<>Cancelled") -> 6 | J13: =COUNTIFS('Action Register'!$K:$K,$H13,'Action Register'!$J:$J,"High") -> 3 | K13: =COUNTIFS('Action Register'!$K:$K,$H13,'Action Register'!$L:$L,"Yes") -> 3
A14: Tony | B14: =COUNTIFS('Action Register'!$D:$D,$A14,'Action Register'!$B:$B,"<>",'Action Register'!$G:$G,"<>Completed",'Action Register'!$G:$G,"<>Cancelled") -> 1 | C14: =COUNTIFS('Action Register'!$D:$D,$A14,'Action Register'!$F:$F,"<"&TODAY(),'Action Register'!$B:$B,"<>",'Action Register'!$G:$G,"<>Completed",'Action Register'!$G:$G,"<>Cancelled",'Action Register'!$G:$G,"<>Deferred") -> 1 | D14: =COUNTIFS('Action Register'!$D:$D,$A14,'Action Register'!$G:$G,"At Risk")+COUNTIFS('Action Register'!$D:$D,$A14,'Action Register'!$G:$G,"Stuck") -> 0 | E14: =COUNTIFS('Action Register'!$D:$D,$A14,'Action Register'!$J:$J,"High") -> 0 | F14: =COUNTIFS('Action Register'!$D:$D,$A14,'Action Register'!$L:$L,"Yes") -> 0 | H14: Sierra Growth | I14: =COUNTIFS('Action Register'!$K:$K,$H14,'Action Register'!$B:$B,"<>",'Action Register'!$G:$G,"<>Completed",'Action Register'!$G:$G,"<>Cancelled") -> 0 | J14: =COUNTIFS('Action Register'!$K:$K,$H14,'Action Register'!$J:$J,"High") -> 0 | K14: =COUNTIFS('Action Register'!$K:$K,$H14,'Action Register'!$L:$L,"Yes") -> 0
A15: Sherry | B15: =COUNTIFS('Action Register'!$D:$D,$A15,'Action Register'!$B:$B,"<>",'Action Register'!$G:$G,"<>Completed",'Action Register'!$G:$G,"<>Cancelled") -> 3 | C15: =COUNTIFS('Action Register'!$D:$D,$A15,'Action Register'!$F:$F,"<"&TODAY(),'Action Register'!$B:$B,"<>",'Action Register'!$G:$G,"<>Completed",'Action Register'!$G:$G,"<>Cancelled",'Action Register'!$G:$G,"<>Deferred") -> 0 | D15: =COUNTIFS('Action Register'!$D:$D,$A15,'Action Register'!$G:$G,"At Risk")+COUNTIFS('Action Register'!$D:$D,$A15,'Action Register'!$G:$G,"Stuck") -> 0 | E15: =COUNTIFS('Action Register'!$D:$D,$A15,'Action Register'!$J:$J,"High") -> 0 | F15: =COUNTIFS('Action Register'!$D:$D,$A15,'Action Register'!$L:$L,"Yes") -> 1 | H15: Federal Licence | I15: =COUNTIFS('Action Register'!$K:$K,$H15,'Action Register'!$B:$B,"<>",'Action Register'!$G:$G,"<>Completed",'Action Register'!$G:$G,"<>Cancelled") -> 0 | J15: =COUNTIFS('Action Register'!$K:$K,$H15,'Action Register'!$J:$J,"High") -> 0 | K15: =COUNTIFS('Action Register'!$K:$K,$H15,'Action Register'!$L:$L,"Yes") -> 0
A16: Sandy | B16: =COUNTIFS('Action Register'!$D:$D,$A16,'Action Register'!$B:$B,"<>",'Action Register'!$G:$G,"<>Completed",'Action Register'!$G:$G,"<>Cancelled") -> 0 | C16: =COUNTIFS('Action Register'!$D:$D,$A16,'Action Register'!$F:$F,"<"&TODAY(),'Action Register'!$B:$B,"<>",'Action Register'!$G:$G,"<>Completed",'Action Register'!$G:$G,"<>Cancelled",'Action Register'!$G:$G,"<>Deferred") -> 0 | D16: =COUNTIFS('Action Register'!$D:$D,$A16,'Action Register'!$G:$G,"At Risk")+COUNTIFS('Action Register'!$D:$D,$A16,'Action Register'!$G:$G,"Stuck") -> 0 | E16: =COUNTIFS('Action Register'!$D:$D,$A16,'Action Register'!$J:$J,"High") -> 0 | F16: =COUNTIFS('Action Register'!$D:$D,$A16,'Action Register'!$L:$L,"Yes") -> 1 | H16: Food Safety | I16: =COUNTIFS('Action Register'!$K:$K,$H16,'Action Register'!$B:$B,"<>",'Action Register'!$G:$G,"<>Completed",'Action Register'!$G:$G,"<>Cancelled") -> 1 | J16: =COUNTIFS('Action Register'!$K:$K,$H16,'Action Register'!$J:$J,"High") -> 0 | K16: =COUNTIFS('Action Register'!$K:$K,$H16,'Action Register'!$L:$L,"Yes") -> 0
A17: Other | B17: =COUNTIFS('Action Register'!$D:$D,$A17,'Action Register'!$B:$B,"<>",'Action Register'!$G:$G,"<>Completed",'Action Register'!$G:$G,"<>Cancelled") -> 0 | C17: =COUNTIFS('Action Register'!$D:$D,$A17,'Action Register'!$F:$F,"<"&TODAY(),'Action Register'!$B:$B,"<>",'Action Register'!$G:$G,"<>Completed",'Action Register'!$G:$G,"<>Cancelled",'Action Register'!$G:$G,"<>Deferred") -> 0 | D17: =COUNTIFS('Action Register'!$D:$D,$A17,'Action Register'!$G:$G,"At Risk")+COUNTIFS('Action Register'!$D:$D,$A17,'Action Register'!$G:$G,"Stuck") -> 0 | E17: =COUNTIFS('Action Register'!$D:$D,$A17,'Action Register'!$J:$J,"High") -> 0 | F17: =COUNTIFS('Action Register'!$D:$D,$A17,'Action Register'!$L:$L,"Yes") -> 0 | H17: Commercial Growth | I17: =COUNTIFS('Action Register'!$K:$K,$H17,'Action Register'!$B:$B,"<>",'Action Register'!$G:$G,"<>Completed",'Action Register'!$G:$G,"<>Cancelled") -> 3 | J17: =COUNTIFS('Action Register'!$K:$K,$H17,'Action Register'!$J:$J,"High") -> 1 | K17: =COUNTIFS('Action Register'!$K:$K,$H17,'Action Register'!$L:$L,"Yes") -> 0
A18: Executive Summary Charts
A37: Recommended Weekly SLT Review Sequence
A38: 1. Review Critical / High Risk / Escalation items first.
A39: 2. Review ASP Go-Live and Governance & Controls as separate executive categories.
A40: 3. Confirm overdue decisions and items requiring CEO/CFO attention.
A41: 4. Review owner accountability dashboard for bottlenecks.
A42: 5. Move decisions from Decision Queue to Decision Log once made, with follow-up owner and due date.

Sheet Board Summary
A1: SLT Action Tracker - Board Summary
A2: Prepared for executive review. Focus areas: overdue decisions, critical/high-risk items, escalation points, ASP Go-Live readiness, and governance controls.
A4: Prepared for | B4: SLT / Board Review | D4: Prepared by | G4: Version | J4: Date | K4: 46219
A6: Open Actions | B6: Overdue | C6: Critical Priority | E6: High Priority | G6: High Risk | I6: Escalations | J6: ASP Go-Live Items
A7: ='Executive Dashboard'!A5 -> 29 | B7: ='Executive Dashboard'!C5 -> 10 | C7: ='Executive Dashboard'!F5 -> 0 | E7: ='Executive Dashboard'!I5 -> 8 | G7: ='Executive Dashboard'!K5 -> 6 | I7: ='Executive Dashboard'!M5 -> 3 | J7: ='Executive Dashboard'!O5 -> 5
A10: Items Requiring Executive Attention
A11: ID | B11: Item | C11: Owner | D11: Due Date | E11: Status | F11: Priority | G11: Risk | H11: Escalation | I11: Strategic Objective | J11: Board Note
A12: {=_xlfn.LET( _xlpm.ids,'Action Register'!$A$5:$A$104, _xlpm.items,'Action Register'!$B$5:$B$104, _xlpm.owners,'Action Register'!$D$5:$D$104, _xlpm.due,'Action Register'!$F$5:$F$104, _xlpm.dueNum,IFERROR(--_xlpm.due,DATEVALUE(_xlpm.due)), _xlpm.status,'Action Register'!$G$5:$G$104, _xlpm.pri,'Action Register'!$H$5:$H$104, _xlpm.risk,'Action Register'!$J$5:$J$104, _xlpm.obj,'Action Register'!$K$5:$K$104, _xlpm.esc,'Action Register'!$L$5:$L$104, _xlpm.note,'Action Register'!$P$5:$P$104, _xlpm.active,'Action Register'!$T$5:$T$104, _xlpm.include,(_xlpm.items<>"")*(_xlpm.active="ACTIVE")*((_xlpm.pri="Critical")+(_xlpm.pri="High")+(_xlpm.risk="High")+(_xlpm.esc="Yes")+(_xlpm.due<=TODAY())), _xlpm.data,CHOOSE({1,2,3,4,5,6,7,8,9,10},_xlpm.ids,_xlpm.items,IF(_xlpm.owners="","",_xlpm.owners),_xlpm.due,_xlpm.status,_xlpm.pri,_xlpm.risk,_xlpm.esc,_xlpm.obj,IF(_xlpm.note="","",_xlpm.note)), _xlpm.prioritySort,_xlfn._xlws.FILTER(_xlfn.SWITCH(_xlpm.pri,"Critical",1,"High",2,"Medium",3,"Low",4,9),_xlpm.include), _xlpm.overdueSort,_xlfn._xlws.FILTER(--(_xlpm.dueNum<TODAY()),_xlpm.include), _xlpm.escalationSort,_xlfn._xlws.FILTER(--(_xlpm.esc="Yes"),_xlpm.include), _xlpm.riskSort,_xlfn._xlws.FILTER(_xlfn.SWITCH(_xlpm.risk,"High",1,"Medium",2,"Low",3,9),_xlpm.include), _xlfn.SORTBY(_xlfn._xlws.FILTER(_xlpm.data,_xlpm.include),_xlpm.prioritySort,1,_xlpm.overdueSort,-1,_xlpm.escalationSort,-1,_xlpm.riskSort,1) )} -> SLT-0051 | B12: Customer Invoice Pricing Discrepancies - London Drugs | C12: Dave | D12: 46311 | E12: In Progress | F12: High | G12: High | H12: No | I12: Other
A13: SLT-0035 | B13: Review December salary and pay-band alignment strategy in Q4 | C13: Gene | D13: 46308 | E13: In Progress | F13: High | G13: Medium | H13: No | I13: People & Culture
A14: SLT-0036 | B14: RTRI Funding Application - Reapplication | C14: Dave | D14: 46307 | E14: In Progress | F14: High | G14: Medium | H14: No | I14: Cost Reduction
A15: SLT-0054 | B15: Vacation and Blackout Period Planning | C15: Gene | D15: 46304 | E15: In Progress | F15: High | G15: Medium | H15: No | I15: People & Culture
A16: SLT-0042 | B16: $700K Risk - Maple Leaf Insurance Claim Risk | C16: Dave | D16: 46321 | E16: In Progress | F16: High | G16: High | H16: Yes | I16: Other
A17: SLT-0015 | B17: YVF Yield Report | C17: Tom | D17: 46322 | E17: In Progress | F17: High | G17: High | H17: No | I17: Commercial Growth | J17: Original request - 1. Confirm yield reports are being distributed to YVF stakeholders (Ryan and James). 2. Add the dollar impact of yields to YVF reports. Will support 2027 transfer price piece
A18: SLT-0025 | B18: Chilled Water System Change Order (OCO-008) | C18: Colin | D18: 46321 | E18: Assigned | F18: High | G18: High | H18: No | I18: ASP Go-Live | J18: Leadership also maintained that responsibility for the omission rests with Coldbox and should not be transferred to its subcontractor.
A19: SLT-0043 | B19: $200K - Inventory issue from 2025 year-end | C19: Dave | D19: 46321 | E19: In Progress | F19: High | G19: High | H19: No | I19: Other | J19: Resolve and record the $200K inventory variance from FY2025 year-end
A20: SLT-0001 | B20: Employee Payroll Advances | C20: Gene | D20: 46254 | E20: In Progress | F20: Medium | G20: Medium | H20: No | I20: Governance | J20: Governance fields added for SLT visibility.
A21: SLT-0008 | B21: Develop a Performance Plan for Tatiana | C21: Adam | D21: 46314 | E21: In Progress | F21: Medium | G21: Medium | H21: No | I21: People & Culture
A22: SLT-0012 | B22: PO Policy Rollout | C22: Dave | D22: 46316 | E22: In Progress | F22: Medium | G22: Medium | H22: No | I22: Governance | J22: Brought from deferred decision on May 11, 2026. Evaluated 2 vendor proposals. Sherry Crawford and Practical Approach.
A23: SLT-0029 | B23: Workorder Closure - Sierra | C23: Dave | D23: 46310 | E23: In Progress | F23: Medium | G23: Medium | H23: No | I23: Governance
A24: SLT-0017 | B24: Deloitte's Best Managed Companies | C24: Tony | D24: 46311 | E24: In Progress | F24: Medium | G24: Low | H24: No | I24: Other
A25: SLT-0004 | B25: CFO Governance & Controls Register | C25: Sherry | D25: 46321 | E25: In Progress | F25: Medium | G25: Medium | H25: Yes | I25: Governance | J25: CFO governance visibility for policies, internal audit, grants, legal review, and controls.
A26: SLT-0044 | B26: DSI Machine (Camera) Root Cause Analysis ($80K value equipment) | C26: Adam | D26: 46321 | E26: In Progress | F26: Medium | G26: Medium | H26: Yes | I26: Cost Reduction
A27: SLT-0022 | B27: Division 9 Steel - Change Order | C27: Colin | D27: 46321 | E27: In Progress | F27: Medium | G27: High | H27: No | I27: ASP Go-Live | J27: Per Colin's Decision Brief submission $410,559.82 remains available for interior alterations according to CBB. What happened to the $800K? Recall this monthly to SLT meetings until it is resolved.
A28: SLT-0048 | B28: Sierra Reserved Parking Policy | C28: Gene | D28: 46310 | E28: In Progress | F28: Low | G28: Low | H28: No | I28: People & Culture
A129: Recommended Review Sequence | G129: Board-Ready Controls Added
A130: 1. Review overdue, critical, high-risk and escalation items first. | G130: • Priority and risk rating
A131: 2. Review ASP Go-Live as a stand-alone executive workstream. | G131: • Strategic objective alignment
A132: 3. Review Governance & Controls as a CFO-led control register. | G132: • Financial impact classification
A133: 4. Confirm decision queue items needing CEO/CFO/SLT direction. | G133: • CEO/CFO escalation flag
A134: 5. Confirm owners, due dates, blockers and follow-up evidence. | G134: • ASP readiness stream
G135: • Decision queue and permanent register

Sheet Executive Dashboard
A1: Executive Dashboard
A2: Board-ready view of open actions, overdue items, risk, escalation, ASP Go-Live, and owner accountability.
A4: Open Actions | C4: Over Due | F4: Critical Priority | I4: High Priority | K4: High Risk | M4: Escalations | O4: ASP Go-Live Items
A5: =COUNTIFS('Action Register'!$T:$T,"ACTIVE",'Action Register'!$B:$B,"<>") -> 29 | C5: =COUNTIFS('Action Register'!$T:$T,"ACTIVE",'Action Register'!$F:$F,"<>",'Action Register'!$F:$F,"<"&TODAY(),'Action Register'!$B:$B,"<>") -> 10 | F5: =COUNTIFS('Action Register'!$T:$T,"ACTIVE",'Action Register'!$H:$H,"Critical",'Action Register'!$B:$B,"<>") -> 0 | I5: =COUNTIFS('Action Register'!$T:$T,"ACTIVE",'Action Register'!$H:$H,"High",'Action Register'!$B:$B,"<>") -> 8 | K5: =COUNTIFS('Action Register'!$T:$T,"ACTIVE",'Action Register'!$J:$J,"High",'Action Register'!$B:$B,"<>") -> 6 | M5: =COUNTIFS('Action Register'!$T:$T,"ACTIVE",'Action Register'!$L:$L,"Yes",'Action Register'!$B:$B,"<>") -> 3 | O5: =COUNTIFS('Action Register'!$T:$T,"ACTIVE",'Action Register'!$K:$K,"ASP Go-Live",'Action Register'!$B:$B,"<>") -> 5
A9: Owner | B9: Open | C9: Overdue | D9: Critical Priority | E9: High Priority | F9: High Risk | G9: At Risk / Stuck | H9: Escalations | J9: Strategic Objective | K9: Open Items | L9: Overdue | M9: Critical priority | N9: high priority | O9: High Risk | P9: Escalations
A10: Gene | B10: =COUNTIFS('Action Register'!$D:$D,$A10,'Action Register'!$B:$B,"<>",'Action Register'!$G:$G,"<>Completed",'Action Register'!$G:$G,"<>Cancelled") -> 4 | C10: =COUNTIFS('Action Register'!$D:$D,$A10,'Action Register'!$F:$F,"<"&TODAY(),'Action Register'!$B:$B,"<>",'Action Register'!$G:$G,"<>Closed",'Action Register'!$G:$G,"<>Completed",'Action Register'!$G:$G,"<>Cancelled",'Action Register'!$G:$G,"<>Deferred") -> 4 | D10: =COUNTIFS('Action Register'!$D:$D,$A10,'Action Register'!$H:$H,"Critical",'Action Register'!$G:$G,"<>Closed",'Action Register'!$G:$G,"<>Completed",'Action Register'!$G:$G,"<>Cancelled",'Action Register'!$G:$G,"<>Deferred") -> 0 | E10: =COUNTIFS('Action Register'!$D:$D,$A10,'Action Register'!$H:$H,"High",'Action Register'!$G:$G,"<>Closed",'Action Register'!$G:$G,"<>Completed",'Action Register'!$G:$G,"<>Cancelled",'Action Register'!$G:$G,"<>Deferred") -> 2 | F10: =COUNTIFS('Action Register'!$D:$D,$A10,'Action Register'!$J:$J,"High",'Action Register'!$G:$G,"<>Closed",'Action Register'!$G:$G,"<>Completed",'Action Register'!$G:$G,"<>Cancelled",'Action Register'!$G:$G,"<>Deferred") -> 0 | G10: =COUNTIFS('Action Register'!$D:$D,$A10,'Action Register'!$G:$G,"At Risk")+COUNTIFS('Action Register'!$D:$D,$A10,'Action Register'!$G:$G,"Stuck") -> 0 | H10: =COUNTIFS('Action Register'!$D:$D,$A10,'Action Register'!$L:$L,"Yes",'Action Register'!$G:$G,"<>Closed",'Action Register'!$G:$G,"<>Completed",'Action Register'!$G:$G,"<>Cancelled",'Action Register'!$G:$G,"<>Deferred") -> 0 | J10: ASP Go-Live | K10: =COUNTIFS('Action Register'!$K:$K,$J10,'Action Register'!$B:$B,"<>",'Action Register'!$G:$G,"<>Closed",'Action Register'!$G:$G,"<>Completed",'Action Register'!$G:$G,"<>Cancelled",'Action Register'!$G:$G,"<>Deferred") -> 5 | L10: =COUNTIFS('Action Register'!$K:$K,$J10,'Action Register'!$F:$F,"<"&TODAY(),'Action Register'!$B:$B,"<>",'Action Register'!$G:$G,"<>Closed",'Action Register'!$G:$G,"<>Completed",'Action Register'!$G:$G,"<>Cancelled",'Action Register'!$G:$G,"<>Deferred") -> 0 | M10: =COUNTIFS('Action Register'!$K:$K,$J10,'Action Register'!$H:$H,"Critical",'Action Register'!$G:$G,"<>Closed",'Action Register'!$G:$G,"<>Completed",'Action Register'!$G:$G,"<>Cancelled",'Action Register'!$G:$G,"<>Deferred") -> 0 | N10: =COUNTIFS('Action Register'!$K:$K,$J10,'Action Register'!$H:$H,"High",'Action Register'!$G:$G,"<>Closed",'Action Register'!$G:$G,"<>Completed",'Action Register'!$G:$G,"<>Cancelled",'Action Register'!$G:$G,"<>Deferred") -> 1 | O10: =COUNTIFS('Action Register'!$K:$K,$J10,'Action Register'!$J:$J,"High",'Action Register'!$G:$G,"<>Closed",'Action Register'!$G:$G,"<>Completed",'Action Register'!$G:$G,"<>Cancelled",'Action Register'!$G:$G,"<>Deferred") -> 2 | P10: =COUNTIFS('Action Register'!$K:$K,$J10,'Action Register'!$L:$L,"Yes",'Action Register'!$G:$G,"<>Closed",'Action Register'!$G:$G,"<>Completed",'Action Register'!$G:$G,"<>Cancelled",'Action Register'!$G:$G,"<>Deferred") -> 0
A11: Dave | B11: =COUNTIFS('Action Register'!$D:$D,$A11,'Action Register'!$B:$B,"<>",'Action Register'!$G:$G,"<>Completed",'Action Register'!$G:$G,"<>Cancelled") -> 7 | C11: =COUNTIFS('Action Register'!$D:$D,$A11,'Action Register'!$F:$F,"<"&TODAY(),'Action Register'!$B:$B,"<>",'Action Register'!$G:$G,"<>Closed",'Action Register'!$G:$G,"<>Completed",'Action Register'!$G:$G,"<>Cancelled",'Action Register'!$G:$G,"<>Deferred") -> 4 | D11: =COUNTIFS('Action Register'!$D:$D,$A11,'Action Register'!$H:$H,"Critical",'Action Register'!$G:$G,"<>Closed",'Action Register'!$G:$G,"<>Completed",'Action Register'!$G:$G,"<>Cancelled",'Action Register'!$G:$G,"<>Deferred") -> 0 | E11: =COUNTIFS('Action Register'!$D:$D,$A11,'Action Register'!$H:$H,"High",'Action Register'!$G:$G,"<>Closed",'Action Register'!$G:$G,"<>Completed",'Action Register'!$G:$G,"<>Cancelled",'Action Register'!$G:$G,"<>Deferred") -> 4 | F11: =COUNTIFS('Action Register'!$D:$D,$A11,'Action Register'!$J:$J,"High",'Action Register'!$G:$G,"<>Closed",'Action Register'!$G:$G,"<>Completed",'Action Register'!$G:$G,"<>Cancelled",'Action Register'!$G:$G,"<>Deferred") -> 3 | G11: =COUNTIFS('Action Register'!$D:$D,$A11,'Action Register'!$G:$G,"At Risk")+COUNTIFS('Action Register'!$D:$D,$A11,'Action Register'!$G:$G,"Stuck") -> 0 | H11: =COUNTIFS('Action Register'!$D:$D,$A11,'Action Register'!$L:$L,"Yes",'Action Register'!$G:$G,"<>Closed",'Action Register'!$G:$G,"<>Completed",'Action Register'!$G:$G,"<>Cancelled",'Action Register'!$G:$G,"<>Deferred") -> 1 | J11: Governance | K11: =COUNTIFS('Action Register'!$K:$K,$J11,'Action Register'!$B:$B,"<>",'Action Register'!$G:$G,"<>Closed",'Action Register'!$G:$G,"<>Completed",'Action Register'!$G:$G,"<>Cancelled",'Action Register'!$G:$G,"<>Deferred") -> 6 | L11: =COUNTIFS('Action Register'!$K:$K,$J11,'Action Register'!$F:$F,"<"&TODAY(),'Action Register'!$B:$B,"<>",'Action Register'!$G:$G,"<>Closed",'Action Register'!$G:$G,"<>Completed",'Action Register'!$G:$G,"<>Cancelled",'Action Register'!$G:$G,"<>Deferred") -> 3 | M11: =COUNTIFS('Action Register'!$K:$K,$J11,'Action Register'!$H:$H,"Critical",'Action Register'!$G:$G,"<>Closed",'Action Register'!$G:$G,"<>Completed",'Action Register'!$G:$G,"<>Cancelled",'Action Register'!$G:$G,"<>Deferred") -> 0 | N11: =COUNTIFS('Action Register'!$K:$K,$J11,'Action Register'!$H:$H,"High",'Action Register'!$G:$G,"<>Closed",'Action Register'!$G:$G,"<>Completed",'Action Register'!$G:$G,"<>Cancelled",'Action Register'!$G:$G,"<>Deferred") -> 0 | O11: =COUNTIFS('Action Register'!$K:$K,$J11,'Action Register'!$J:$J,"High",'Action Register'!$G:$G,"<>Closed",'Action Register'!$G:$G,"<>Completed",'Action Register'!$G:$G,"<>Cancelled",'Action Register'!$G:$G,"<>Deferred") -> 0 | P11: =COUNTIFS('Action Register'!$K:$K,$J11,'Action Register'!$L:$L,"Yes",'Action Register'!$G:$G,"<>Closed",'Action Register'!$G:$G,"<>Completed",'Action Register'!$G:$G,"<>Cancelled",'Action Register'!$G:$G,"<>Deferred") -> 1
A12: Maurizio | B12: =COUNTIFS('Action Register'!$D:$D,$A12,'Action Register'!$B:$B,"<>",'Action Register'!$G:$G,"<>Completed",'Action Register'!$G:$G,"<>Cancelled") -> 1 | C12: =COUNTIFS('Action Register'!$D:$D,$A12,'Action Register'!$F:$F,"<"&TODAY(),'Action Register'!$B:$B,"<>",'Action Register'!$G:$G,"<>Closed",'Action Register'!$G:$G,"<>Completed",'Action Register'!$G:$G,"<>Cancelled",'Action Register'!$G:$G,"<>Deferred") -> 0 | D12: =COUNTIFS('Action Register'!$D:$D,$A12,'Action Register'!$H:$H,"Critical",'Action Register'!$G:$G,"<>Closed",'Action Register'!$G:$G,"<>Completed",'Action Register'!$G:$G,"<>Cancelled",'Action Register'!$G:$G,"<>Deferred") -> 0 | E12: =COUNTIFS('Action Register'!$D:$D,$A12,'Action Register'!$H:$H,"High",'Action Register'!$G:$G,"<>Closed",'Action Register'!$G:$G,"<>Completed",'Action Register'!$G:$G,"<>Cancelled",'Action Register'!$G:$G,"<>Deferred") -> 0 | F12: =COUNTIFS('Action Register'!$D:$D,$A12,'Action Register'!$J:$J,"High",'Action Register'!$G:$G,"<>Closed",'Action Register'!$G:$G,"<>Completed",'Action Register'!$G:$G,"<>Cancelled",'Action Register'!$G:$G,"<>Deferred") -> 0 | G12: =COUNTIFS('Action Register'!$D:$D,$A12,'Action Register'!$G:$G,"At Risk")+COUNTIFS('Action Register'!$D:$D,$A12,'Action Register'!$G:$G,"Stuck") -> 0 | H12: =COUNTIFS('Action Register'!$D:$D,$A12,'Action Register'!$L:$L,"Yes",'Action Register'!$G:$G,"<>Closed",'Action Register'!$G:$G,"<>Completed",'Action Register'!$G:$G,"<>Cancelled",'Action Register'!$G:$G,"<>Deferred") -> 0 | J12: Cost Reduction | K12: =COUNTIFS('Action Register'!$K:$K,$J12,'Action Register'!$B:$B,"<>",'Action Register'!$G:$G,"<>Closed",'Action Register'!$G:$G,"<>Completed",'Action Register'!$G:$G,"<>Cancelled",'Action Register'!$G:$G,"<>Deferred") -> 2 | L12: =COUNTIFS('Action Register'!$K:$K,$J12,'Action Register'!$F:$F,"<"&TODAY(),'Action Register'!$B:$B,"<>",'Action Register'!$G:$G,"<>Closed",'Action Register'!$G:$G,"<>Completed",'Action Register'!$G:$G,"<>Cancelled",'Action Register'!$G:$G,"<>Deferred") -> 1 | M12: =COUNTIFS('Action Register'!$K:$K,$J12,'Action Register'!$H:$H,"Critical",'Action Register'!$G:$G,"<>Closed",'Action Register'!$G:$G,"<>Completed",'Action Register'!$G:$G,"<>Cancelled",'Action Register'!$G:$G,"<>Deferred") -> 0 | N12: =COUNTIFS('Action Register'!$K:$K,$J12,'Action Register'!$H:$H,"High",'Action Register'!$G:$G,"<>Closed",'Action Register'!$G:$G,"<>Completed",'Action Register'!$G:$G,"<>Cancelled",'Action Register'!$G:$G,"<>Deferred") -> 1 | O12: =COUNTIFS('Action Register'!$K:$K,$J12,'Action Register'!$J:$J,"High",'Action Register'!$G:$G,"<>Closed",'Action Register'!$G:$G,"<>Completed",'Action Register'!$G:$G,"<>Cancelled",'Action Register'!$G:$G,"<>Deferred") -> 0 | P12: =COUNTIFS('Action Register'!$K:$K,$J12,'Action Register'!$L:$L,"Yes",'Action Register'!$G:$G,"<>Closed",'Action Register'!$G:$G,"<>Completed",'Action Register'!$G:$G,"<>Cancelled",'Action Register'!$G:$G,"<>Deferred") -> 1
A13: Tom | B13: =COUNTIFS('Action Register'!$D:$D,$A13,'Action Register'!$B:$B,"<>",'Action Register'!$G:$G,"<>Completed",'Action Register'!$G:$G,"<>Cancelled") -> 5 | C13: =COUNTIFS('Action Register'!$D:$D,$A13,'Action Register'!$F:$F,"<"&TODAY(),'Action Register'!$B:$B,"<>",'Action Register'!$G:$G,"<>Closed",'Action Register'!$G:$G,"<>Completed",'Action Register'!$G:$G,"<>Cancelled",'Action Register'!$G:$G,"<>Deferred") -> 0 | D13: =COUNTIFS('Action Register'!$D:$D,$A13,'Action Register'!$H:$H,"Critical",'Action Register'!$G:$G,"<>Closed",'Action Register'!$G:$G,"<>Completed",'Action Register'!$G:$G,"<>Cancelled",'Action Register'!$G:$G,"<>Deferred") -> 0 | E13: =COUNTIFS('Action Register'!$D:$D,$A13,'Action Register'!$H:$H,"High",'Action Register'!$G:$G,"<>Closed",'Action Register'!$G:$G,"<>Completed",'Action Register'!$G:$G,"<>Cancelled",'Action Register'!$G:$G,"<>Deferred") -> 1 | F13: =COUNTIFS('Action Register'!$D:$D,$A13,'Action Register'!$J:$J,"High",'Action Register'!$G:$G,"<>Closed",'Action Register'!$G:$G,"<>Completed",'Action Register'!$G:$G,"<>Cancelled",'Action Register'!$G:$G,"<>Deferred") -> 1 | G13: =COUNTIFS('Action Register'!$D:$D,$A13,'Action Register'!$G:$G,"At Risk")+COUNTIFS('Action Register'!$D:$D,$A13,'Action Register'!$G:$G,"Stuck") -> 0 | H13: =COUNTIFS('Action Register'!$D:$D,$A13,'Action Register'!$L:$L,"Yes",'Action Register'!$G:$G,"<>Closed",'Action Register'!$G:$G,"<>Completed",'Action Register'!$G:$G,"<>Cancelled",'Action Register'!$G:$G,"<>Deferred") -> 0 | J13: People & Culture | K13: =COUNTIFS('Action Register'!$K:$K,$J13,'Action Register'!$B:$B,"<>",'Action Register'!$G:$G,"<>Closed",'Action Register'!$G:$G,"<>Completed",'Action Register'!$G:$G,"<>Cancelled",'Action Register'!$G:$G,"<>Deferred") -> 6 | L13: =COUNTIFS('Action Register'!$K:$K,$J13,'Action Register'!$F:$F,"<"&TODAY(),'Action Register'!$B:$B,"<>",'Action Register'!$G:$G,"<>Closed",'Action Register'!$G:$G,"<>Completed",'Action Register'!$G:$G,"<>Cancelled",'Action Register'!$G:$G,"<>Deferred") -> 4 | M13: =COUNTIFS('Action Register'!$K:$K,$J13,'Action Register'!$H:$H,"Critical",'Action Register'!$G:$G,"<>Closed",'Action Register'!$G:$G,"<>Completed",'Action Register'!$G:$G,"<>Cancelled",'Action Register'!$G:$G,"<>Deferred") -> 0 | N13: =COUNTIFS('Action Register'!$K:$K,$J13,'Action Register'!$H:$H,"High",'Action Register'!$G:$G,"<>Closed",'Action Register'!$G:$G,"<>Completed",'Action Register'!$G:$G,"<>Cancelled",'Action Register'!$G:$G,"<>Deferred") -> 2 | O13: =COUNTIFS('Action Register'!$K:$K,$J13,'Action Register'!$J:$J,"High",'Action Register'!$G:$G,"<>Closed",'Action Register'!$G:$G,"<>Completed",'Action Register'!$G:$G,"<>Cancelled",'Action Register'!$G:$G,"<>Deferred") -> 0 | P13: =COUNTIFS('Action Register'!$K:$K,$J13,'Action Register'!$L:$L,"Yes",'Action Register'!$G:$G,"<>Closed",'Action Register'!$G:$G,"<>Completed",'Action Register'!$G:$G,"<>Cancelled",'Action Register'!$G:$G,"<>Deferred") -> 0
A14: Tony | B14: =COUNTIFS('Action Register'!$D:$D,$A14,'Action Register'!$B:$B,"<>",'Action Register'!$G:$G,"<>Completed",'Action Register'!$G:$G,"<>Cancelled") -> 1 | C14: =COUNTIFS('Action Register'!$D:$D,$A14,'Action Register'!$F:$F,"<"&TODAY(),'Action Register'!$B:$B,"<>",'Action Register'!$G:$G,"<>Closed",'Action Register'!$G:$G,"<>Completed",'Action Register'!$G:$G,"<>Cancelled",'Action Register'!$G:$G,"<>Deferred") -> 1 | D14: =COUNTIFS('Action Register'!$D:$D,$A14,'Action Register'!$H:$H,"Critical",'Action Register'!$G:$G,"<>Closed",'Action Register'!$G:$G,"<>Completed",'Action Register'!$G:$G,"<>Cancelled",'Action Register'!$G:$G,"<>Deferred") -> 0 | E14: =COUNTIFS('Action Register'!$D:$D,$A14,'Action Register'!$H:$H,"High",'Action Register'!$G:$G,"<>Closed",'Action Register'!$G:$G,"<>Completed",'Action Register'!$G:$G,"<>Cancelled",'Action Register'!$G:$G,"<>Deferred") -> 0 | F14: =COUNTIFS('Action Register'!$D:$D,$A14,'Action Register'!$J:$J,"High",'Action Register'!$G:$G,"<>Closed",'Action Register'!$G:$G,"<>Completed",'Action Register'!$G:$G,"<>Cancelled",'Action Register'!$G:$G,"<>Deferred") -> 0 | G14: =COUNTIFS('Action Register'!$D:$D,$A14,'Action Register'!$G:$G,"At Risk")+COUNTIFS('Action Register'!$D:$D,$A14,'Action Register'!$G:$G,"Stuck") -> 0 | H14: =COUNTIFS('Action Register'!$D:$D,$A14,'Action Register'!$L:$L,"Yes",'Action Register'!$G:$G,"<>Closed",'Action Register'!$G:$G,"<>Completed",'Action Register'!$G:$G,"<>Cancelled",'Action Register'!$G:$G,"<>Deferred") -> 0 | J14: Sierra Growth | K14: =COUNTIFS('Action Register'!$K:$K,$J14,'Action Register'!$B:$B,"<>",'Action Register'!$G:$G,"<>Closed",'Action Register'!$G:$G,"<>Completed",'Action Register'!$G:$G,"<>Cancelled",'Action Register'!$G:$G,"<>Deferred") -> 0 | L14: =COUNTIFS('Action Register'!$K:$K,$J14,'Action Register'!$F:$F,"<"&TODAY(),'Action Register'!$B:$B,"<>",'Action Register'!$G:$G,"<>Closed",'Action Register'!$G:$G,"<>Completed",'Action Register'!$G:$G,"<>Cancelled",'Action Register'!$G:$G,"<>Deferred") -> 0 | M14: =COUNTIFS('Action Register'!$K:$K,$J14,'Action Register'!$H:$H,"Critical",'Action Register'!$G:$G,"<>Closed",'Action Register'!$G:$G,"<>Completed",'Action Register'!$G:$G,"<>Cancelled",'Action Register'!$G:$G,"<>Deferred") -> 0 | N14: =COUNTIFS('Action Register'!$K:$K,$J14,'Action Register'!$H:$H,"High",'Action Register'!$G:$G,"<>Closed",'Action Register'!$G:$G,"<>Completed",'Action Register'!$G:$G,"<>Cancelled",'Action Register'!$G:$G,"<>Deferred") -> 0 | O14: =COUNTIFS('Action Register'!$K:$K,$J14,'Action Register'!$J:$J,"High",'Action Register'!$G:$G,"<>Closed",'Action Register'!$G:$G,"<>Completed",'Action Register'!$G:$G,"<>Cancelled",'Action Register'!$G:$G,"<>Deferred") -> 0 | P14: =COUNTIFS('Action Register'!$K:$K,$J14,'Action Register'!$L:$L,"Yes",'Action Register'!$G:$G,"<>Closed",'Action Register'!$G:$G,"<>Completed",'Action Register'!$G:$G,"<>Cancelled",'Action Register'!$G:$G,"<>Deferred") -> 0
A15: Sherry | B15: =COUNTIFS('Action Register'!$D:$D,$A15,'Action Register'!$B:$B,"<>",'Action Register'!$G:$G,"<>Completed",'Action Register'!$G:$G,"<>Cancelled") -> 3 | C15: =COUNTIFS('Action Register'!$D:$D,$A15,'Action Register'!$F:$F,"<"&TODAY(),'Action Register'!$B:$B,"<>",'Action Register'!$G:$G,"<>Closed",'Action Register'!$G:$G,"<>Completed",'Action Register'!$G:$G,"<>Cancelled",'Action Register'!$G:$G,"<>Deferred") -> 0 | D15: =COUNTIFS('Action Register'!$D:$D,$A15,'Action Register'!$H:$H,"Critical",'Action Register'!$G:$G,"<>Closed",'Action Register'!$G:$G,"<>Completed",'Action Register'!$G:$G,"<>Cancelled",'Action Register'!$G:$G,"<>Deferred") -> 0 | E15: =COUNTIFS('Action Register'!$D:$D,$A15,'Action Register'!$H:$H,"High",'Action Register'!$G:$G,"<>Closed",'Action Register'!$G:$G,"<>Completed",'Action Register'!$G:$G,"<>Cancelled",'Action Register'!$G:$G,"<>Deferred") -> 0 | F15: =COUNTIFS('Action Register'!$D:$D,$A15,'Action Register'!$J:$J,"High",'Action Register'!$G:$G,"<>Closed",'Action Register'!$G:$G,"<>Completed",'Action Register'!$G:$G,"<>Cancelled",'Action Register'!$G:$G,"<>Deferred") -> 0 | G15: =COUNTIFS('Action Register'!$D:$D,$A15,'Action Register'!$G:$G,"At Risk")+COUNTIFS('Action Register'!$D:$D,$A15,'Action Register'!$G:$G,"Stuck") -> 0 | H15: =COUNTIFS('Action Register'!$D:$D,$A15,'Action Register'!$L:$L,"Yes",'Action Register'!$G:$G,"<>Closed",'Action Register'!$G:$G,"<>Completed",'Action Register'!$G:$G,"<>Cancelled",'Action Register'!$G:$G,"<>Deferred") -> 1 | J15: Federal Licence | K15: =COUNTIFS('Action Register'!$K:$K,$J15,'Action Register'!$B:$B,"<>",'Action Register'!$G:$G,"<>Closed",'Action Register'!$G:$G,"<>Completed",'Action Register'!$G:$G,"<>Cancelled",'Action Register'!$G:$G,"<>Deferred") -> 0 | L15: =COUNTIFS('Action Register'!$K:$K,$J15,'Action Register'!$F:$F,"<"&TODAY(),'Action Register'!$B:$B,"<>",'Action Register'!$G:$G,"<>Closed",'Action Register'!$G:$G,"<>Completed",'Action Register'!$G:$G,"<>Cancelled",'Action Register'!$G:$G,"<>Deferred") -> 0 | M15: =COUNTIFS('Action Register'!$K:$K,$J15,'Action Register'!$H:$H,"Critical",'Action Register'!$G:$G,"<>Closed",'Action Register'!$G:$G,"<>Completed",'Action Register'!$G:$G,"<>Cancelled",'Action Register'!$G:$G,"<>Deferred") -> 0 | N15: =COUNTIFS('Action Register'!$K:$K,$J15,'Action Register'!$H:$H,"High",'Action Register'!$G:$G,"<>Closed",'Action Register'!$G:$G,"<>Completed",'Action Register'!$G:$G,"<>Cancelled",'Action Register'!$G:$G,"<>Deferred") -> 0 | O15: =COUNTIFS('Action Register'!$K:$K,$J15,'Action Register'!$J:$J,"High",'Action Register'!$G:$G,"<>Closed",'Action Register'!$G:$G,"<>Completed",'Action Register'!$G:$G,"<>Cancelled",'Action Register'!$G:$G,"<>Deferred") -> 0 | P15: =COUNTIFS('Action Register'!$K:$K,$J15,'Action Register'!$L:$L,"Yes",'Action Register'!$G:$G,"<>Closed",'Action Register'!$G:$G,"<>Completed",'Action Register'!$G:$G,"<>Cancelled",'Action Register'!$G:$G,"<>Deferred") -> 0
A16: Sandy | B16: =COUNTIFS('Action Register'!$D:$D,$A16,'Action Register'!$B:$B,"<>",'Action Register'!$G:$G,"<>Completed",'Action Register'!$G:$G,"<>Cancelled") -> 0 | C16: =COUNTIFS('Action Register'!$D:$D,$A16,'Action Register'!$F:$F,"<"&TODAY(),'Action Register'!$B:$B,"<>",'Action Register'!$G:$G,"<>Closed",'Action Register'!$G:$G,"<>Completed",'Action Register'!$G:$G,"<>Cancelled",'Action Register'!$G:$G,"<>Deferred") -> 0 | D16: =COUNTIFS('Action Register'!$D:$D,$A16,'Action Register'!$H:$H,"Critical",'Action Register'!$G:$G,"<>Closed",'Action Register'!$G:$G,"<>Completed",'Action Register'!$G:$G,"<>Cancelled",'Action Register'!$G:$G,"<>Deferred") -> 0 | E16: =COUNTIFS('Action Register'!$D:$D,$A16,'Action Register'!$H:$H,"High",'Action Register'!$G:$G,"<>Closed",'Action Register'!$G:$G,"<>Completed",'Action Register'!$G:$G,"<>Cancelled",'Action Register'!$G:$G,"<>Deferred") -> 0 | F16: =COUNTIFS('Action Register'!$D:$D,$A16,'Action Register'!$J:$J,"High",'Action Register'!$G:$G,"<>Closed",'Action Register'!$G:$G,"<>Completed",'Action Register'!$G:$G,"<>Cancelled",'Action Register'!$G:$G,"<>Deferred") -> 0 | G16: =COUNTIFS('Action Register'!$D:$D,$A16,'Action Register'!$G:$G,"At Risk")+COUNTIFS('Action Register'!$D:$D,$A16,'Action Register'!$G:$G,"Stuck") -> 0 | H16: =COUNTIFS('Action Register'!$D:$D,$A16,'Action Register'!$L:$L,"Yes",'Action Register'!$G:$G,"<>Closed",'Action Register'!$G:$G,"<>Completed",'Action Register'!$G:$G,"<>Cancelled",'Action Register'!$G:$G,"<>Deferred") -> 0 | J16: Food Safety | K16: =COUNTIFS('Action Register'!$K:$K,$J16,'Action Register'!$B:$B,"<>",'Action Register'!$G:$G,"<>Closed",'Action Register'!$G:$G,"<>Completed",'Action Register'!$G:$G,"<>Cancelled",'Action Register'!$G:$G,"<>Deferred") -> 1 | L16: =COUNTIFS('Action Register'!$K:$K,$J16,'Action Register'!$F:$F,"<"&TODAY(),'Action Register'!$B:$B,"<>",'Action Register'!$G:$G,"<>Closed",'Action Register'!$G:$G,"<>Completed",'Action Register'!$G:$G,"<>Cancelled",'Action Register'!$G:$G,"<>Deferred") -> 0 | M16: =COUNTIFS('Action Register'!$K:$K,$J16,'Action Register'!$H:$H,"Critical",'Action Register'!$G:$G,"<>Closed",'Action Register'!$G:$G,"<>Completed",'Action Register'!$G:$G,"<>Cancelled",'Action Register'!$G:$G,"<>Deferred") -> 0 | N16: =COUNTIFS('Action Register'!$K:$K,$J16,'Action Register'!$H:$H,"High",'Action Register'!$G:$G,"<>Closed",'Action Register'!$G:$G,"<>Completed",'Action Register'!$G:$G,"<>Cancelled",'Action Register'!$G:$G,"<>Deferred") -> 0 | O16: =COUNTIFS('Action Register'!$K:$K,$J16,'Action Register'!$J:$J,"High",'Action Register'!$G:$G,"<>Closed",'Action Register'!$G:$G,"<>Completed",'Action Register'!$G:$G,"<>Cancelled",'Action Register'!$G:$G,"<>Deferred") -> 0 | P16: =COUNTIFS('Action Register'!$K:$K,$J16,'Action Register'!$L:$L,"Yes",'Action Register'!$G:$G,"<>Closed",'Action Register'!$G:$G,"<>Completed",'Action Register'!$G:$G,"<>Cancelled",'Action Register'!$G:$G,"<>Deferred") -> 0
A17: Other | B17: {=SUMPRODUCT(--('Action Register'!$B$5:$B$104<>""),--(COUNTIF($A$10:$A$16,'Action Register'!$D$5:$D$104)=0),--('Action Register'!$G$5:$G$104<>"Closed"),--('Action Register'!$G$5:$G$104<>"Completed"),--('Action Register'!$G$5:$G$104<>"Cancelled"),--('Action Register'!$G$5:$G$104<>"Deferred"))} -> 8 | C17: {=SUMPRODUCT(--('Action Register'!$B$5:$B$104<>""),--(COUNTIF($A$10:$A$16,'Action Register'!$D$5:$D$104)=0),--('Action Register'!$F$5:$F$104<>""),--('Action Register'!$F$5:$F$104<TODAY()),--('Action Register'!$G$5:$G$104<>"Closed"),--('Action Register'!$G$5:$G$104<>"Completed"),--('Action Register'!$G$5:$G$104<>"Cancelled"),--('Action Register'!$G$5:$G$104<>"Deferred"))} -> 1 | D17: {=SUMPRODUCT(--('Action Register'!$B$5:$B$104<>""),--(COUNTIF($A$10:$A$16,'Action Register'!$D$5:$D$104)=0),--('Action Register'!$H$5:$H$104="Critical"),--('Action Register'!$G$5:$G$104<>"Closed"),--('Action Register'!$G$5:$G$104<>"Completed"),--('Action Register'!$G$5:$G$104<>"Cancelled"),--('Action Register'!$G$5:$G$104<>"Deferred"))} -> 0 | E17: {=SUMPRODUCT(--('Action Register'!$B$5:$B$104<>""),--(COUNTIF($A$10:$A$16,'Action Register'!$D$5:$D$104)=0),--('Action Register'!$H$5:$H$104="High"),--('Action Register'!$G$5:$G$104<>"Closed"),--('Action Register'!$G$5:$G$104<>"Completed"),--('Action Register'!$G$5:$G$104<>"Cancelled"),--('Action Register'!$G$5:$G$104<>"Deferred"))} -> 1 | F17: {=SUMPRODUCT(--('Action Register'!$B$5:$B$104<>""),--(COUNTIF($A$10:$A$16,'Action Register'!$D$5:$D$104)=0),--('Action Register'!$J$5:$J$104="High"),--('Action Register'!$G$5:$G$104<>"Closed"),--('Action Register'!$G$5:$G$104<>"Completed"),--('Action Register'!$G$5:$G$104<>"Cancelled"),--('Action Register'!$G$5:$G$104<>"Deferred"))} -> 2 | G17: {=SUMPRODUCT(--('Action Register'!$B$5:$B$104<>""),--(COUNTIF($A$10:$A$16,'Action Register'!$D$5:$D$104)=0),--((('Action Register'!$G$5:$G$104="At Risk")+('Action Register'!$G$5:$G$104="Stuck"))>0))} -> 0 | H17: {=SUMPRODUCT(--('Action Register'!$B$5:$B$104<>""),--(COUNTIF($A$10:$A$16,'Action Register'!$D$5:$D$104)=0),--('Action Register'!$L$5:$L$104="Yes"),--('Action Register'!$G$5:$G$104<>"Closed"),--('Action Register'!$G$5:$G$104<>"Completed"),--('Action Register'!$G$5:$G$104<>"Cancelled"),--('Action Register'!$G$5:$G$104<>"Deferred"))} -> 1 | J17: Commercial Growth | K17: =COUNTIFS('Action Register'!$K:$K,$J17,'Action Register'!$B:$B,"<>",'Action Register'!$G:$G,"<>Closed",'Action Register'!$G:$G,"<>Completed",'Action Register'!$G:$G,"<>Cancelled",'Action Register'!$G:$G,"<>Deferred") -> 3 | L17: =COUNTIFS('Action Register'!$K:$K,$J17,'Action Register'!$F:$F,"<"&TODAY(),'Action Register'!$B:$B,"<>",'Action Register'!$G:$G,"<>Closed",'Action Register'!$G:$G,"<>Completed",'Action Register'!$G:$G,"<>Cancelled",'Action Register'!$G:$G,"<>Deferred") -> 0 | M17: =COUNTIFS('Action Register'!$K:$K,$J17,'Action Register'!$H:$H,"Critical",'Action Register'!$G:$G,"<>Closed",'Action Register'!$G:$G,"<>Completed",'Action Register'!$G:$G,"<>Cancelled",'Action Register'!$G:$G,"<>Deferred") -> 0 | N17: =COUNTIFS('Action Register'!$K:$K,$J17,'Action Register'!$H:$H,"High",'Action Register'!$G:$G,"<>Closed",'Action Register'!$G:$G,"<>Completed",'Action Register'!$G:$G,"<>Cancelled",'Action Register'!$G:$G,"<>Deferred") -> 1 | O17: =COUNTIFS('Action Register'!$K:$K,$J17,'Action Register'!$J:$J,"High",'Action Register'!$G:$G,"<>Closed",'Action Register'!$G:$G,"<>Completed",'Action Register'!$G:$G,"<>Cancelled",'Action Register'!$G:$G,"<>Deferred") -> 1 | P17: =COUNTIFS('Action Register'!$K:$K,$J17,'Action Register'!$L:$L,"Yes",'Action Register'!$G:$G,"<>Closed",'Action Register'!$G:$G,"<>Completed",'Action Register'!$G:$G,"<>Cancelled",'Action Register'!$G:$G,"<>Deferred") -> 0
A18: Executive Summary Charts
A37: Recommended Weekly SLT Review Sequence
A38: 1. Review Critical / High Risk / Escalation items first.
A39: 2. Review ASP Go-Live and Governance & Controls as separate executive categories.
A40: 3. Confirm overdue decisions and items requiring CEO/CFO attention.
A41: 4. Review owner accountability dashboard for bottlenecks.
A42: 5. Move decisions from Decision Queue to Decision Log once made, with follow-up owner and due date.
A44: =NOW() -> 46317.028 | B44: Updated

Sheet Action Register
A1: SLT Action Register
A2: Board-ready action log with priority, risk, strategic alignment, financial impact, escalation, and ASP Go-Live visibility.
A4: SLT Item ID | B4: Item | C4: Category | D4: Owner | E4: Next Action | F4: Due Date | G4: Status | H4: Priority | I4: Flag | J4: Risk Impact | K4: Strategic Objective | L4: Escalation Required | M4: Financial Impact | N4: ASP Readiness Stream | O4: Blocker / Waiting On | P4: Notes | Q4: Date Added | R4: Last Updated | S4: SLT Immutable Key | T4: Active Record
A5: =IF($B5<>"","SLT-"&TEXT(--RIGHT($S5,4),"0000"),"") -> SLT-0001 | B5: Employee Payroll Advances | C5: Human Resources | D5: Gene | E5: Review and refine the draft Payroll Advance Policy and return via Decision Brief for approval by July 20. | F5: 46254 | G5: In Progress | H5: Medium | I5: =IF($H5="Critical","⚑",IF($H5="High","⚑","")) | J5: Medium | K5: Governance | L5: No | M5: Unknown / TBD | N5: N/A | P5: Governance fields added for SLT visibility. | Q5: 46219 | R5: 46219 | S5: SLT-K-0001 | T5: =IF($B5="","",IF(OR($G5="Completed",$G5="Cancelled",$G5="Deferred"),"INACTIVE","ACTIVE")) -> ACTIVE
A6: =IF($B6<>"","SLT-"&TEXT(--RIGHT($S6,4),"0000"),"") -> SLT-0002 | B6: Annual Wage Increase Review and Implementation Plan | C6: Compensation | D6: Gene | E6: Implement approved August increases. Manager communication materials prepared. Review December salary and pay-band alignment strategy in Q4. Item to remain open until approval is finalized and changes are communicated. | F6: 46273 | G6: Completed | H6: High | I6: =IF($H6="Critical","⚑",IF($H6="High","⚑","")) -> ⚑ | J6: Medium | K6: People & Culture | L6: Yes | M6: Unknown / TBD | N6: N/A | P6: Completed September 4, 2026. Letters have been distributed to managers for communication with employees, including 3 salaries eimployees. Sharon Jemima - letter to be provided to Sherry for delivery. Rick Wark and Carol Maia - letters to be provided to Tony to communicate. | Q6: 46219 | R6: 46226 | S6: SLT-K-0002 | T6: =IF($B6="","",IF(OR($G6="Completed",$G6="Cancelled",$G6="Deferred"),"INACTIVE","ACTIVE")) -> INACTIVE
A7: =IF($B7<>"","SLT-"&TEXT(--RIGHT($S7,4),"0000"),"") -> SLT-0003 | B7: ASP Go-Live Executive Readiness Tracker | C7: ASP Go-Live | D7: Maurizio | E7: Create consolidated readiness view covering licensing, construction, operations readiness, HR, training, ERP, capital spend, customer transition and risk register. | F7: 46227 | G7: Cancelled | H7: Low | I7: =IF($H7="Critical","⚑",IF($H7="High","⚑","")) | J7: Low | K7: ASP Go-Live | L7: Yes | M7: >$250K | N7: Operations Readiness | O7: Requires cross-functional inputs | P7: Executive workstream control for ASP Go-Live readiness. | Q7: 46219 | R7: 46219 | S7: SLT-K-0003 | T7: =IF($B7="","",IF(OR($G7="Completed",$G7="Cancelled",$G7="Deferred"),"INACTIVE","ACTIVE")) -> INACTIVE
A8: =IF($B8<>"","SLT-"&TEXT(--RIGHT($S8,4),"0000"),"") -> SLT-0004 | B8: CFO Governance & Controls Register | C8: Governance & Controls | D8: Sherry | E8: Maintain live register of DOA, contract policy, AI governance, incident management, internal audit findings, grant compliance and legal review items. | F8: 46321 | G8: In Progress | H8: Medium | I8: =IF($H8="Critical","⚑",IF($H8="High","⚑","")) | J8: Medium | K8: Governance | L8: Yes | M8: Unknown / TBD | N8: N/A | P8: CFO governance visibility for policies, internal audit, grants, legal review, and controls. | Q8: 46219 | R8: 46219 | S8: SLT-K-0004 | T8: =IF($B8="","",IF(OR($G8="Completed",$G8="Cancelled",$G8="Deferred"),"INACTIVE","ACTIVE")) -> ACTIVE
A9: =IF($B9<>"","SLT-"&TEXT(--RIGHT($S9,4),"0000"),"") -> SLT-0005 | B9: Financial Impact Classification for Open SLT Items | C9: Finance | D9: Dave | E9: Classify open SLT items by estimated financial impact and identify items requiring CFO/CEO review. | F9: 46225 | G9: Completed | H9: High | I9: =IF($H9="Critical","⚑",IF($H9="High","⚑","")) -> ⚑ | J9: High | K9: Cost Reduction | L9: Yes | M9: $50K-$250K | N9: N/A | P9: Financial materiality classification for open SLT items. | Q9: 46219 | R9: 46219 | S9: SLT-K-0005 | T9: =IF($B9="","",IF(OR($G9="Completed",$G9="Cancelled",$G9="Deferred"),"INACTIVE","ACTIVE")) -> INACTIVE
A10: =IF($B10<>"","SLT-"&TEXT(--RIGHT($S10,4),"0000"),"") -> SLT-0006 | B10: Owner Accountability Dashboard Review | C10: Governance & Controls | D10: Sandy | E10: Add owner-level summary of open, overdue and at-risk actions to improve weekly SLT accountability reporting. | F10: 46225 | G10: Completed | H10: High | I10: =IF($H10="Critical","⚑",IF($H10="High","⚑","")) -> ⚑ | J10: Medium | K10: Governance | L10: Yes | M10: Unknown / TBD | N10: N/A | P10: Dashboard control for weekly owner accountability. | Q10: 46219 | R10: 46219 | S10: SLT-K-0006 | T10: =IF($B10="","",IF(OR($G10="Completed",$G10="Cancelled",$G10="Deferred"),"INACTIVE","ACTIVE")) -> INACTIVE
A11: =IF($B11<>"","SLT-"&TEXT(--RIGHT($S11,4),"0000"),"") -> SLT-0007 | B11: ASP Gap Analysis - Ron Judge | C11: ASP Go-Live | D11: Tom | E11: Engaged Ron Judge to formalize scope of work and deliverables to perform the formal readiness and gap assessment. Continue with Practical Approach for: Equipment and maintenance support, maintenance system setup, and remains available to provide targeted support once specific gaps have been identified. | F11: 46251 | G11: Completed | H11: High | I11: =IF($H11="Critical","⚑",IF($H11="High","⚑","")) -> ⚑ | J11: High | K11: ASP Go-Live | L11: Yes | M11: Unknown / TBD | N11: Operations Readiness | P11: Options Considered: Ron Judge, Practical Approach, MNP. Ron Judge presented to SLT on August 17. Action and and ownership teams were assigned and transitioned to the weekly ASP Go-Live meetings for tracking and execution. | Q11: 46225 | R11: 46226 | S11: SLT-K-0007 | T11: =IF($B11="","",IF(OR($G11="Completed",$G11="Cancelled",$G11="Deferred"),"INACTIVE","ACTIVE")) -> INACTIVE
A12: =IF($B12<>"","SLT-"&TEXT(--RIGHT($S12,4),"0000"),"") -> SLT-0008 | B12: Develop a Performance Plan for Tatiana | C12: People & Culture | D12: Adam | E12: Performance plan complete and deliver written operational improvement plan including KPIs, milestones (30/60/90 days), and review checkpoints. Meet with Tatiana by the end of the week, October 9. | F12: 46314 | G12: In Progress | H12: Medium | I12: =IF($H12="Critical","⚑",IF($H12="High","⚑","")) | J12: Medium | K12: People & Culture | L12: No | M12: Unknown / TBD | N12: N/A | Q12: 46226 | R12: 46226 | S12: SLT-K-0008 | T12: =IF($B12="","",IF(OR($G12="Completed",$G12="Cancelled",$G12="Deferred"),"INACTIVE","ACTIVE")) -> ACTIVE
A13: =IF($B13<>"","SLT-"&TEXT(--RIGHT($S13,4),"0000"),"") -> SLT-0009 | B13: Editable Organization Charts | C13: People & Culture | D13: Gene | E13: Provide editable organization charts with open roles identified, replacing the current Canva versions to support ongoing updates and review | F13: 46230 | G13: Completed | H13: High | I13: =IF($H13="Critical","⚑",IF($H13="High","⚑","")) -> ⚑ | J13: High | K13: People & Culture | L13: Yes | M13: Unknown / TBD | N13: Operations Readiness | Q13: 46226 | R13: 46226 | S13: SLT-K-0009 | T13: =IF($B13="","",IF(OR($G13="Completed",$G13="Cancelled",$G13="Deferred"),"INACTIVE","ACTIVE")) -> INACTIVE
A14: =IF($B14<>"","SLT-"&TEXT(--RIGHT($S14,4),"0000"),"") -> SLT-0010 | B14: Company Performance Update in lieu of Town Hall | C14: People & Culture | D14: Tom | E14: 1. Issue company-wide communication with Q2 performance update. 2. Department Leads to communicate results with respective teams. Tom to discuss with HR and Sales teams. | F14: 46262 | G14: Completed | H14: Medium | I14: =IF($H14="Critical","⚑",IF($H14="High","⚑","")) | J14: Medium | K14: Internal Communication | L14: No | M14: Unknown / TBD | N14: N/A | P14: Communication went to company on September 11, 2026 | Q14: 46226 | R14: 46226 | S14: SLT-K-0010 | T14: =IF($B14="","",IF(OR($G14="Completed",$G14="Cancelled",$G14="Deferred"),"INACTIVE","ACTIVE")) -> INACTIVE
A15: =IF($B15<>"","SLT-"&TEXT(--RIGHT($S15,4),"0000"),"") -> SLT-0011 | B15: Standardizing Halal Certification Body Across AGC | C15: Risk & Compliance | D15: Tom | E15: Refer to Dec003 - on Decision Queue - Quotes obtained from CHFCA and MANA for certification of AGC facilities. Maintain the certification consistent and centralized. Recommendation is CHFCA. Tony and Sherry to hold a separate, private conversation with Dr. Imam Slimi on the certification. | F15: 46319 | G15: Gathering Info | H15: Medium | I15: =IF($H15="Critical","⚑",IF($H15="High","⚑","")) | J15: Medium | K15: Food Safety | L15: No | M15: Unknown / TBD | N15: Operations Readiness | P15: Tony and Sherry to hold a separate, private conversation with Dr. Imam Slimi on the certification. | Q15: 46226 | R15: 46226 | S15: SLT-K-0011 | T15: =IF($B15="","",IF(OR($G15="Completed",$G15="Cancelled",$G15="Deferred"),"INACTIVE","ACTIVE")) -> ACTIVE
A16: =IF($B16<>"","SLT-"&TEXT(--RIGHT($S16,4),"0000"),"") -> SLT-0012 | B16: PO Policy Rollout | C16: Governance & Controls | D16: Dave | E16: Rollout training. Full company-wide rollout of automated PO process in BC, including workflow routing and authorization controls. Practical Approach selected as vendor based on $15K quote. Rollout trainging week of October 21. | F16: 46316 | G16: In Progress | H16: Medium | I16: =IF($H16="Critical","⚑",IF($H16="High","⚑","")) | J16: Medium | K16: Governance | L16: No | M16: Unknown / TBD | N16: Operations Readiness | P16: Brought from deferred decision on May 11, 2026. Evaluated 2 vendor proposals. Sherry Crawford and Practical Approach. | Q16: 46153 | R16: 46292 | S16: SLT-K-0012 | T16: =IF($B16="","",IF(OR($G16="Completed",$G16="Cancelled",$G16="Deferred"),"INACTIVE","ACTIVE")) -> ACTIVE
A17: =IF($B17<>"","SLT-"&TEXT(--RIGHT($S17,4),"0000"),"") -> SLT-0013 | B17: Bill S-211 Compliance | C17: Governance & Controls | D17: Sherry | E17: AGC to complete the required minimal compliance reporting internally rather than engage MNP, avoiding the quoted $12.5K external cost, while remaining compliant with reporting requirements. | F17: 46322 | G17: In Progress | H17: Medium | I17: =IF($H17="Critical","⚑",IF($H17="High","⚑","")) | J17: Medium | K17: Governance | L17: No | M17: Unknown / TBD | Q17: 46244 | S17: SLT-K-0013 | T17: =IF($B17="","",IF(OR($G17="Completed",$G17="Cancelled",$G17="Deferred"),"INACTIVE","ACTIVE")) -> ACTIVE
A18: =IF($B18<>"","SLT-"&TEXT(--RIGHT($S18,4),"0000"),"") -> SLT-0014 | B18: 2027 Civic Holiday - 2027 Planning Process | C18: People & Culture | D18: Dave | E18: Gene and David to evaluate the cost and implications of introducing the Civic Holiday as a paid company holiday effective 2027 and return with a recommendation for an SLT decision. | F18: 46451 | G18: Assigned | H18: Medium | I18: =IF($H18="Critical","⚑",IF($H18="High","⚑","")) | J18: Medium | K18: People & Culture | L18: No | M18: Unknown / TBD | N18: N/A | Q18: 46244 | R18: 46246 | S18: SLT-K-0014 | T18: =IF($B18="","",IF(OR($G18="Completed",$G18="Cancelled",$G18="Deferred"),"INACTIVE","ACTIVE")) -> ACTIVE
A19: =IF($B19<>"","SLT-"&TEXT(--RIGHT($S19,4),"0000"),"") -> SLT-0015 | B19: YVF Yield Report | C19: Commercial | D19: Tom | E19: Next step – Share the 60/40 split with YVF and provide visibility into the calculation methodology for a representative item. The YVF ask – Keep penny profits whole versus percentage. To be discussed at the weekly call. Exploring a long-term pricing approach aligned with the lease agreement, including annual pricing adjustments. First draft sent to YVF (50 cent change on boneless). | F19: 46322 | G19: In Progress | H19: High | I19: =IF($H19="Critical","⚑",IF($H19="High","⚑","")) -> ⚑ | J19: High | K19: Commercial Growth | L19: No | M19: Unknown / TBD | N19: N/A | P19: Original request - 1. Confirm yield reports are being distributed to YVF stakeholders (Ryan and James). 2. Add the dollar impact of yields to YVF reports. Will support 2027 transfer price piece | Q19: 46246 | R19: 46300 | S19: SLT-K-0015 | T19: =IF($B19="","",IF(OR($G19="Completed",$G19="Cancelled",$G19="Deferred"),"INACTIVE","ACTIVE")) -> ACTIVE
A20: =IF($B20<>"","SLT-"&TEXT(--RIGHT($S20,4),"0000"),"") -> SLT-0016 | B20: Workorder Closure & Gross Profit Reporting | C20: Finance | D20: Dave | E20: (1) Effective Aug. 17, review work order closure status during daily DOR meetings to improve accountability and timely closure. (2) Effective Sept. 1, incorporate gross profit metrics into KPI reporting to enhance operational and financial performance visibility. (3) Ensure timely closure of work orders to support accurate gross profit reporting and KPI metrics. | F20: 46266 | G20: Completed | H20: High | I20: =IF($H20="Critical","⚑",IF($H20="High","⚑","")) -> ⚑ | J20: High | K20: Governance | L20: No | M20: Unknown / TBD | N20: N/A | Q20: 46246 | R20: 46246 | S20: SLT-K-0016 | T20: =IF($B20="","",IF(OR($G20="Completed",$G20="Cancelled",$G20="Deferred"),"INACTIVE","ACTIVE")) -> INACTIVE
A21: =IF($B21<>"","SLT-"&TEXT(--RIGHT($S21,4),"0000"),"") -> SLT-0017 | B21: Deloitte's Best Managed Companies | C21: Other | D21: Tony | E21: Deloitte’s Best Managed Companies — Key Milestones: 🔴 August 17 | SLT Approval of Employee Survey 🟠 August 18 | Stakeholder Sections Due Tom: Strategy Adam: Capabilities and Innovation Dave: Section delivered excluding Sherry’s input on questions. 🟡 August 20 | Extension Granted Gene: Culture and Commitment 🟢 August 24 | Launch Employee Survey 🔵 September 8 | Deloitte Lab Session (2:00pm-4:00pm) 🟢 September 23 | Submit Draft to Deloitte coaches 🔵 October 16 | Final Online Submission | F21: 46311 | G21: In Progress | H21: Medium | I21: =IF($H21="Critical","⚑",IF($H21="High","⚑","")) | J21: Low | K21: Other | L21: No | M21: Unknown / TBD | N21: N/A | Q21: 46246 | R21: 46246 | S21: SLT-K-0017 | T21: =IF($B21="","",IF(OR($G21="Completed",$G21="Cancelled",$G21="Deferred"),"INACTIVE","ACTIVE")) -> ACTIVE
A22: =IF($B22<>"","SLT-"&TEXT(--RIGHT($S22,4),"0000"),"") -> SLT-0018 | B22: Finalize Sierra QA/FSQA Role | C22: People & Culture | D22: Maurizio | E22: Job description outstanding. Maurizio to forward a draft of current role to Enid. | F22: 46251 | G22: Completed | H22: Medium | I22: =IF($H22="Critical","⚑",IF($H22="High","⚑","")) | J22: Medium | K22: People & Culture | L22: No | M22: Unknown / TBD | N22: N/A | Q22: 46246 | R22: 46246 | S22: SLT-K-0018 | T22: =IF($B22="","",IF(OR($G22="Completed",$G22="Cancelled",$G22="Deferred"),"INACTIVE","ACTIVE")) -> INACTIVE
A23: =IF($B23<>"","SLT-"&TEXT(--RIGHT($S23,4),"0000"),"") -> SLT-0019 | B23: Hiring Strategy - ASP | C23: People & Culture | D23: Maurizio | E23: Maurizio to perform additional market research on rural location premiums and potential compensation adjustments for positions based in rural areas and provide findings and recommendations at future SLT meeting. Action closed, no longer needed, replaced with Review People Plan Budget for ASP. | F23: 46265 | G23: Cancelled | H23: Low | I23: =IF($H23="Critical","⚑",IF($H23="High","⚑","")) | J23: Low | K23: People & Culture | L23: Yes | M23: Unknown / TBD | N23: Operations Readiness | S23: SLT-K-0019 | T23: =IF($B23="","",IF(OR($G23="Completed",$G23="Cancelled",$G23="Deferred"),"INACTIVE","ACTIVE")) -> INACTIVE
A24: =IF($B24<>"","SLT-"&TEXT(--RIGHT($S24,4),"0000"),"") -> SLT-0020 | B24: Grant Opportunities | C24: Governance & Controls | D24: Sherry | E24: Sherry to present the partner evaluation framework, selection criteria, historical success rates, and review of grant applications from the last 12-24 months at the next SLT meeting | F24: 46251 | G24: Completed | H24: Medium | I24: =IF($H24="Critical","⚑",IF($H24="High","⚑","")) | J24: Medium | K24: Governance | L24: No | M24: Unknown / TBD | N24: N/A | P24: Grant Opportunities – Sherry presented grant program performance, highlighting a 67% approval rate and $11.4M in funding secured. The grants application process, grant tracking methodology, and consultant selection criteria have been documented and standa | S24: SLT-K-0020 | T24: =IF($B24="","",IF(OR($G24="Completed",$G24="Cancelled",$G24="Deferred"),"INACTIVE","ACTIVE")) -> INACTIVE
A25: =IF($B25<>"","SLT-"&TEXT(--RIGHT($S25,4),"0000"),"") -> SLT-0021 | B25: Governance Policy Alignment (DOA, Incident Governance, PO Approval) | C25: Governance & Controls | D25: Sherry | E25: Presented the first draft of the AGC Enterprise Governance Framework, including delegation of authority, approval thresholds, and incident escalation requirements. Hard copy of DOA handed out at the meeting. -Distribute the updated DOA, including Tom’s tier. -Pending feedback from Dave S. | F25: 46321 | G25: In Progress | H25: Medium | I25: =IF($H25="Critical","⚑",IF($H25="High","⚑","")) | J25: Medium | K25: Governance | L25: No | M25: Unknown / TBD | N25: N/A | Q25: 46216 | S25: SLT-K-0021 | T25: =IF($B25="","",IF(OR($G25="Completed",$G25="Cancelled",$G25="Deferred"),"INACTIVE","ACTIVE")) -> ACTIVE
A26: =IF($B26<>"","SLT-"&TEXT(--RIGHT($S26,4),"0000"),"") -> SLT-0022 | B26: Division 9 Steel - Change Order | C26: Governance & Controls | D26: Colin | E26: Approximately $600K of spend has been incurred or defined, with remaining scope continuing to be assessed as CFIA requirements continue to be identified. Total costs are trending above the $800K allowance due to unidentified snow shed and additional CFIA requirements. | F26: 46321 | G26: In Progress | H26: Medium | I26: =IF($H26="Critical","⚑",IF($H26="High","⚑","")) | J26: High | K26: ASP Go-Live | L26: No | M26: $50K-$250K | N26: Capital Spend | P26: Per Colin's Decision Brief submission $410,559.82 remains available for interior alterations according to CBB. What happened to the $800K? Recall this monthly to SLT meetings until it is resolved. | Q26: 46258 | R26: 46300 | S26: SLT-K-0022 | T26: =IF($B26="","",IF(OR($G26="Completed",$G26="Cancelled",$G26="Deferred"),"INACTIVE","ACTIVE")) -> ACTIVE
A27: =IF($B27<>"","SLT-"&TEXT(--RIGHT($S27,4),"0000"),"") -> SLT-0023 | B27: Construction Site Trailer Rental | C27: Operations | D27: Colin | E27: Proceed with trailer rental arrangements. Colin to confirm trailer layout, occupancy requirements, furniture needs, and final placement location. | F27: 46293 | G27: Completed | H27: Medium | I27: =IF($H27="Critical","⚑",IF($H27="High","⚑","")) | J27: Medium | K27: ASP Go-Live | L27: No | M27: $10K-$50K | N27: Construction | S27: SLT-K-0023 | T27: =IF($B27="","",IF(OR($G27="Completed",$G27="Cancelled",$G27="Deferred"),"INACTIVE","ACTIVE")) -> INACTIVE
A28: =IF($B28<>"","SLT-"&TEXT(--RIGHT($S28,4),"0000"),"") -> SLT-0024 | B28: UWB Generator Pad Change Order | C28: ASP Go-Live | D28: Colin | E28: Obtain and share total credit amount once transformer is sold. Project remains substantially on budget against the $950K allowance, with an estimated variance of approximately $12K. Approximately 85% of the change order has been signed off, with the remaining approval expected this week, completing the contract process. | F28: 46321 | G28: In Progress | H28: Low | I28: =IF($H28="Critical","⚑",IF($H28="High","⚑","")) | J28: Low | K28: ASP Go-Live | L28: No | M28: >$250K | N28: Capital Spend | P28: Recall this monthly to SLT meetings. Obtain and share total credit amount once transformer is sold. | Q28: 46258 | S28: SLT-K-0024 | T28: =IF($B28="","",IF(OR($G28="Completed",$G28="Cancelled",$G28="Deferred"),"INACTIVE","ACTIVE")) -> ACTIVE
A29: =IF($B29<>"","SLT-"&TEXT(--RIGHT($S29,4),"0000"),"") -> SLT-0025 | B29: Chilled Water System Change Order (OCO-008) | C29: ASP Go-Live | D29: Colin | E29: Final approval remains contingent on Coldbox meeting the agreed occupancy date (Dec 12); Coldbox confirmed verbally, but not yet formally confirmed in wirting. Negotiated change order value has been reduced from approximately $406K to $200K. | F29: 46321 | G29: Assigned | H29: High | I29: =IF($H29="Critical","⚑",IF($H29="High","⚑","")) -> ⚑ | J29: High | K29: ASP Go-Live | L29: No | M29: >$250K | N29: Operations Readiness | P29: Leadership also maintained that responsibility for the omission rests with Coldbox and should not be transferred to its subcontractor. | Q29: 46258 | S29: SLT-K-0025 | T29: =IF($B29="","",IF(OR($G29="Completed",$G29="Cancelled",$G29="Deferred"),"INACTIVE","ACTIVE")) -> ACTIVE
A30: =IF($B30<>"","SLT-"&TEXT(--RIGHT($S30,4),"0000"),"") -> SLT-0026 | B30: Team Visit to Baader Facility | C30: ASP Go-Live | D30: Colin | E30: Engage Baader and identify suitable North American facility tour options. Confirm recommended attendees (Adam, Tuhin, Maintenance Manager, Alexander). Evaluate U.S. and Newfoundland sites and return with a proposed visit plan. | F30: 46321 | G30: Assigned | H30: Medium | I30: =IF($H30="Critical","⚑",IF($H30="High","⚑","")) | J30: Medium | K30: ASP Go-Live | L30: No | M30: Unknown / TBD | N30: Operations Readiness | Q30: 46258 | S30: SLT-K-0026 | T30: =IF($B30="","",IF(OR($G30="Completed",$G30="Cancelled",$G30="Deferred"),"INACTIVE","ACTIVE")) -> ACTIVE
A31: =IF($B31<>"","SLT-"&TEXT(--RIGHT($S31,4),"0000"),"") -> SLT-0027 | B31: Coaching on Interviewing Conduct | C31: People & Culture | D31: Gene | E31: Coach Martin on structured interviewing and candidate evaluation process due to concerns raised regarding interview conduct. Arrange for a meeting with Martin and document conversation (Pending). | F31: 46300 | G31: Completed | H31: Medium | I31: =IF($H31="Critical","⚑",IF($H31="High","⚑","")) | J31: Medium | K31: People & Culture | L31: No | M31: Unknown / TBD | N31: N/A | Q31: 46251 | R31: 46289 | S31: SLT-K-0027 | T31: =IF($B31="","",IF(OR($G31="Completed",$G31="Cancelled",$G31="Deferred"),"INACTIVE","ACTIVE")) -> INACTIVE
A32: =IF($B32<>"","SLT-"&TEXT(--RIGHT($S32,4),"0000"),"") -> SLT-0028 | B32: Add Peter Post as Plant Manager to Interview Process | C32: People & Culture | D32: Maurizio | E32: Include Peter Post in maintenance interviews to provide an additional perspective. | F32: 46258 | G32: Completed | H32: Medium | I32: =IF($H32="Critical","⚑",IF($H32="High","⚑","")) | J32: Medium | K32: People & Culture | L32: No | M32: Unknown / TBD | N32: N/A | S32: SLT-K-0028 | T32: =IF($B32="","",IF(OR($G32="Completed",$G32="Cancelled",$G32="Deferred"),"INACTIVE","ACTIVE")) -> INACTIVE
A33: =IF($B33<>"","SLT-"&TEXT(--RIGHT($S33,4),"0000"),"") -> SLT-0029 | B33: Workorder Closure - Sierra | C33: Finance | D33: Dave | E33: Sierra work order closures to be transitioned to finance. | F33: 46310 | G33: In Progress | H33: Medium | J33: Medium | K33: Governance | L33: No | M33: Unknown / TBD | N33: N/A | Q33: 46230 | S33: SLT-K-0029 | T33: =IF($B33="","",IF(OR($G33="Completed",$G33="Cancelled",$G33="Deferred"),"INACTIVE","ACTIVE")) -> ACTIVE
A34: =IF($B34<>"","SLT-"&TEXT(--RIGHT($S34,4),"0000"),"") -> SLT-0030 | B34: Prepare and Share the ASP Freezer Inventory Report | C34: Sales | D34: Tony | E34: Generate and share a current ASP freezer inventory report to assess inventory levels, customer demand opportunities, and potential impacts of holding versus discounting excess large-bird inventory. Softer summer market resulted in additional volumes of extra-large and other size birds being placed into the freezer at ASP | F34: 46279 | G34: Completed | H34: Medium | J34: Medium | K34: Governance | L34: No | M34: >$250K | P34: David includes this on the weekly KPI report | Q34: 46258 | R34: 46292 | S34: SLT-K-0030 | T34: =IF($B34="","",IF(OR($G34="Completed",$G34="Cancelled",$G34="Deferred"),"INACTIVE","ACTIVE")) -> INACTIVE
A35: =IF($B35<>"","SLT-"&TEXT(--RIGHT($S35,4),"0000"),"") -> SLT-0031 | B35: Hiring Strategy – Timelines for Org Chart Positions | C35: Human Resources | D35: Maurizio | E35: SLT agreed that future staffing updates should include both the organizational structure and recruitment timelines to better assess hiring delays, associated risks, and potential financial impacts. | F35: 46251 | G35: Completed | H35: High | I35: =IF($H35="Critical","⚑",IF($H35="High","⚑","")) -> ⚑ | J35: High | K35: ASP Go-Live | L35: No | M35: Unknown / TBD | N35: HR Readiness | P35: Incorporated by August 17 | Q35: 46244 | R35: 46251 | S35: SLT-K-0031 | T35: =IF($B35="","",IF(OR($G35="Completed",$G35="Cancelled",$G35="Deferred"),"INACTIVE","ACTIVE")) -> INACTIVE
A36: =IF($B36<>"","SLT-"&TEXT(--RIGHT($S36,4),"0000"),"") -> SLT-0032 | B36: Add Peter Post as Plant Manager to Interview Process (at Sierra) | C36: Human Resources | D36: Maurizio | E36: Include Peter Post in maintenance interviews to provide an additional perspective. | F36: 46258 | G36: Completed | H36: Medium | I36: =IF($H36="Critical","⚑",IF($H36="High","⚑","")) | J36: Medium | K36: Sierra Growth | L36: No | M36: Unknown / TBD | N36: N/A | P36: Maurizio spoke to Peter and has been including him. This was open as a result of Martin - coaching action. | Q36: 46251 | R36: 46258 | S36: SLT-K-0032 | T36: =IF($B36="","",IF(OR($G36="Completed",$G36="Cancelled",$G36="Deferred"),"INACTIVE","ACTIVE")) -> INACTIVE
A37: =IF($B37<>"","SLT-"&TEXT(--RIGHT($S37,4),"0000"),"") -> SLT-0033 | B37: Employee Launch Survey | C37: People & Culture | E37: Launch the employee survey across the company | F37: 46287 | G37: Completed | H37: High | I37: =IF($H37="Critical","⚑",IF($H37="High","⚑","")) -> ⚑ | J37: High | K37: People & Culture | L37: No | P37: Employee Survey Launched Sept 23 - email sent out | Q37: 46265 | R37: 46288 | S37: SLT-K-0033 | T37: =IF($B37="","",IF(OR($G37="Completed",$G37="Cancelled",$G37="Deferred"),"INACTIVE","ACTIVE")) -> INACTIVE
A38: =IF($B38<>"","SLT-"&TEXT(--RIGHT($S38,4),"0000"),"") -> SLT-0034 | B38: Bonus Year-To-Date Communication | D38: Dave | E38: 1. Dave, Tom and Gene to meet and confirm bonus calculator, including a floor and ceiling payout, for bonus program communication. 2. Finalize manager specific bonus guidance to be sent out separate from Q2 company-wide update. Next step: Review at the Finance meeting on Thursday, September 3. Allocate time in the September strategy sessions to discuss compensation framework and bonus structure discussion. | F38: 46269 | G38: Completed | H38: High | I38: =IF($H38="Critical","⚑",IF($H38="High","⚑","")) -> ⚑ | J38: High | K38: People & Culture | L38: No | P38: August 27 - Dave communicated the file and names to SLT. | Q38: 46265 | R38: 46280 | S38: SLT-K-0034 | T38: =IF($B38="","",IF(OR($G38="Completed",$G38="Cancelled",$G38="Deferred"),"INACTIVE","ACTIVE")) -> INACTIVE
A39: =IF($B39<>"","SLT-"&TEXT(--RIGHT($S39,4),"0000"),"") -> SLT-0035 | B39: Review December salary and pay-band alignment strategy in Q4 | C39: Human Resources | D39: Gene | E39: Review December salary and pay-band alignment strategy in Q4 Develop and finalize 2027 salary review and pay band process. Meet to align performance review timing, salary recommendations, budget assumptions, and January 1 implementation approach for 2027. Gene to simplify performance review template. Gene and Dave to meet and return to SLT. Item to remain open until approval is finalized and changes are communicated. | F39: 46308 | G39: In Progress | H39: High | I39: =IF($H39="Critical","⚑",IF($H39="High","⚑","")) -> ⚑ | J39: Medium | K39: People & Culture | L39: No | M39: $10K-$50K | N39: N/A | Q39: 46223 | R39: 46292 | S39: SLT-K-0035 | T39: =IF($B39="","",IF(OR($G39="Completed",$G39="Cancelled",$G39="Deferred"),"INACTIVE","ACTIVE")) -> ACTIVE
A40: =IF($B40<>"","SLT-"&TEXT(--RIGHT($S40,4),"0000"),"") -> SLT-0036 | B40: RTRI Funding Application - Reapplication | C40: Finance | D40: Dave | E40: Prepare and submit the application for up to $2 million in non-repayable funding and support the reassessment of the AQM application. Team to include Dave, Adam, Colin, Tom. Target completion date - 2 weeks Update: Application process formally initiated. Colin and team met with Grant Synergy to begin preparing the funding application, with a target to complete within two weeks. Dave performing assessment. | F40: 46307 | G40: In Progress | H40: High | I40: =IF($H40="Critical","⚑",IF($H40="High","⚑","")) -> ⚑ | J40: Medium | K40: Cost Reduction | L40: No | M40: >$250K | Q40: 46286 | R40: 46292 | S40: SLT-K-0036 | T40: =IF($B40="","",IF(OR($G40="Completed",$G40="Cancelled",$G40="Deferred"),"INACTIVE","ACTIVE")) -> ACTIVE
A41: =IF($B41<>"","SLT-"&TEXT(--RIGHT($S41,4),"0000"),"") -> SLT-0037 | B41: TRQ Application & Workback Schedule | C41: Finance | D41: Dave | E41: Develop and document a formal SOP for the TRQ application process (Harsha to complete and present SOP). Create a workback schedule to include the SLT review 2 weeks prior to submission. | F41: 46296 | G41: Completed | H41: Medium | I41: =IF($H41="Critical","⚑",IF($H41="High","⚑","")) | J41: Medium | K41: Other | L41: No | P41: Per Dave, Harsha working on SOP and Dave to bring up at the Finance meeting the week of Sept 28. | Q41: 46286 | R41: 46292 | S41: SLT-K-0037 | T41: =IF($B41="","",IF(OR($G41="Completed",$G41="Cancelled",$G41="Deferred"),"INACTIVE","ACTIVE")) -> INACTIVE
A42: =IF($B42<>"","SLT-"&TEXT(--RIGHT($S42,4),"0000"),"") -> SLT-0038 | B42: TRQ Dates - Add to SLT Calendar | C42: Other | D42: Sandy | E42: Update the SLT calendar with TRQ application deadlines. | F42: 46296 | G42: Completed | H42: High | I42: =IF($H42="Critical","⚑",IF($H42="High","⚑","")) -> ⚑ | J42: Medium | K42: Internal Communication | L42: No | Q42: 46286 | R42: 46292 | S42: SLT-K-0038 | T42: =IF($B42="","",IF(OR($G42="Completed",$G42="Cancelled",$G42="Deferred"),"INACTIVE","ACTIVE")) -> INACTIVE
A43: =IF($B43<>"","SLT-"&TEXT(--RIGHT($S43,4),"0000"),"") -> SLT-0039 | B43: Lamex - Complete & Submit Product Marketing Materials | C43: Commercial | D43: Tom | E43: Complete and submit product marketing materials (videos, photos, measurements, and specifications) to Lamex to facilitate product review and support future export market opportunities. Andrew Lash managing client. | F43: 46293 | G43: Completed | H43: Medium | I43: =IF($H43="Critical","⚑",IF($H43="High","⚑","")) | J43: Medium | K43: Commercial Growth | L43: No | Q43: 46286 | R43: 46292 | S43: SLT-K-0039 | T43: =IF($B43="","",IF(OR($G43="Completed",$G43="Cancelled",$G43="Deferred"),"INACTIVE","ACTIVE")) -> INACTIVE
A44: =IF($B44<>"","SLT-"&TEXT(--RIGHT($S44,4),"0000"),"") -> SLT-0040 | B44: Sysco Volume Decline | C44: Finance | D44: Dave | E44: Review Sysco volume decline and identify root cause of reduced sales performance. Mark as completed - refer to item SLT-0041 (Quarterly Sysco Volume Accountability) | F44: 46300 | G44: Completed | H44: Medium | I44: =IF($H44="Critical","⚑",IF($H44="High","⚑","")) | J44: Medium | K44: Commercial Growth | L44: No | Q44: 46286 | R44: 46292 | S44: SLT-K-0040 | T44: =IF($B44="","",IF(OR($G44="Completed",$G44="Cancelled",$G44="Deferred"),"INACTIVE","ACTIVE")) -> INACTIVE
A45: =IF($B45<>"","SLT-"&TEXT(--RIGHT($S45,4),"0000"),"") -> SLT-0041 | B45: Quarterly Sysco Volume Accountability | C45: Commercial | D45: Tom | E45: To reinstate the Quarterly volume tracking for Sysco/Popeyes and hold client accountable. Update: Tom is participating in ongoing meetings with Jason to review volume forecasts and actual performance. Action item can be closed; volume performance will be shared with the team monthly at the Thursday Finance meeting. Note: David and Enid track it and update it weekly on an Excel file. Move item to Finance meeting, once per month. Add to the Agenda. | F45: 46331 | G45: Assigned | H45: Medium | I45: =IF($H45="Critical","⚑",IF($H45="High","⚑","")) | J45: Medium | K45: Commercial Growth | L45: No | Q45: 46286 | R45: 46292 | S45: SLT-K-0041 | T45: =IF($B45="","",IF(OR($G45="Completed",$G45="Cancelled",$G45="Deferred"),"INACTIVE","ACTIVE")) -> ACTIVE
A46: =IF($B46<>"","SLT-"&TEXT(--RIGHT($S46,4),"0000"),"") -> SLT-0042 | B46: $700K Risk - Maple Leaf Insurance Claim Risk | C46: Risk & Compliance | D46: Dave | E46: Maple Leaf Claim – Request Meeting If no substantive response received week of October 5, request a face-to-face meeting, scheduled about two weeks out. Insurance claim remains under review and has not yet been approved. Status/Risk: The amount remains recorded in the balance sheet. If unresolved by year-end, it will need to be brought to EBITDA. | F46: 46321 | G46: In Progress | H46: High | I46: =IF($H46="Critical","⚑",IF($H46="High","⚑","")) -> ⚑ | J46: High | K46: Other | L46: Yes | M46: >$250K | R46: 46293 | S46: SLT-K-0042 | T46: =IF($B46="","",IF(OR($G46="Completed",$G46="Cancelled",$G46="Deferred"),"INACTIVE","ACTIVE")) -> ACTIVE
A47: =IF($B47<>"","SLT-"&TEXT(--RIGHT($S47,4),"0000"),"") -> SLT-0043 | B47: $200K - Inventory issue from 2025 year-end | C47: Other | D47: Dave | E47: Remaining ~$90K of $200K has been identified and is planned for write-off in September, along with related month-end adjustments and invoice matching. | F47: 46321 | G47: In Progress | H47: High | I47: =IF($H47="Critical","⚑",IF($H47="High","⚑","")) -> ⚑ | J47: High | K47: Other | L47: No | M47: $50K-$250K | P47: Resolve and record the $200K inventory variance from FY2025 year-end | R47: 46300 | S47: SLT-K-0043 | T47: =IF($B47="","",IF(OR($G47="Completed",$G47="Cancelled",$G47="Deferred"),"INACTIVE","ACTIVE")) -> ACTIVE
A48: =IF($B48<>"","SLT-"&TEXT(--RIGHT($S48,4),"0000"),"") -> SLT-0044 | B48: DSI Machine (Camera) Root Cause Analysis ($80K value equipment) | C48: Operations | D48: Adam | E48: Tatiana to complete Root Cause Analysis / Corrective Actions | F48: 46321 | G48: In Progress | H48: Medium | I48: =IF($H48="Critical","⚑",IF($H48="High","⚑","")) | J48: Medium | K48: Cost Reduction | L48: Yes | M48: $50K-$250K | S48: SLT-K-0044 | T48: =IF($B48="","",IF(OR($G48="Completed",$G48="Cancelled",$G48="Deferred"),"INACTIVE","ACTIVE")) -> ACTIVE
A49: =IF($B49<>"","SLT-"&TEXT(--RIGHT($S49,4),"0000"),"") -> SLT-0045 | B49: ASP Generator | C49: Operations | D49: Adam | E49: Address Issues | F49: 46321 | H49: Medium | I49: =IF($H49="Critical","⚑",IF($H49="High","⚑","")) | J49: Medium | S49: SLT-K-0045 | T49: =IF($B49="","",IF(OR($G49="Completed",$G49="Cancelled",$G49="Deferred"),"INACTIVE","ACTIVE")) -> ACTIVE
A50: =IF($B50<>"","SLT-"&TEXT(--RIGHT($S50,4),"0000"),"") -> SLT-0046 | B50: Inventory Levels / Inventory Carrying Costs | C50: Operations | D50: Tom | E50: To address elevated inventory levels and associated carrying costs, a temporary $0.35/kg surcharge was implemented on Maple Leaf tempering orders and will be reviewed as inventory levels improve. Cost has been added. | F50: 46300 | G50: Completed | H50: Medium | I50: =IF($H50="Critical","⚑",IF($H50="High","⚑","")) | J50: Medium | K50: Cost Reduction | L50: No | Q50: 46293 | R50: 46300 | S50: SLT-K-0046 | T50: =IF($B50="","",IF(OR($G50="Completed",$G50="Cancelled",$G50="Deferred"),"INACTIVE","ACTIVE")) -> INACTIVE
A51: =IF($B51<>"","SLT-"&TEXT(--RIGHT($S51,4),"0000"),"") -> SLT-0047 | B51: Customer Invoice Pricing Discrepancies - Assess Scope and Impact | C51: Finance | D51: Dave | E51: Update: Steve provided an analysis. Mansi has been retrained on order of operations, and a manual check from Finance has been built into process. Issue occurs when volume changes from initial PO to final, specific steps and sequence is to be taken. The order was changed creating issue. This issue is specific to YVF. ***** Sept 28 - Conduct a review of customer invoice pricing discrepancies to determine scope, root cause, timing, and financial impact, and implement enhanced invoice verification controls to prevent recurrence. Continue manual verification process in the meantime. | F51: 46300 | G51: Completed | H51: High | I51: =IF($H51="Critical","⚑",IF($H51="High","⚑","")) -> ⚑ | J51: High | K51: Other | L51: No | M51: Unknown / TBD | P51: Note: Initial discrepancies identified in YVF and London Foods accounts; review underway to assess broader exposure. | Q51: 46293 | R51: 46300 | S51: SLT-K-0047 | T51: =IF($B51="","",IF(OR($G51="Completed",$G51="Cancelled",$G51="Deferred"),"INACTIVE","ACTIVE")) -> INACTIVE
A52: =IF($B52<>"","SLT-"&TEXT(--RIGHT($S52,4),"0000"),"") -> SLT-0048 | B52: Sierra Reserved Parking Policy | C52: Sierra | D52: Gene | E52: Develop and implement a reserved parking policy and procedures for the reserved parking spaces at Sierra. | F52: 46310 | G52: In Progress | H52: Low | I52: =IF($H52="Critical","⚑",IF($H52="High","⚑","")) | J52: Low | K52: People & Culture | L52: No | M52: Unknown / TBD | Q52: 46230 | R52: 46300 | S52: SLT-K-0048 | T52: =IF($B52="","",IF(OR($G52="Completed",$G52="Cancelled",$G52="Deferred"),"INACTIVE","ACTIVE")) -> ACTIVE
A53: =IF($B53<>"","SLT-"&TEXT(--RIGHT($S53,4),"0000"),"") -> SLT-0049 | B53: Talent Acquisition Resourcing Strategy | C53: Human Resources | D53: Maurizio | E53: Complete a comparative assessment of internal talent acquisition capability versus external agency support, including hiring requirements, costs, timing, and ROI, and return with a recommendation for decision. | F53: 46321 | G53: Waiting on Information | H53: Medium | I53: =IF($H53="Critical","⚑",IF($H53="High","⚑","")) | J53: Medium | K53: People & Culture | L53: No | M53: $50K-$250K | N53: HR Readiness | O53: Waiting on Maurizio to provide information, cost analysis, option A & B | Q53: 46293 | R53: 46300 | S53: SLT-K-0049 | T53: =IF($B53="","",IF(OR($G53="Completed",$G53="Cancelled",$G53="Deferred"),"INACTIVE","ACTIVE")) -> ACTIVE
A54: =IF($B54<>"","SLT-"&TEXT(--RIGHT($S54,4),"0000"),"") -> SLT-0050 | B54: Plant Manager Weekly Operational Meetings | C54: Operations | D54: Adam | E54: Define the metrics, data sources, and reporting expectations for Plant Manager participation in weekly operational meetings (to include FSQA, Operations and SLT). Target implementation: end of October. | F54: 46321 | G54: Assigned | H54: Medium | I54: =IF($H54="Critical","⚑",IF($H54="High","⚑","")) | J54: Medium | K54: Other | L54: No | M54: Unknown / TBD | Q54: 46286 | R54: 46321 | S54: SLT-K-0050 | T54: =IF($B54="","",IF(OR($G54="Completed",$G54="Cancelled",$G54="Deferred"),"INACTIVE","ACTIVE")) -> ACTIVE
A55: =IF($B55<>"","SLT-"&TEXT(--RIGHT($S55,4),"0000"),"") -> SLT-0051 | B55: Customer Invoice Pricing Discrepancies - London Drugs | C55: Finance | D55: Dave | E55: Confirm the pricing issue with London was human error. Follow up required. | F55: 46311 | G55: In Progress | H55: High | I55: =IF($H55="Critical","⚑",IF($H55="High","⚑","")) -> ⚑ | J55: High | K55: Other | L55: No | M55: Unknown / TBD | Q55: 46301 | R55: 46307 | S55: SLT-K-0051 | T55: =IF($B55="","",IF(OR($G55="Completed",$G55="Cancelled",$G55="Deferred"),"INACTIVE","ACTIVE")) -> ACTIVE
A56: =IF($B56<>"","SLT-"&TEXT(--RIGHT($S56,4),"0000"),"") -> SLT-0052 | B56: TRQ Application & Workback Schedule | C56: Finance | D56: Dave | E56: Develop and document a formal SOP for the TRQ application process. Create a workback schedule (Harsha) to include the SLT review 2 weeks prior to submission. Due Oct 1 - Finance Meeting | F56: 46296 | G56: Completed | H56: Medium | I56: =IF($H56="Critical","⚑",IF($H56="High","⚑","")) | J56: Medium | K56: Governance | L56: No | M56: Unknown / TBD | Q56: 46286 | R56: 46296 | S56: SLT-K-0052 | T56: =IF($B56="","",IF(OR($G56="Completed",$G56="Cancelled",$G56="Deferred"),"INACTIVE","ACTIVE")) -> INACTIVE
A57: =IF($B57<>"","SLT-"&TEXT(--RIGHT($S57,4),"0000"),"") -> SLT-0053 | B57: Analysis of Quota for 2027 – Impact of Redirecting Quota from Popeyes to Alternative Channels | C57: Commercial | D57: Tom | E57: Perform analysis to evaluate the financial impact of reallocating quota from Popeyes to alternative channels (e.g. Loblaws feature programs or other customers). Assess contribution margin, capacity utilization, white meat optimization, and overall profitability to determine the highest-value use of quota for 2027 planning. Ongoing | F57: 46377 | G57: Visibility Only | H57: Medium | I57: =IF($H57="Critical","⚑",IF($H57="High","⚑","")) | J57: Medium | K57: Commercial Growth | L57: No | M57: Unknown / TBD | Q57: 46265 | R57: 46307 | S57: SLT-K-0053 | T57: =IF($B57="","",IF(OR($G57="Completed",$G57="Cancelled",$G57="Deferred"),"INACTIVE","ACTIVE")) -> ACTIVE
A58: =IF($B58<>"","SLT-"&TEXT(--RIGHT($S58,4),"0000"),"") -> SLT-0054 | B58: Vacation and Blackout Period Planning | C58: Human Resources | D58: Gene | E58: Circulate employee vacation balances and identify employees with significant unused vacation that may impact year-end operations | F58: 46304 | G58: In Progress | H58: High | I58: =IF($H58="Critical","⚑",IF($H58="High","⚑","")) -> ⚑ | J58: Medium | K58: People & Culture | L58: No | M58: Unknown / TBD | Q58: 46300 | R58: 46300 | S58: SLT-K-0054 | T58: =IF($B58="","",IF(OR($G58="Completed",$G58="Cancelled",$G58="Deferred"),"INACTIVE","ACTIVE")) -> ACTIVE
A59: =IF($B59<>"","SLT-"&TEXT(--RIGHT($S59,4),"0000"),"") -> SLT-0055 | B59: Farmer Intake Process & Ownership | C59: ASP Go-Live | D59: Tom | E59: Ali to become the central coordinator for the farmer intake process. | F59: 46321 | G59: Assigned | H59: Medium | I59: =IF($H59="Critical","⚑",IF($H59="High","⚑","")) | J59: Medium | K59: ASP Go-Live | L59: No | M59: Unknown / TBD | Q59: 46300 | R59: 46307 | S59: SLT-K-0055 | T59: =IF($B59="","",IF(OR($G59="Completed",$G59="Cancelled",$G59="Deferred"),"INACTIVE","ACTIVE")) -> ACTIVE
A60: =IF($B60<>"","SLT-"&TEXT(--RIGHT($S60,4),"0000"),"") | I60: =IF($H60="Critical","⚑",IF($H60="High","⚑","")) | S60: SLT-K-0056 | T60: =IF($B60="","",IF(OR($G60="Completed",$G60="Cancelled",$G60="Deferred"),"INACTIVE","ACTIVE"))
A61: =IF($B61<>"","SLT-"&TEXT(--RIGHT($S61,4),"0000"),"") | I61: =IF($H61="Critical","⚑",IF($H61="High","⚑","")) | S61: SLT-K-0057 | T61: =IF($B61="","",IF(OR($G61="Completed",$G61="Cancelled",$G61="Deferred"),"INACTIVE","ACTIVE"))
A62: =IF($B62<>"","SLT-"&TEXT(--RIGHT($S62,4),"0000"),"") | I62: =IF($H62="Critical","⚑",IF($H62="High","⚑","")) | S62: SLT-K-0058 | T62: =IF($B62="","",IF(OR($G62="Completed",$G62="Cancelled",$G62="Deferred"),"INACTIVE","ACTIVE"))
A63: =IF($B63<>"","SLT-"&TEXT(--RIGHT($S63,4),"0000"),"") | I63: =IF($H63="Critical","⚑",IF($H63="High","⚑","")) | S63: SLT-K-0059 | T63: =IF($B63="","",IF(OR($G63="Completed",$G63="Cancelled",$G63="Deferred"),"INACTIVE","ACTIVE"))
A64: =IF($B64<>"","SLT-"&TEXT(--RIGHT($S64,4),"0000"),"") | I64: =IF($H64="Critical","⚑",IF($H64="High","⚑","")) | S64: SLT-K-0060 | T64: =IF($B64="","",IF(OR($G64="Completed",$G64="Cancelled",$G64="Deferred"),"INACTIVE","ACTIVE"))
A65: =IF($B65<>"","SLT-"&TEXT(--RIGHT($S65,4),"0000"),"") | I65: =IF($H65="Critical","⚑",IF($H65="High","⚑","")) | S65: SLT-K-0061 | T65: =IF($B65="","",IF(OR($G65="Completed",$G65="Cancelled",$G65="Deferred"),"INACTIVE","ACTIVE"))
A66: =IF($B66<>"","SLT-"&TEXT(--RIGHT($S66,4),"0000"),"") | I66: =IF($H66="Critical","⚑",IF($H66="High","⚑","")) | S66: SLT-K-0062 | T66: =IF($B66="","",IF(OR($G66="Completed",$G66="Cancelled",$G66="Deferred"),"INACTIVE","ACTIVE"))
A67: =IF($B67<>"","SLT-"&TEXT(--RIGHT($S67,4),"0000"),"") | I67: =IF($H67="Critical","⚑",IF($H67="High","⚑","")) | S67: SLT-K-0063 | T67: =IF($B67="","",IF(OR($G67="Completed",$G67="Cancelled",$G67="Deferred"),"INACTIVE","ACTIVE"))
A68: =IF($B68<>"","SLT-"&TEXT(--RIGHT($S68,4),"0000"),"") | I68: =IF($H68="Critical","⚑",IF($H68="High","⚑","")) | S68: SLT-K-0064 | T68: =IF($B68="","",IF(OR($G68="Completed",$G68="Cancelled",$G68="Deferred"),"INACTIVE","ACTIVE"))
A69: =IF($B69<>"","SLT-"&TEXT(--RIGHT($S69,4),"0000"),"") | I69: =IF($H69="Critical","⚑",IF($H69="High","⚑","")) | S69: SLT-K-0065 | T69: =IF($B69="","",IF(OR($G69="Completed",$G69="Cancelled",$G69="Deferred"),"INACTIVE","ACTIVE"))
A70: =IF($B70<>"","SLT-"&TEXT(--RIGHT($S70,4),"0000"),"") | I70: =IF($H70="Critical","⚑",IF($H70="High","⚑","")) | S70: SLT-K-0066 | T70: =IF($B70="","",IF(OR($G70="Completed",$G70="Cancelled",$G70="Deferred"),"INACTIVE","ACTIVE"))
A71: =IF($B71<>"","SLT-"&TEXT(--RIGHT($S71,4),"0000"),"") | I71: =IF($H71="Critical","⚑",IF($H71="High","⚑","")) | S71: SLT-K-0067 | T71: =IF($B71="","",IF(OR($G71="Completed",$G71="Cancelled",$G71="Deferred"),"INACTIVE","ACTIVE"))
... A104: =IF($B104<>"","SLT-"&TEXT(--RIGHT($S104,4),"0000"),"") | I104: =IF($H104="Critical","⚑",IF($H104="High","⚑","")) | S104: SLT-K-0100 | T104: =IF($B104="","",IF(OR($G104="Completed",$G104="Cancelled",$G104="Deferred"),"INACTIVE","ACTIVE"))

Sheet Decision Queue
A1: Decision Queue
A2: Pending decisions awaiting recommendation, approval, alignment, or executive direction.
A3: NEW ITEM: copy the fixed value shown as Next Queue ID on Lists & Controls into Decision ID. ARCHIVE: copy columns A:AN for the completed decision and paste them into the next blank Decision Register row, then clear the Queue record.
A4: Decision ID | B4: Decision Required | C4: Workstream | D4: Assigned To | E4: Decision Deadline | F4: Recommendation | G4: Status | H4: Decision Type | I4: CEO/CFO Attention | J4: Financial Impact | K4: Risk Impact | L4: Strategic Objective | M4: Decision Date | N4: Further Action Required | O4: Context / Input Required | P4: Owned By | Q4: Requested By | R4: Date Raised | S4: Delay Impact / Risk | T4: Blocker / Waiting On | U4: Notes | V4: Queue Immutable Key | W4: Active Record | X4: Decision Log ID | Y4: Source Decision ID | Z4: Decision Summary | AA4: Decision Maker | AB4: Next Action | AC4: Original Issue | AD4: Rationale | AE4: Follow-up Status | AF4: Requester | AG4: Due Date | AH4: Logged Date | AI4: Decision Log Immutable Key | AJ4: Queue Source Key | AK4: Parent Decision ID | AL4: Consistency Check | AM4: ID Origin | AN4: ID Check
A5: DEC-0001 | B5: Confirm SLT tracker governance fields and dashboard structure | C5: Governance | D5: Sandy | E5: 46225 | F5: Adopt enhanced tracker with priority, risk, strategic alignment, financial impact and escalation fields. | G5: Completed | H5: Governance Decision | I5: CEO & CFO | J5: Unknown / TBD | K5: Medium | L5: Governance | N5: Yes | O5: Agree which fields are mandatory for weekly SLT review. | P5: Sandy | Q5: Sherry | R5: 46219 | S5: Without a standard data model, tracker may remain administrative rather than decision-focused. | U5: Proposed enhancement from CFO review. | V5: DECQ-K-0001 | W5: =IF($B5="","",IF(OR($G5="Completed",$G5="Cancelled"),"INACTIVE","ACTIVE")) -> INACTIVE | AM5: Queue-issued | AN5: =IF($A5="","",IF(COUNTIF('Decision Queue'!$A$5:$A$204,$A5)+COUNTIF('Decision Register'!$A$5:$A$304,$A5)>1,"DUPLICATE ID","OK")) -> OK
A6: DEC-0002 | B6: Confirm separate ASP Go-Live executive section | C6: ASP Go-Live | D6: Maurizio | E6: 46227 | F6: Track ASP as a separate executive workstream with readiness sub-streams rather than a generic Projects category. | G6: Deferred | H6: Strategic Decision | I6: CEO & CFO | J6: >$250K | K6: High | L6: ASP Go-Live | N6: Yes | O6: Confirm owner and weekly reporting cadence. | P6: Maurizio | Q6: Sherry | R6: 46219 | S6: ASP risk may be diluted if tracked only as a generic project. | U6: Recommended due to ASP scale and governance visibility needs. | V6: DECQ-K-0002 | W6: =IF($B6="","",IF(OR($G6="Completed",$G6="Cancelled"),"INACTIVE","ACTIVE")) -> ACTIVE | AM6: Queue-issued | AN6: =IF($A6="","",IF(COUNTIF('Decision Queue'!$A$5:$A$204,$A6)+COUNTIF('Decision Register'!$A$5:$A$304,$A6)>1,"DUPLICATE ID","OK")) -> OK
A7: DEC-0003 | B7: Standardize Halal Certification Body Across AGC | C7: Risk & Compliance | D7: Tom | E7: 46251 | F7: Note: Tony & Sherry to hold a separate, private conversaion with Dr. Imam Slimi on certification. Establish CHFCA as the primary corporate Halal certification body for future Halal certification activities across AQM, ASP and SCF. Existing customer or commercial requirements requiring alternative certification bodies would continue where necessary. | G7: Assigned | H7: Approval Required | I7: SLT | J7: Unknown / TBD | K7: Medium | L7: Food Safety | N7: Yes | O7: Gather pricing and information first. Follow up with Troy Warren regarding export-market certification requirements and recognized bodies. | P7: Tom | Q7: Tom | R7: 46223 | S7: Multiple certification bodies increase administrative effort, create different audit and documentation requirements, and limit standardization. | V7: DECQ-K-0003 | W7: =IF($B7="","",IF(OR($G7="Completed",$G7="Cancelled"),"INACTIVE","ACTIVE")) -> ACTIVE | AM7: Queue-issued | AN7: =IF($A7="","",IF(COUNTIF('Decision Queue'!$A$5:$A$204,$A7)+COUNTIF('Decision Register'!$A$5:$A$304,$A7)>1,"DUPLICATE ID","OK")) -> OK
A8: DEC-0004 | B8: 2027 Civic Holiday - 2027 Planning - Decision Brief | C8: People & Culture | D8: Dave | E8: 46451 | F8: Consider recognizing the Civic Holiday as a paid company holiday beginning in 2027. The cost of one additional paid day off is expected to be modest, while supporting employee recognition, engagement, and retention, and acknowledging employees’ contributions to AGC’s operations, growth priorities, customer commitments, and key initiatives. | G8: Waiting on Information | H8: Approval Required | I8: CEO & CFO | J8: Unknown / TBD | K8: Low | L8: People & Culture | M8: 46310 | N8: Yes | O8: No immediate impact, as a decision is not being requested currently. The proposal is intended to be included in AGC’s 2027 planning discussions to allow sufficient time to evaluate the operational, financial, and cultural benefits and determine whether it aligns with our employee engagement strategy. | P8: Dave | Q8: Sherry | R8: 46244 | S8: No immediate impact. | U8: After 2027 Planning Sessions | W8: =IF($B8="","",IF(OR($G8="Completed",$G8="Cancelled"),"INACTIVE","ACTIVE")) -> ACTIVE | AN8: =IF($A8="","",IF(COUNTIF('Decision Queue'!$A$5:$A$204,$A8)+COUNTIF('Decision Register'!$A$5:$A$304,$A8)>1,"DUPLICATE ID","OK")) -> OK
A9: DEC-0005 | B9: Approval to Hire a Talent Acquisition Manager / Specialist 12-month Contract | C9: People & Culture | D9: Maurizio | E9: 46300 | F9: Approve Option A: The TA role is not a one-person position. For this role / department to be successful and sustainable, this needs to be a two-person team. A two-person team will: 1. Allows for faster search results which in turn will result in faster hiring 2. Cost control: at $95K salary, we will eliminate the need for the next 12 months, to use external agencies and keep all work in house 3. Develop an internal database of candidates for finance, trades and plant roles. | G9: Deferred | H9: Approval Required | I9: SLT | K9: Medium | L9: People & Culture | M9: 46300 | O9: Three options considered: A. Hire a 12-month contract Talent Acquisition Manager. B. Maintain agency support for capacity and critical hiring needs. C. Shift junior/hourly recruitment to HR Business Partners. | P9: Maurizio | Q9: Maurizio | R9: 46293 | S9: Delaying approval will continue to put pressure on a limited resource, which will slow down results and activity. | T9: Decision deferred to October 26 pending further evaluation of hiring requirements, costs, timing, and ROI. Maurizio returns October 26 with cost of each option A & B, forecast 2027 hiring volume by level, and YTD agency spend. Decision taken October 26. | W9: =IF($B9="","",IF(OR($G9="Completed",$G9="Cancelled"),"INACTIVE","ACTIVE")) -> ACTIVE | AN9: =IF($A9="","",IF(COUNTIF('Decision Queue'!$A$5:$A$204,$A9)+COUNTIF('Decision Register'!$A$5:$A$304,$A9)>1,"DUPLICATE ID","OK")) -> OK
A10: DEC-0006 | W10: =IF($B10="","",IF(OR($G10="Completed",$G10="Cancelled"),"INACTIVE","ACTIVE")) | AN10: =IF($A10="","",IF(COUNTIF('Decision Queue'!$A$5:$A$204,$A10)+COUNTIF('Decision Register'!$A$5:$A$304,$A10)>1,"DUPLICATE ID","OK")) -> OK
W11: =IF($B11="","",IF(OR($G11="Completed",$G11="Cancelled"),"INACTIVE","ACTIVE")) | AN11: =IF($A11="","",IF(COUNTIF('Decision Queue'!$A$5:$A$204,$A11)+COUNTIF('Decision Register'!$A$5:$A$304,$A11)>1,"DUPLICATE ID","OK"))
W12: =IF($B12="","",IF(OR($G12="Completed",$G12="Cancelled"),"INACTIVE","ACTIVE")) | AN12: =IF($A12="","",IF(COUNTIF('Decision Queue'!$A$5:$A$204,$A12)+COUNTIF('Decision Register'!$A$5:$A$304,$A12)>1,"DUPLICATE ID","OK"))
W13: =IF($B13="","",IF(OR($G13="Completed",$G13="Cancelled"),"INACTIVE","ACTIVE")) | AN13: =IF($A13="","",IF(COUNTIF('Decision Queue'!$A$5:$A$204,$A13)+COUNTIF('Decision Register'!$A$5:$A$304,$A13)>1,"DUPLICATE ID","OK"))
W14: =IF($B14="","",IF(OR($G14="Completed",$G14="Cancelled"),"INACTIVE","ACTIVE")) | AN14: =IF($A14="","",IF(COUNTIF('Decision Queue'!$A$5:$A$204,$A14)+COUNTIF('Decision Register'!$A$5:$A$304,$A14)>1,"DUPLICATE ID","OK"))
W15: =IF($B15="","",IF(OR($G15="Completed",$G15="Cancelled"),"INACTIVE","ACTIVE")) | AN15: =IF($A15="","",IF(COUNTIF('Decision Queue'!$A$5:$A$204,$A15)+COUNTIF('Decision Register'!$A$5:$A$304,$A15)>1,"DUPLICATE ID","OK"))
W16: =IF($B16="","",IF(OR($G16="Completed",$G16="Cancelled"),"INACTIVE","ACTIVE")) | AN16: =IF($A16="","",IF(COUNTIF('Decision Queue'!$A$5:$A$204,$A16)+COUNTIF('Decision Register'!$A$5:$A$304,$A16)>1,"DUPLICATE ID","OK"))
W17: =IF($B17="","",IF(OR($G17="Completed",$G17="Cancelled"),"INACTIVE","ACTIVE")) | AN17: =IF($A17="","",IF(COUNTIF('Decision Queue'!$A$5:$A$204,$A17)+COUNTIF('Decision Register'!$A$5:$A$304,$A17)>1,"DUPLICATE ID","OK"))
W18: =IF($B18="","",IF(OR($G18="Completed",$G18="Cancelled"),"INACTIVE","ACTIVE")) | AN18: =IF($A18="","",IF(COUNTIF('Decision Queue'!$A$5:$A$204,$A18)+COUNTIF('Decision Register'!$A$5:$A$304,$A18)>1,"DUPLICATE ID","OK"))
W19: =IF($B19="","",IF(OR($G19="Completed",$G19="Cancelled"),"INACTIVE","ACTIVE")) | AN19: =IF($A19="","",IF(COUNTIF('Decision Queue'!$A$5:$A$204,$A19)+COUNTIF('Decision Register'!$A$5:$A$304,$A19)>1,"DUPLICATE ID","OK"))
W20: =IF($B20="","",IF(OR($G20="Completed",$G20="Cancelled"),"INACTIVE","ACTIVE")) | AN20: =IF($A20="","",IF(COUNTIF('Decision Queue'!$A$5:$A$204,$A20)+COUNTIF('Decision Register'!$A$5:$A$304,$A20)>1,"DUPLICATE ID","OK"))
W21: =IF($B21="","",IF(OR($G21="Completed",$G21="Cancelled"),"INACTIVE","ACTIVE")) | AN21: =IF($A21="","",IF(COUNTIF('Decision Queue'!$A$5:$A$204,$A21)+COUNTIF('Decision Register'!$A$5:$A$304,$A21)>1,"DUPLICATE ID","OK"))
W22: =IF($B22="","",IF(OR($G22="Completed",$G22="Cancelled"),"INACTIVE","ACTIVE")) | AN22: =IF($A22="","",IF(COUNTIF('Decision Queue'!$A$5:$A$204,$A22)+COUNTIF('Decision Register'!$A$5:$A$304,$A22)>1,"DUPLICATE ID","OK"))
... W204: =IF($B204="","",IF(OR($G204="Completed",$G204="Cancelled"),"INACTIVE","ACTIVE")) | AN204: =IF($A204="","",IF(COUNTIF('Decision Queue'!$A$5:$A$204,$A204)+COUNTIF('Decision Register'!$A$5:$A$304,$A204)>1,"DUPLICATE ID","OK"))

Sheet Decision Register
A1: Decision Register
A2: Permanent archive of decisions made, including historical decisions entered manually.
A3: QUEUE ITEM: paste columns A:AN from Decision Queue into the next blank row; its DEC ID is retained. HISTORICAL ITEM: enter the decision fields directly and a HIST-2026-### ID appears automatically. Column AO contains the protected immutable key.
A4: Decision ID | B4: Decision Required | C4: Workstream | D4: Assigned To | E4: Decision Deadline | F4: Recommendation | G4: Status | H4: Decision Type | I4: CEO/CFO Attention | J4: Financial Impact | K4: Risk Impact | L4: Strategic Objective | M4: Decision Date | N4: Further Action Required | O4: Context / Input Required | P4: Owned By | Q4: Requested By | R4: Date Raised | S4: Delay Impact / Risk | T4: Blocker / Waiting On | U4: Notes | V4: Queue Immutable Key | W4: Active Record | X4: Decision Log ID | Y4: Source Decision ID | Z4: Decision Summary | AA4: Decision Maker | AB4: Next Action | AC4: Original Issue | AD4: Rationale | AE4: Follow-up Status | AF4: Requester | AG4: Due Date | AH4: Logged Date | AI4: Decision Log Immutable Key | AJ4: Queue Source Key | AK4: Parent Decision ID | AL4: Consistency Check | AM4: ID Origin | AN4: ID Check
A5: HIST-2026-001 | B5: Work order closure Plan to hit the 20th deadline | C5: Finance | D5: Adam | E5: 46167 | F5: → Decided — work order closure delayed given current Sierra resource constraints. Impact on month-end reporting accepted by SLT. Matt to identify all open work orders — deadline June 17th. Adam and David to force-close all open work orders by June 17th | G5: Completed | H5: Strategic Decision | I5: No | J5: Unknown / TBD | W5: =IF($B5="","",IF(OR($G5="Completed",$G5="Cancelled"),"INACTIVE","ACTIVE")) -> INACTIVE | X5: DEC-0001-L1 | Y5: DEC-0001 | Z5: YVF Price Increase | AA5: SLT | AB5: Implement price increase | AC5: Need to take price increases to offset labour/OH rates. Then standardize yield review and cost process next. | AD5: 2.5% Labour and OH Increase | AH5: 46175 | AI5: DECL-K-0001 | AL5: Missing queue key | AM5: Historical/manual | AN5: =IF($A5="","",IF(COUNTIF('Decision Queue'!$A$5:$A$204,$A5)+COUNTIF('Decision Register'!$A$5:$A$304,$A5)>1,"DUPLICATE ID","OK")) -> OK | AO5: HISTK-2026-001
A6: HIST-2026-002 | B6: YVF Price Increase | C6: Commercial | D6: Tom | E6: 46175 | F6: → Decided — Move forward with 2.5% Labour and OH increase = $180k annually effective July 1st. | G6: Completed | H6: Strategic Decision | I6: CEO & CFO | L6: Commercial Growth | M6: 46175 | N6: Yes | O6: Monitor smooth transition from a financial perspective (PO's and invoices reflect correct updated pricing) | P6: Dave | R6: 46175 | W6: =IF($B6="","",IF(OR($G6="Completed",$G6="Cancelled"),"INACTIVE","ACTIVE")) -> INACTIVE | X6: DEC-0002-L1 | Y6: DEC-0002 | Z6: Popeyes Price Increase | AA6: SLT | AB6: Implement price increase | AD6: Boneless items - increase of $1.00. 2-piece - increase effective mid to end of August. | AH6: 46175 | AI6: DECL-K-0002 | AL6: Missing queue key | AM6: Historical/manual | AN6: =IF($A6="","",IF(COUNTIF('Decision Queue'!$A$5:$A$204,$A6)+COUNTIF('Decision Register'!$A$5:$A$304,$A6)>1,"DUPLICATE ID","OK")) -> OK | AO6: HISTK-2026-002
A7: =IF($B7="","",SUBSTITUTE($AO7,"HISTK-","HIST-")) -> HIST-2026-003 | B7: Popeyes Price Increase | C7: Commercial | D7: Tom | E7: 46175 | F7: → Decided — Boneless items - increase of $1.00. | G7: Completed | H7: Strategic Decision | I7: CEO & CFO | L7: Commercial Growth | M7: 46181 | N7: No | O7: Monitor smooth transition. Coontinue to Monitor that POs, overrides, and deductions remain compliant. | P7: Dave | W7: =IF($B7="","",IF(OR($G7="Completed",$G7="Cancelled"),"INACTIVE","ACTIVE")) -> INACTIVE | AM7: =IF($B7="","","Historical/manual") -> Historical/manual | AN7: =IF($A7="","",IF(COUNTIF('Decision Queue'!$A$5:$A$204,$A7)+COUNTIF('Decision Register'!$A$5:$A$304,$A7)>1,"DUPLICATE ID","OK")) -> OK | AO7: HISTK-2026-003
A8: =IF($B8="","",SUBSTITUTE($AO8,"HISTK-","HIST-")) -> HIST-2026-004 | B8: Restaurant business Continue / change / exit | C8: Commercial | D8: Tom | E8: 46181 | F8: → Decided — price increase 15% margin. Effective June 15th. | G8: Completed | H8: Strategic Decision | I8: CEO & CFO | L8: Commercial Growth | M8: 46181 | N8: No | W8: =IF($B8="","",IF(OR($G8="Completed",$G8="Cancelled"),"INACTIVE","ACTIVE")) -> INACTIVE | AM8: =IF($B8="","","Historical/manual") -> Historical/manual | AN8: =IF($A8="","",IF(COUNTIF('Decision Queue'!$A$5:$A$204,$A8)+COUNTIF('Decision Register'!$A$5:$A$304,$A8)>1,"DUPLICATE ID","OK")) -> OK | AO8: HISTK-2026-004
A9: =IF($B9="","",SUBSTITUTE($AO9,"HISTK-","HIST-")) -> HIST-2026-005 | B9: Internship Request (Martin Thangaraj) | C9: People & Culture | D9: Gene | E9: 46181 | F9: → Decided — Unpaid internship arrangement denied. Request to bring in a foreign student for a short-term (150-hour) unpaid internship. US citizen would not have WSIB coverage. Uninsured workplace risk. | G9: Completed | H9: Governance Decision | I9: CEO & CFO | L9: People & Culture | M9: 46181 | N9: No | W9: =IF($B9="","",IF(OR($G10="Completed",$G10="Cancelled"),"INACTIVE","ACTIVE")) -> ACTIVE | AM9: =IF($B9="","","Historical/manual") -> Historical/manual | AN9: =IF($A9="","",IF(COUNTIF('Decision Queue'!$A$5:$A$204,$A9)+COUNTIF('Decision Register'!$A$5:$A$304,$A9)>1,"DUPLICATE ID","OK")) -> OK | AO9: HISTK-2026-005
A10: =IF($B10="","",SUBSTITUTE($AO10,"HISTK-","HIST-")) -> HIST-2026-006 | B10: ASP Strategy Items | C10: ASP Go-Live | D10: Tom | E10: 46181 | F10: → Decided — to discuss items at next ASP Strategy Meeting on June 17 ASP pricing strategy, cost increases, small-bird program requirements, processing capacity, and regulatory obligations will be reviewed as a dedicated agenda item at the next ASP Strategy Meeting. | G10: Visibility Only | H10: Strategic Decision | I10: CEO & CFO | L10: ASP Go-Live | M10: 46181 | N10: Yes | O10: Transferred to ASP Go-Live meetings and other internal meetings. | P10: Tom | R10: 46181 | W10: =IF($B10="","",IF(OR(#REF!="Completed",#REF!="Cancelled"),"INACTIVE","ACTIVE")) -> #REF! | AM10: =IF($B10="","","Historical/manual") -> Historical/manual | AN10: =IF($A10="","",IF(COUNTIF('Decision Queue'!$A$5:$A$204,$A10)+COUNTIF('Decision Register'!$A$5:$A$304,$A10)>1,"DUPLICATE ID","OK")) -> OK | AO10: HISTK-2026-006
A11: =IF($B11="","",SUBSTITUTE($AO11,"HISTK-","HIST-")) -> HIST-2026-007 | B11: Jay – LMIA Request (Reconsideration) Original Recommendation brought forward to SLT on June 1, 2026. | C11: People & Culture | D11: Gene | E11: 46188 | F11: → Decided - Declined — No LMIA sponsorship commitment was made to Jay. Gene to communicate the SLT decision. Existing LMIA support continues for Carol Maia (WP expires 2029). LMIA can be offered as intended (possibly for ASP). | G11: Completed | H11: Governance Decision | I11: CEO & CFO | L11: Other | M11: 46202 | N11: Yes | O11: LMIA can be offered as intended (possibly for ASP). Carol Maia Work Permit expiring in 2029. | P11: Gene | R11: 46189 | W11: =IF($B11="","",IF(OR($G11="Completed",$G11="Cancelled"),"INACTIVE","ACTIVE")) -> INACTIVE | AM11: =IF($B11="","","Historical/manual") -> Historical/manual | AN11: =IF($A11="","",IF(COUNTIF('Decision Queue'!$A$5:$A$204,$A11)+COUNTIF('Decision Register'!$A$5:$A$304,$A11)>1,"DUPLICATE ID","OK")) -> OK | AO11: HISTK-2026-007
A12: =IF($B12="","",SUBSTITUTE($AO12,"HISTK-","HIST-")) -> HIST-2026-008 | B12: Trade Show (SIAL) | C12: Operations | D12: Sherry | E12: 46195 | F12: → Deferred — To smaller group meeting. Assessed budget. Approximate cost per traveller is $8K (includes all costs). | G12: Deferred | H12: Recommendation Required | I12: SLT | L12: Commercial Growth | M12: 46202 | N12: No | O12: Next Steps: - Determine which members should attend - Deliverables - Dave to investigate Growth Programs available to Amir fund it | P12: Tom | Q12: Sherry | R12: 46195 | W12: =IF($B12="","",IF(OR($G12="Completed",$G12="Cancelled"),"INACTIVE","ACTIVE")) -> ACTIVE | AM12: =IF($B12="","","Historical/manual") -> Historical/manual | AN12: =IF($A12="","",IF(COUNTIF('Decision Queue'!$A$5:$A$204,$A12)+COUNTIF('Decision Register'!$A$5:$A$304,$A12)>1,"DUPLICATE ID","OK")) -> OK | AO12: HISTK-2026-008
A13: =IF($B13="","",SUBSTITUTE($AO13,"HISTK-","HIST-")) -> HIST-2026-009 | B13: ASP Inventory Analysis | C13: ASP Go-Live | D13: Tom | E13: 46195 | F13: → Decided — Assigned Sales Team to go direct to 30+ independent Asian supermarkets on June 24, selling-in utility birds. Reduce inventory, get a better price. ASP Inventory report added to regular KPI report (Dave). Update to be provided after Blitz at Thursday meeting. | G13: Completed | H13: Strategic Decision | I13: SLT | M13: 46195 | N13: No | W13: =IF($B13="","",IF(OR($G13="Completed",$G13="Cancelled"),"INACTIVE","ACTIVE")) -> INACTIVE | AM13: =IF($B13="","","Historical/manual") -> Historical/manual | AN13: =IF($A13="","",IF(COUNTIF('Decision Queue'!$A$5:$A$204,$A13)+COUNTIF('Decision Register'!$A$5:$A$304,$A13)>1,"DUPLICATE ID","OK")) -> OK | AO13: HISTK-2026-009
A14: =IF($B14="","",SUBSTITUTE($AO14,"HISTK-","HIST-")) -> HIST-2026-010 | B14: Cargo insurance | C14: Risk & Compliance | D14: Dave | E14: 46195 | F14: → Decided — Pending further review Estimated premium: ~$150K for $300M coverage. Cost-benefit ratio appears unfavourable. Too expensive. Decided and closed on June 22. | G14: Completed | H14: Approval Required | I14: No | J14: >$250K | L14: Other | M14: 46202 | N14: No | W14: =IF($B14="","",IF(OR($G14="Completed",$G14="Cancelled"),"INACTIVE","ACTIVE")) -> INACTIVE | AM14: =IF($B14="","","Historical/manual") -> Historical/manual | AN14: =IF($A14="","",IF(COUNTIF('Decision Queue'!$A$5:$A$204,$A14)+COUNTIF('Decision Register'!$A$5:$A$304,$A14)>1,"DUPLICATE ID","OK")) -> OK | AO14: HISTK-2026-010
A15: =IF($B15="","",SUBSTITUTE($AO15,"HISTK-","HIST-")) -> HIST-2026-011 | B15: Approval of LinkedIn Recruiter Contract Renewal | C15: People & Culture | D15: Maurizio | E15: 46195 | F15: → Decided — Spend/ROI – Gene to Request Summary from Philip. Initiate tracking Operation and Non-Operational Lane. Currently no other options beyond LI recruiter. LI recruiter viewed is a necessary tool for talent acquisition. The annual cost of this contract is $23K USD. Requires a two-year commitment. | G15: In Progress | H15: Information Only | I15: CEO & CFO | J15: $10K-$50K | L15: People & Culture | M15: 46195 | N15: Yes | O15: Gene to Request Summary from Philip. Initiate tracking Operation and Non-Operational Lane. Currently no other options beyond LI recruiter. | P15: Gene | Q15: SLT | R15: 46195 | W15: =IF($B15="","",IF(OR($G15="Completed",$G15="Cancelled"),"INACTIVE","ACTIVE")) -> ACTIVE | AM15: =IF($B15="","","Historical/manual") -> Historical/manual | AN15: =IF($A15="","",IF(COUNTIF('Decision Queue'!$A$5:$A$204,$A15)+COUNTIF('Decision Register'!$A$5:$A$304,$A15)>1,"DUPLICATE ID","OK")) -> OK | AO15: HISTK-2026-011
A16: =IF($B16="","",SUBSTITUTE($AO16,"HISTK-","HIST-")) -> HIST-2026-012 | B16: Potential Office Relocation | C16: Other | D16: Sherry | E16: 46202 | F16: Closed at the June 29 SLT; relocation not being pursued. Sherry followed up with State and relocation not being pursued. | G16: Completed | H16: Information Only | I16: CEO & CFO | J16: Unknown / TBD | L16: Other | M16: 46202 | N16: No | W16: =IF($B16="","",IF(OR($G16="Completed",$G16="Cancelled"),"INACTIVE","ACTIVE")) -> INACTIVE | AM16: =IF($B16="","","Historical/manual") -> Historical/manual | AN16: =IF($A16="","",IF(COUNTIF('Decision Queue'!$A$5:$A$204,$A16)+COUNTIF('Decision Register'!$A$5:$A$304,$A16)>1,"DUPLICATE ID","OK")) -> OK | AO16: HISTK-2026-012
A17: =IF($B17="","",SUBSTITUTE($AO17,"HISTK-","HIST-")) -> HIST-2026-013 | B17: Memberships (CPEP) | C17: Other | D17: Tom | E17: 46202 | F17: Assess budget, determine return on participation. Evaluate networking opportunities. Technical council available to provide guidance and insights on MPIP. Regular meetings are held to address industry questions and concerns. Pending response from CPEP. Returns after cost is available. | G17: Completed | H17: Strategic Decision | I17: SLT | J17: Unknown / TBD | L17: Commercial Growth | M17: 46216 | N17: Yes | O17: Meeting held with CPEP. Membership cost is modest. FPAC membership not required. CPEP technical council will advise on MPIP. Documentation was submitted to CPEP on July 10, 2026. | P17: Tom | Q17: SLT | R17: 46202 | W17: =IF($B17="","",IF(OR($G17="Completed",$G17="Cancelled"),"INACTIVE","ACTIVE")) -> INACTIVE | AM17: =IF($B17="","","Historical/manual") -> Historical/manual | AN17: =IF($A17="","",IF(COUNTIF('Decision Queue'!$A$5:$A$204,$A17)+COUNTIF('Decision Register'!$A$5:$A$304,$A17)>1,"DUPLICATE ID","OK")) -> OK | AO17: HISTK-2026-013
A18: =IF($B18="","",SUBSTITUTE($AO18,"HISTK-","HIST-")) -> HIST-2026-014 | B18: Grant Application (SRF Food Security Funding Opportunity) | C18: Finance | D18: Sherry | E18: 46202 | F18: → Decided — AGC will apply for the SRF grant for the ASP wastewater project. Sherry owns submission (Aug 4); David on financials; Tony to pressure-test before it goes in. | G18: In Progress | H18: Information Only | I18: SLT | J18: Unknown / TBD | L18: ASP Go-Live | M18: 46202 | N18: Yes | O18: Tony to pressure-test before tapplication is submitted. | P18: Sherry | Q18: Sherry | R18: 46202 | W18: =IF($B18="","",IF(OR($G18="Completed",$G18="Cancelled"),"INACTIVE","ACTIVE")) -> ACTIVE | AM18: =IF($B18="","","Historical/manual") -> Historical/manual | AN18: =IF($A18="","",IF(COUNTIF('Decision Queue'!$A$5:$A$204,$A18)+COUNTIF('Decision Register'!$A$5:$A$304,$A18)>1,"DUPLICATE ID","OK")) -> OK | AO18: HISTK-2026-014
A19: =IF($B19="","",SUBSTITUTE($AO19,"HISTK-","HIST-")) -> HIST-2026-015 | B19: Annual Wage Increase Review and Implementation Plan | C19: People & Culture | D19: Gene | E19: 46209 | F19: General 3% wage increase for plant and operations employees, excluding head office staff and anyone employed for less than six months. This approach delivers the greatest benefit at the least financial impact. Total estimated cost: approximately $66,000 over five months — $29,000 for salaried employees, with the balance for hourly employees. Head office salary increases deferred to December pending financial performance review. Seven individuals to be reviewed offline by Dave and Gene and confirmed. Employees receiving increases: 56 hourly employees and approximately 116 salaried staff (counts to be verified). Implementation timeline: the 3% increase takes effect in August; equity adjustments require a separate decision. Funding source: anticipated favourability of approximately $1 million in advertising budget lines. | G19: In Progress | H19: Capital Approval | I19: SLT | J19: $50K-$250K | K19: Medium | L19: People & Culture | M19: 46209 | N19: Yes | O19: Gene and Dave to align on the seven individuals; Gene to circulate the summary for final approval. | P19: Gene | Q19: SLT | R19: 46209 | U19: Remains on Action Register until fully implemented. | W19: =IF($B19="","",IF(OR($G19="Completed",$G19="Cancelled"),"INACTIVE","ACTIVE")) -> ACTIVE | AM19: =IF($B19="","","Historical/manual") -> Historical/manual | AN19: =IF($A19="","",IF(COUNTIF('Decision Queue'!$A$5:$A$204,$A19)+COUNTIF('Decision Register'!$A$5:$A$304,$A19)>1,"DUPLICATE ID","OK")) -> OK | AO19: HISTK-2026-015
A20: =IF($B20="","",SUBSTITUTE($AO20,"HISTK-","HIST-")) -> HIST-2026-016 | B20: Signing of Contracts | C20: Governance | D20: Sherry | E20: 46216 | F20: → Decided — all contracts go to Legal for review before execution. | G20: Completed | H20: Approval Required | I20: CFO | L20: Governance | M20: 46216 | N20: Yes | O20: Sherry to circulate the draft to David for feedback, then finalize and implement. Does not return to SLT. | P20: Sherry | Q20: Sherry | R20: 46216 | W20: =IF($B20="","",IF(OR($G20="Completed",$G20="Cancelled"),"INACTIVE","ACTIVE")) -> INACTIVE | AM20: =IF($B20="","","Historical/manual") -> Historical/manual | AN20: =IF($A20="","",IF(COUNTIF('Decision Queue'!$A$5:$A$204,$A20)+COUNTIF('Decision Register'!$A$5:$A$304,$A20)>1,"DUPLICATE ID","OK")) -> OK | AO20: HISTK-2026-016
A21: =IF($B21="","",SUBSTITUTE($AO21,"HISTK-","HIST-")) -> HIST-2026-017 | B21: AI Policy | C21: Governance | D21: Gene | E21: 46223 | F21: → Decided — policy approval pending Gene and Sherry aligned on policy. Does not return to SLT. | G21: Completed | H21: Governance Decision | I21: CEO & CFO | L21: Governance | M21: 46223 | N21: Yes | O21: Next steps: IT is responsible for determining and communicating which AI platforms are officially approved for use. Policy to be released once IT confirms approved AI platform(s) and governance requirements. Ownership transitioning to IT | P21: Adam | Q21: Sherry | R21: 46223 | W21: =IF($B21="","",IF(OR($G21="Completed",$G21="Cancelled"),"INACTIVE","ACTIVE")) -> INACTIVE | AM21: =IF($B21="","","Historical/manual") -> Historical/manual | AN21: =IF($A21="","",IF(COUNTIF('Decision Queue'!$A$5:$A$204,$A21)+COUNTIF('Decision Register'!$A$5:$A$304,$A21)>1,"DUPLICATE ID","OK")) -> OK | AO21: HISTK-2026-017
A22: =IF($B22="","",SUBSTITUTE($AO22,"HISTK-","HIST-")) -> HIST-2026-018 | B22: Consultant Strategy | C22: ASP Go-Live | D22: Tom | E22: 46223 | F22: → Decided — Engage Ron Judge to formalize scope of work and deliverables to perform the formal readiness and gap assessment. Continue with Practical Approach for: Equipment and maintenance support, maintenance system setup, and remains available to provide targeted support once specific gaps have been identified. | G22: Completed | H22: Strategic Decision | I22: SLT | L22: ASP Go-Live | M22: 46223 | N22: Yes | O22: Engage Ron Judge to formalize scope of work and deliverables to perform the formal readiness and gap assessment. Ron Judge to present the ASP Gap Analysis Findings and Recommendations on August 17, 2026 (after the SLT meeting) | P22: Tom | Q22: SLT | R22: 46223 | U22: Options considered: Ron Judge (MPIP expert only) – consultant with FSQA experience; to provide end-to-end MPIP pricing by end of day. Practical Approach (team of four) – small project on the equipment side with Colin; an opportunity to assess fit and pace of work. Deloitte – expected to be expensive. MNP – scope evaluation started. | W22: =IF($B22="","",IF(OR($G22="Completed",$G22="Cancelled"),"INACTIVE","ACTIVE")) -> INACTIVE | AM22: =IF($B22="","","Historical/manual") -> Historical/manual | AN22: =IF($A22="","",IF(COUNTIF('Decision Queue'!$A$5:$A$204,$A22)+COUNTIF('Decision Register'!$A$5:$A$304,$A22)>1,"DUPLICATE ID","OK")) -> OK | AO22: HISTK-2026-018
A23: =IF($B23="","",SUBSTITUTE($AO23,"HISTK-","HIST-")) -> HIST-2026-019 | B23: Continue Development of a Solution for ASP Vision-Based Quality Control System | C23: ASP Go-Live | D23: Colin | E23: 46223 | F23: → Decided — Continue development and evaluation. Capital investment: approximately $750,000 Annual software subscription: approximately $70,000 Cost to continue evaluation and development work: minimal (approximately $600 per week in resources) | G23: Visibility Only | H23: Strategic Decision | I23: CEO & CFO | J23: <$10K | N23: Yes | O23: Assess costs associated with additional defect categories. Develop a grower quality/downgrade program framework. Build the business case and ROI/payback analysis. Develop a funding and budget strategy for potential implementation. | P23: Colin | R23: 46223 | W23: =IF($B23="","",IF(OR($G23="Completed",$G23="Cancelled"),"INACTIVE","ACTIVE")) -> ACTIVE | AM23: =IF($B23="","","Historical/manual") -> Historical/manual | AN23: =IF($A23="","",IF(COUNTIF('Decision Queue'!$A$5:$A$204,$A23)+COUNTIF('Decision Register'!$A$5:$A$304,$A23)>1,"DUPLICATE ID","OK")) -> OK | AO23: HISTK-2026-019
A24: =IF($B24="","",SUBSTITUTE($AO24,"HISTK-","HIST-")) -> HIST-2026-020 | B24: Bill S-211 Compliance (Reconsideration) | C24: Finance | D24: Sherry | E24: 46223 | F24: → Decided — Internalizing the reporting. AGC will complete the required minimal compliance reporting internally rather than engage MNP, avoiding the quoted $12,500 external cost while remaining compliant with reporting requirements. | G24: Completed | H24: Capital Approval | I24: CFO | P24: Dave | W24: =IF($B24="","",IF(OR($G24="Completed",$G24="Cancelled"),"INACTIVE","ACTIVE")) -> INACTIVE | AM24: =IF($B24="","","Historical/manual") -> Historical/manual | AN24: =IF($A24="","",IF(COUNTIF('Decision Queue'!$A$5:$A$204,$A24)+COUNTIF('Decision Register'!$A$5:$A$304,$A24)>1,"DUPLICATE ID","OK")) -> OK | AO24: HISTK-2026-020
A25: =IF($B25="","",SUBSTITUTE($AO25,"HISTK-","HIST-")) -> HIST-2026-021 | B25: ASP Wastewater Treatment Plant (WWTP) Pre-Engineering Contracts | C25: ASP Go-Live | D25: Colin | E25: 46223 | F25: → Decided — Proceed with FRC (Process Engineering) and Mallard Creek (Building Engineering). Estimated cost of $723,000.00. Colin to continue monitoring MECP pre-consultation status. | G25: Completed | H25: Capital Approval | I25: CEO & CFO | P25: Colin | W25: =IF($B25="","",IF(OR($G25="Completed",$G25="Cancelled"),"INACTIVE","ACTIVE")) -> INACTIVE | AM25: =IF($B25="","","Historical/manual") -> Historical/manual | AN25: =IF($A25="","",IF(COUNTIF('Decision Queue'!$A$5:$A$204,$A25)+COUNTIF('Decision Register'!$A$5:$A$304,$A25)>1,"DUPLICATE ID","OK")) -> OK | AO25: HISTK-2026-021
A26: =IF($B26="","",SUBSTITUTE($AO26,"HISTK-","HIST-")) -> HIST-2026-022 | B26: ASP Equipment Installation Bid Selection (Rigging, mechanical, electrical services and install overhead rail systems for all process equipment) | C26: ASP Go-Live | D26: Colin | E26: 46244 | F26: Recommendation: Rigging, Mechanical and Overhead Rail Contractor(Dynamic - $3.3MM) / Electrical contractor (Sheridan - $1.1MM) → Decided — Split Rigging, Mechanical, and Overhead Rail contract between MWS and Dynamic - Rigging and Overhead Rail – Dynamic ($1.7MM) - Mechanical – MWS ($1.4MM) Rigging, Mechanical, and Overhead Rail Contractors: Obtain additional references for Dynamic and MWS. Decision deferred pending additional reference checks. $600K cost differential between Dynamic and MWS requires further validation. Validate concerns related to change orders, scope management, and delivery performance. Electrical Scope - Proceed with Sheridan. | G26: Completed | H26: Capital Approval | I26: CEO & CFO | L26: ASP Go-Live | N26: Yes | O26: Decision deferred pending additional reference checks. $600K cost differential between Dynamic and MWS requires further validation. Validate concerns related to change orders, scope management, and delivery performance. | P26: Colin | Q26: SLT | R26: 46230 | U26: Does not return to SLT. | W26: =IF($B26="","",IF(OR($G26="Completed",$G26="Cancelled"),"INACTIVE","ACTIVE")) -> INACTIVE | AM26: =IF($B26="","","Historical/manual") -> Historical/manual | AN26: =IF($A26="","",IF(COUNTIF('Decision Queue'!$A$5:$A$204,$A26)+COUNTIF('Decision Register'!$A$5:$A$304,$A26)>1,"DUPLICATE ID","OK")) -> OK | AO26: HISTK-2026-022
A27: =IF($B27="","",SUBSTITUTE($AO27,"HISTK-","HIST-")) -> HIST-2026-023 | B27: A-206 (December 13 to February 6) Harvest Schedule for ASP | C27: ASP Go-Live | D27: Adam | E27: 46244 | F27: → Decided — Option A. Communicate to CK Poultry the SLT decision. Maintain roasters through December to meet harvest requirements, then transition to all broilers in January. The resulting 6,000 birds/week excess capacity will support wet testing, commencing in January (not sooner). | G27: In Progress | H27: Strategic Decision | I27: SLT | J27: $50K-$250K | K27: Medium | L27: ASP Go-Live | M27: 46244 | W27: =IF($B27="","",IF(OR($G27="Completed",$G27="Cancelled"),"INACTIVE","ACTIVE")) -> ACTIVE | AM27: =IF($B27="","","Historical/manual") -> Historical/manual | AN27: =IF($A27="","",IF(COUNTIF('Decision Queue'!$A$5:$A$204,$A27)+COUNTIF('Decision Register'!$A$5:$A$304,$A27)>1,"DUPLICATE ID","OK")) -> OK | AO27: HISTK-2026-023
A28: =IF($B28="","",SUBSTITUTE($AO28,"HISTK-","HIST-")) -> HIST-2026-024 | B28: Bill S-211 Compliance (Reconsideration) | C28: Finance | D28: Sherry | E28: 46258 | F28: → Deferred — Reintroduced at meeting on August 10, Reassessing due to internal resource constraints. Decision to be made August 17, on whether AGC will internalize or engage MNP. Note - Refer to Action Register for open action item and Decision register #HIST 2026-20 → Aug 24 - Decided — Decision was made to move forward with MNP services. Confirmed that MNP to perform the work at a cost of $12,500. The recommendation has shifted due to internal resource constraints and project complexity. | G28: Completed | H28: Capital Approval | W28: =IF($B28="","",IF(OR($G28="Completed",$G28="Cancelled"),"INACTIVE","ACTIVE")) -> INACTIVE | AM28: =IF($B28="","","Historical/manual") -> Historical/manual | AN28: =IF($A28="","",IF(COUNTIF('Decision Queue'!$A$5:$A$204,$A28)+COUNTIF('Decision Register'!$A$5:$A$304,$A28)>1,"DUPLICATE ID","OK")) -> OK | AO28: HISTK-2026-024
A29: =IF($B29="","",SUBSTITUTE($AO29,"HISTK-","HIST-")) -> HIST-2026-025 | B29: Division 9 Steel – CO Approval | C29: ASP Go-Live | D29: Colin | E29: 46258 | F29: → Decided — $125K Change Order was approved. Clarification requested on budget allocation and the $800K for Interior Alterations allowance. Clarify the CBB spend against the $800K and the $410K remaining allowance indicated by CBB. | G29: In Progress | H29: Capital Approval | I29: CEO & CFO | J29: $50K-$250K | K29: Medium | L29: ASP Go-Live | M29: 46258 | N29: Yes | O29: Colin to reconcile actual costs against the approved $800K budget allowance and confirm cost categorization and remaining allowance balance with Coldbox. | W29: =IF($B29="","",IF(OR($G29="Completed",$G29="Cancelled"),"INACTIVE","ACTIVE")) -> ACTIVE | AM29: =IF($B29="","","Historical/manual") -> Historical/manual | AN29: =IF($A29="","",IF(COUNTIF('Decision Queue'!$A$5:$A$204,$A29)+COUNTIF('Decision Register'!$A$5:$A$304,$A29)>1,"DUPLICATE ID","OK")) -> OK | AO29: HISTK-2026-025
A30: =IF($B30="","",SUBSTITUTE($AO30,"HISTK-","HIST-")) -> HIST-2026-026 | B30: Construction Site Trailer Rental | C30: Operations | D30: Colin | E30: 46258 | F30: → Decided — Decision was made to proceed with trailer rental arrangements. Approved the rental of a temporary construction office trailer to accommodate employees during office renovations and support additional staffing requirements through occupancy. Approximate cost $15,209 + HST (12' × 60' mobile office). Colin to confirm trailer layout, occupancy requirements, furniture needs, and final placement location. | G30: Assigned | H30: Capital Approval | I30: CEO & CFO | J30: $10K-$50K | K30: Medium | L30: ASP Go-Live | M30: 46258 | N30: Yes | O30: Colin to confirm trailer layout, occupancy requirements, furniture needs, and final placement location. | W30: =IF($B30="","",IF(OR($G30="Completed",$G30="Cancelled"),"INACTIVE","ACTIVE")) -> ACTIVE | AM30: =IF($B30="","","Historical/manual") -> Historical/manual | AN30: =IF($A30="","",IF(COUNTIF('Decision Queue'!$A$5:$A$204,$A30)+COUNTIF('Decision Register'!$A$5:$A$304,$A30)>1,"DUPLICATE ID","OK")) -> OK | AO30: HISTK-2026-026
A31: =IF($B31="","",SUBSTITUTE($AO31,"HISTK-","HIST-")) -> HIST-2026-027 | B31: UWB Generator Pad Change Order | C31: ASP Go-Live | D31: Colin | E31: 46258 | F31: → Decided — Agreed to proceed with Change Order. Reviewed $1.1M change order relating to generator pad infrastructure. Agreed to proceed with critical-path scope while continuing to evaluate electrical costs and transformer credit recovery opportunities. | G31: Assigned | H31: Capital Approval | I31: CEO & CFO | J31: >$250K | K31: Medium | L31: ASP Go-Live | M31: 46258 | N31: Yes | O31: Proceed with critical-path work to avoid schedule delays. Further assess electrical scope and pursue transformer credit recovery. | W31: =IF($B31="","",IF(OR($G31="Completed",$G31="Cancelled"),"INACTIVE","ACTIVE")) -> ACTIVE | AM31: =IF($B31="","","Historical/manual") -> Historical/manual | AN31: =IF($A31="","",IF(COUNTIF('Decision Queue'!$A$5:$A$204,$A31)+COUNTIF('Decision Register'!$A$5:$A$304,$A31)>1,"DUPLICATE ID","OK")) -> OK | AO31: HISTK-2026-027
A32: =IF($B32="","",SUBSTITUTE($AO32,"HISTK-","HIST-")) -> HIST-2026-028 | B32: Chilled Water System Change Order (OCO-008) | C32: ASP Go-Live | D32: Colin | E32: 46258 | F32: → Decided — Pursue a negotiated settlement tied to project completion milestones. Schedule risk outweighs cost dispute risk. $406K refrigeration change order required to support offal and chilled water processing capacity. Colin to negotiate a reduced settlement with Coldbox, targeting approximately 50% of the claim value and making any payment contingent upon achieving the December 12 project milestone. | G32: Assigned | H32: Capital Approval | I32: CEO & CFO | J32: >$250K | K32: High | L32: ASP Go-Live | M32: 46258 | N32: Yes | O32: Colin to negotiate a reduced settlement with Coldbox, targeting approximately 50% of the claim value and making any payment contingent upon achieving the December 12 project milestone | W32: =IF($B32="","",IF(OR($G32="Completed",$G32="Cancelled"),"INACTIVE","ACTIVE")) -> ACTIVE | AM32: =IF($B32="","","Historical/manual") -> Historical/manual | AN32: =IF($A32="","",IF(COUNTIF('Decision Queue'!$A$5:$A$204,$A32)+COUNTIF('Decision Register'!$A$5:$A$304,$A32)>1,"DUPLICATE ID","OK")) -> OK | AO32: HISTK-2026-028
A33: =IF($B33="","",SUBSTITUTE($AO33,"HISTK-","HIST-")) -> HIST-2026-029 | B33: Team Visit to Baader Facility | C33: ASP Go-Live | D33: Colin | E33: 46258 | F33: → Decided — Send skeleton functional leads to a North American facility (U.S. or Newfoundland). Baader presented an opportunity for key associates to tour existing plants to gain operational insights relevant to ASP startup and equipment implementation. Recommended team to visit site - Adam, Maintenance Manager, Alexander. Evaluate U.S. and Newfoundland sites. | G33: Assigned | H33: Approval Required | I33: SLT | J33: Unknown / TBD | K33: Low | L33: ASP Go-Live | M33: 46258 | N33: Yes | O33: Engage Baader and identify suitable North American facility tour options. Confirm recommended attendees (Adam, Tuhin, Maintenance Manager, Alexander). Evaluate U.S. and Newfoundland sites and return with a proposed visit plan and | W33: =IF($B33="","",IF(OR($G33="Completed",$G33="Cancelled"),"INACTIVE","ACTIVE")) -> ACTIVE | AM33: =IF($B33="","","Historical/manual") -> Historical/manual | AN33: =IF($A33="","",IF(COUNTIF('Decision Queue'!$A$5:$A$204,$A33)+COUNTIF('Decision Register'!$A$5:$A$304,$A33)>1,"DUPLICATE ID","OK")) -> OK | AO33: HISTK-2026-029
A34: =IF($B34="","",SUBSTITUTE($AO34,"HISTK-","HIST-")) -> HIST-2026-030 | B34: Reserved Parking Policy and Eligibility Criteria (Sierra) | C34: Sierra | D34: Gene | E34: 46286 | F34: → Decided — The recommendation is that Managers and Supervisors have designated reserved parking spaces, while all other employees use the remaining spaces on a first-come, first-served basis. I would also recommend establishing clear rules around the use of reserved spaces. Develop a similar structure to AQM adapted to Sierra operation. Gene to develop the policy/procedures. Gene to present it once done. | G34: Assigned | H34: Governance Decision | I34: SLT | J34: Unknown / TBD | K34: Low | M34: 46286 | N34: Yes | O34: Develop a similar structure to AQM adapted to Sierra operation. Gene to develop the policy/procedures. Gene to present it once done. Note - → Deferred to Next SLT Meeting. (Septembet 15) Develop and present recommendations regarding reserved parking allocation and parking governance across facilities. | P34: Gene | Q34: SLT | R34: 46286 | W34: =IF($B34="","",IF(OR($G34="Completed",$G34="Cancelled"),"INACTIVE","ACTIVE")) -> ACTIVE | AM34: =IF($B34="","","Historical/manual") -> Historical/manual | AN34: =IF($A34="","",IF(COUNTIF('Decision Queue'!$A$5:$A$204,$A34)+COUNTIF('Decision Register'!$A$5:$A$304,$A34)>1,"DUPLICATE ID","OK")) -> OK | AO34: HISTK-2026-030
A35: =IF($B35="","",SUBSTITUTE($AO35,"HISTK-","HIST-")) -> HIST-2026-031 | B35: 2026 Gala Sponsorship Structure / Levels | C35: People & Culture | D35: Sherry | E35: 46286 | F35: → Decided — Approved the revised 2026 Gala sponsorship levels. Move forward with approved tiered sponsorship levels, targeted sponsorship opportunities, and honorable mentions. Approved sponsorship tiered levels: Platinum $9,000 | Gold $7,000 | Silver $5,000 | Bronze $3,000 | G35: In Progress | H35: Information Only | I35: No | J35: Unknown / TBD | K35: Low | L35: People & Culture | M35: 46286 | N35: Yes | P35: Sherry | Q35: Sherry | R35: 46286 | W35: =IF($B35="","",IF(OR($G35="Completed",$G35="Cancelled"),"INACTIVE","ACTIVE")) -> ACTIVE | AM35: =IF($B35="","","Historical/manual") -> Historical/manual | AN35: =IF($A35="","",IF(COUNTIF('Decision Queue'!$A$5:$A$204,$A35)+COUNTIF('Decision Register'!$A$5:$A$304,$A35)>1,"DUPLICATE ID","OK")) -> OK | AO35: HISTK-2026-031
A36: =IF($B36="","",SUBSTITUTE($AO36,"HISTK-","HIST-")) -> HIST-2026-032 | B36: Invite Colin to attend SLT meetings for the balance of 2026. | C36: ASP Go-Live | D36: Colin | E36: 46286 | F36: → Decided — Invite Colin to attend SLT meetings for the balance of 2026, in preparation for ASP Go-Live. | G36: Completed | H36: Strategic Decision | I36: SLT | L36: ASP Go-Live | M36: 46286 | N36: No | P36: Tom | Q36: Tom | R36: 46286 | W36: =IF($B36="","",IF(OR($G36="Completed",$G36="Cancelled"),"INACTIVE","ACTIVE")) -> INACTIVE | AM36: =IF($B36="","","Historical/manual") -> Historical/manual | AN36: =IF($A36="","",IF(COUNTIF('Decision Queue'!$A$5:$A$204,$A36)+COUNTIF('Decision Register'!$A$5:$A$304,$A36)>1,"DUPLICATE ID","OK")) -> OK | AO36: HISTK-2026-032
A37: =IF($B37="","",SUBSTITUTE($AO37,"HISTK-","HIST-")) -> HIST-2026-033 | B37: ASP New Farmer / Grower Application – Review, Farmer Circulation & Project Ownership | C37: ASP Go-Live | D37: Tom | E37: 46300 | F37: → DECIDED — Use of a standardized farmer intake form for evaluating new farmer opportunities. The team agreed that Ali will serve as the central coordinator for collecting information, managing inquiries, and advancing opportunities through the review process. Accountable Owner: Tom Coordinator: Ali Returns to SLT: October 26, 2026 | G37: In Progress | H37: Governance Decision | I37: SLT | J37: Unknown / TBD | L37: ASP Go-Live | M37: 46300 | N37: Yes | O37: The team agreed that Ali will serve as the central coordinator for collecting information, managing inquiries, and advancing opportunities through the review process. Accountable Owner: Tom Coordinator: Ali | P37: Tom | Q37: Sherry | R37: 46300 | W37: =IF($B37="","",IF(OR($G37="Completed",$G37="Cancelled"),"INACTIVE","ACTIVE")) -> ACTIVE | AM37: =IF($B37="","","Historical/manual") -> Historical/manual | AN37: =IF($A37="","",IF(COUNTIF('Decision Queue'!$A$5:$A$204,$A37)+COUNTIF('Decision Register'!$A$5:$A$304,$A37)>1,"DUPLICATE ID","OK")) -> OK | AO37: HISTK-2026-033
A38: =IF($B38="","",SUBSTITUTE($AO38,"HISTK-","HIST-")) | W38: =IF($B38="","",IF(OR($G38="Completed",$G38="Cancelled"),"INACTIVE","ACTIVE")) | AM38: =IF($B38="","","Historical/manual") | AN38: =IF($A38="","",IF(COUNTIF('Decision Queue'!$A$5:$A$204,$A38)+COUNTIF('Decision Register'!$A$5:$A$304,$A38)>1,"DUPLICATE ID","OK")) | AO38: HISTK-2026-034
A39: =IF($B39="","",SUBSTITUTE($AO39,"HISTK-","HIST-")) | W39: =IF($B39="","",IF(OR($G39="Completed",$G39="Cancelled"),"INACTIVE","ACTIVE")) | AM39: =IF($B39="","","Historical/manual") | AN39: =IF($A39="","",IF(COUNTIF('Decision Queue'!$A$5:$A$204,$A39)+COUNTIF('Decision Register'!$A$5:$A$304,$A39)>1,"DUPLICATE ID","OK")) | AO39: HISTK-2026-035
A40: =IF($B40="","",SUBSTITUTE($AO40,"HISTK-","HIST-")) | W40: =IF($B40="","",IF(OR($G40="Completed",$G40="Cancelled"),"INACTIVE","ACTIVE")) | AM40: =IF($B40="","","Historical/manual") | AN40: =IF($A40="","",IF(COUNTIF('Decision Queue'!$A$5:$A$204,$A40)+COUNTIF('Decision Register'!$A$5:$A$304,$A40)>1,"DUPLICATE ID","OK")) | AO40: HISTK-2026-036
A41: =IF($B41="","",SUBSTITUTE($AO41,"HISTK-","HIST-")) | W41: =IF($B41="","",IF(OR($G41="Completed",$G41="Cancelled"),"INACTIVE","ACTIVE")) | AM41: =IF($B41="","","Historical/manual") | AN41: =IF($A41="","",IF(COUNTIF('Decision Queue'!$A$5:$A$204,$A41)+COUNTIF('Decision Register'!$A$5:$A$304,$A41)>1,"DUPLICATE ID","OK")) | AO41: HISTK-2026-037
A42: =IF($B42="","",SUBSTITUTE($AO42,"HISTK-","HIST-")) | W42: =IF($B42="","",IF(OR($G42="Completed",$G42="Cancelled"),"INACTIVE","ACTIVE")) | AM42: =IF($B42="","","Historical/manual") | AN42: =IF($A42="","",IF(COUNTIF('Decision Queue'!$A$5:$A$204,$A42)+COUNTIF('Decision Register'!$A$5:$A$304,$A42)>1,"DUPLICATE ID","OK")) | AO42: HISTK-2026-038
A43: =IF($B43="","",SUBSTITUTE($AO43,"HISTK-","HIST-")) | W43: =IF($B43="","",IF(OR($G43="Completed",$G43="Cancelled"),"INACTIVE","ACTIVE")) | AM43: =IF($B43="","","Historical/manual") | AN43: =IF($A43="","",IF(COUNTIF('Decision Queue'!$A$5:$A$204,$A43)+COUNTIF('Decision Register'!$A$5:$A$304,$A43)>1,"DUPLICATE ID","OK")) | AO43: HISTK-2026-039
A44: =IF($B44="","",SUBSTITUTE($AO44,"HISTK-","HIST-")) | W44: =IF($B44="","",IF(OR($G44="Completed",$G44="Cancelled"),"INACTIVE","ACTIVE")) | AM44: =IF($B44="","","Historical/manual") | AN44: =IF($A44="","",IF(COUNTIF('Decision Queue'!$A$5:$A$204,$A44)+COUNTIF('Decision Register'!$A$5:$A$304,$A44)>1,"DUPLICATE ID","OK")) | AO44: HISTK-2026-040
A45: =IF($B45="","",SUBSTITUTE($AO45,"HISTK-","HIST-")) | W45: =IF($B45="","",IF(OR($G45="Completed",$G45="Cancelled"),"INACTIVE","ACTIVE")) | AM45: =IF($B45="","","Historical/manual") | AN45: =IF($A45="","",IF(COUNTIF('Decision Queue'!$A$5:$A$204,$A45)+COUNTIF('Decision Register'!$A$5:$A$304,$A45)>1,"DUPLICATE ID","OK")) | AO45: HISTK-2026-041
A46: =IF($B46="","",SUBSTITUTE($AO46,"HISTK-","HIST-")) | W46: =IF($B46="","",IF(OR($G46="Completed",$G46="Cancelled"),"INACTIVE","ACTIVE")) | AM46: =IF($B46="","","Historical/manual") | AN46: =IF($A46="","",IF(COUNTIF('Decision Queue'!$A$5:$A$204,$A46)+COUNTIF('Decision Register'!$A$5:$A$304,$A46)>1,"DUPLICATE ID","OK")) | AO46: HISTK-2026-042
A47: =IF($B47="","",SUBSTITUTE($AO47,"HISTK-","HIST-")) | W47: =IF($B47="","",IF(OR($G47="Completed",$G47="Cancelled"),"INACTIVE","ACTIVE")) | AM47: =IF($B47="","","Historical/manual") | AN47: =IF($A47="","",IF(COUNTIF('Decision Queue'!$A$5:$A$204,$A47)+COUNTIF('Decision Register'!$A$5:$A$304,$A47)>1,"DUPLICATE ID","OK")) | AO47: HISTK-2026-043
A48: =IF($B48="","",SUBSTITUTE($AO48,"HISTK-","HIST-")) | W48: =IF($B48="","",IF(OR($G48="Completed",$G48="Cancelled"),"INACTIVE","ACTIVE")) | AM48: =IF($B48="","","Historical/manual") | AN48: =IF($A48="","",IF(COUNTIF('Decision Queue'!$A$5:$A$204,$A48)+COUNTIF('Decision Register'!$A$5:$A$304,$A48)>1,"DUPLICATE ID","OK")) | AO48: HISTK-2026-044
A49: =IF($B49="","",SUBSTITUTE($AO49,"HISTK-","HIST-")) | W49: =IF($B49="","",IF(OR($G49="Completed",$G49="Cancelled"),"INACTIVE","ACTIVE")) | AM49: =IF($B49="","","Historical/manual") | AN49: =IF($A49="","",IF(COUNTIF('Decision Queue'!$A$5:$A$204,$A49)+COUNTIF('Decision Register'!$A$5:$A$304,$A49)>1,"DUPLICATE ID","OK")) | AO49: HISTK-2026-045
... A304: =IF($B304="","",SUBSTITUTE($AO304,"HISTK-","HIST-")) | W304: =IF($B304="","",IF(OR($G304="Completed",$G304="Cancelled"),"INACTIVE","ACTIVE")) | AM304: =IF($B304="","","Historical/manual") | AN304: =IF($A304="","",IF(COUNTIF('Decision Queue'!$A$5:$A$204,$A304)+COUNTIF('Decision Register'!$A$5:$A$304,$A304)>1,"DUPLICATE ID","OK")) | AO304: HISTK-2026-300

Sheet 90-Commitments
A1: 90 DAY COMMITMENTS - 2026
A2: Open | B2: On Track | C2: At Risk | D2: Overdue
A3: =COUNTIFS(CommitmentsTable[Commitment / deliverable],"<>",CommitmentsTable[Status2],"<>Closed") -> 19 | B3: =COUNTIF(CommitmentsTable[RAG Status],"*Met/On Track*") -> 11 | C3: =COUNTIF(CommitmentsTable[RAG Status],"*At Risk/Carried Forward*") -> 0 | D3: =COUNTIF(CommitmentsTable[RAG Status],"*Late/Missed*") -> 0
A12: ID | B12: Commitment / deliverable | C12: Success Measure | D12: Owner | E12: RAG Status | F12: Status1 | G12: Date record entered | H12: Date Assigned if different from entry date | I12: Original due | J12: 30 Day Check-In Update due | K12: 30 Day Check-In Notes | L12: 60 Day Check-In Update due | M12: 60 Day Check-In Notes | N12: 90 Day Check-In Update Dates | O12: Extension Approved By | P12: Ext. Approval Date | Q12: Revised due | R12: Delivered on | S12: Current due | T12: Status2 | U12: Report cue | V12: Change / risk / next step | W12: Immutable Key
A13: =IF(OR(CommitmentsTable[[#This Row],[Commitment / deliverable]]="",CommitmentsTable[[#This Row],[Immutable Key]]=""),"",SUBSTITUTE(CommitmentsTable[[#This Row],[Immutable Key]],"-K-","-")) -> C90-WXFPP2VF | B13: Define KPIs and associated processes to support the 2027 budget rollout. All SLT members will identify and report on no more than 10 KPIs to ensure a focused and consistent approach to performance measurement. | C13: A standardized KPI framework, including defined metrics, ownership, targets, and reporting cadence, is established and adopted by the SLT to support performance management and accountability. | D13: Tom | E13: 🟢 Met/On Track | F13: New Assigned - Sept 15, 2026 | G13: =IF(CommitmentsTable[[#This Row],[Commitment / deliverable]]="","",IF(CommitmentsTable[[#This Row],[Date record entered]]="",TODAY(),CommitmentsTable[[#This Row],[Date record entered]])) -> 46307 | H13: 46280 | I13: =IF(CommitmentsTable[[#This Row],[Date Assigned if different from entry date]]<>"",CommitmentsTable[[#This Row],[Date Assigned if different from entry date]]+90,IF(CommitmentsTable[[#This Row],[Date record entered]]<>"",CommitmentsTable[[#This Row],[Date record entered]]+90,"")) -> 46370 | J13: =IF(CommitmentsTable[[#This Row],[Date Assigned if different from entry date]]<>"",CommitmentsTable[[#This Row],[Date Assigned if different from entry date]]+30,IF(CommitmentsTable[[#This Row],[Date record entered]]<>"",CommitmentsTable[[#This Row],[Date record entered]]+30,"")) -> 46310 | L13: =IF(CommitmentsTable[[#This Row],[Date Assigned if different from entry date]]<>"",CommitmentsTable[[#This Row],[Date Assigned if different from entry date]]+60,IF(CommitmentsTable[[#This Row],[Date record entered]]<>"",CommitmentsTable[[#This Row],[Date record entered]]+60,"")) -> 46340 | S13: =IF(CommitmentsTable[[#This Row],[Commitment / deliverable]]="","",IF(CommitmentsTable[[#This Row],[Revised due]]<>"",CommitmentsTable[[#This Row],[Revised due]],CommitmentsTable[[#This Row],[Original due]])) -> 46370 | T13: =IF(OR(CommitmentsTable[[#This Row],[Commitment / deliverable]]="",CommitmentsTable[[#This Row],[Owner]]=""),"",IF(CommitmentsTable[[#This Row],[Status2]]="","Open",CommitmentsTable[[#This Row],[Status2]])) -> Open | U13: =IF(B13="","",IF(T13="Closed","",IF(OR(T13="Slipped",T13="At risk",AND(S13<>"",S13<TODAY())),"Slipped / at risk",IF(G13=TODAY(),"New today",IF(S13=TODAY()+1,"Due tomorrow",""))))) | W13: C90-K-WXFPP2VF
A14: =IF(OR(CommitmentsTable[[#This Row],[Commitment / deliverable]]="",CommitmentsTable[[#This Row],[Immutable Key]]=""),"",SUBSTITUTE(CommitmentsTable[[#This Row],[Immutable Key]],"-K-","-")) -> C90-RXFDMSTS | B14: Develop a company-wide scorecard with key financial, operational, and commercial KPIs aligned to strategic priorities. | C14: Leadership scorecard implemented and reviewed regularly, incorporating: • Sales Report • Weekly Operations Metrics • Turnover • FSQA Claims (Inbound/Outbound) • Fill Rates • Volume Outputs • Safety • FCC Covenants • AR/AP • Inventory by Line Item • Headcount (Full-Time vs. Agency) | D14: Dave | E14: 🟢 Met/On Track | F14: New Assigned - Sept 15, 2026 | G14: =IF(CommitmentsTable[[#This Row],[Commitment / deliverable]]="","",IF(CommitmentsTable[[#This Row],[Date record entered]]="",TODAY(),CommitmentsTable[[#This Row],[Date record entered]])) -> 46307 | H14: 46280 | I14: =IF(CommitmentsTable[[#This Row],[Date Assigned if different from entry date]]<>"",CommitmentsTable[[#This Row],[Date Assigned if different from entry date]]+90,IF(CommitmentsTable[[#This Row],[Date record entered]]<>"",CommitmentsTable[[#This Row],[Date record entered]]+90,"")) -> 46370 | J14: =IF(CommitmentsTable[[#This Row],[Date Assigned if different from entry date]]<>"",CommitmentsTable[[#This Row],[Date Assigned if different from entry date]]+30,IF(CommitmentsTable[[#This Row],[Date record entered]]<>"",CommitmentsTable[[#This Row],[Date record entered]]+30,"")) -> 46310 | L14: =IF(CommitmentsTable[[#This Row],[Date Assigned if different from entry date]]<>"",CommitmentsTable[[#This Row],[Date Assigned if different from entry date]]+60,IF(CommitmentsTable[[#This Row],[Date record entered]]<>"",CommitmentsTable[[#This Row],[Date record entered]]+60,"")) -> 46340 | S14: =IF(CommitmentsTable[[#This Row],[Commitment / deliverable]]="","",IF(CommitmentsTable[[#This Row],[Revised due]]<>"",CommitmentsTable[[#This Row],[Revised due]],CommitmentsTable[[#This Row],[Original due]])) -> 46370 | T14: =IF(OR(CommitmentsTable[[#This Row],[Commitment / deliverable]]="",CommitmentsTable[[#This Row],[Owner]]=""),"",IF(CommitmentsTable[[#This Row],[Status2]]="","Open",CommitmentsTable[[#This Row],[Status2]])) -> Open | U14: =IF(B14="","",IF(T14="Closed","",IF(OR(T14="Slipped",T14="At risk",AND(S14<>"",S14<TODAY())),"Slipped / at risk",IF(G14=TODAY(),"New today",IF(S14=TODAY()+1,"Due tomorrow",""))))) | W14: C90-K-RXFDMSTS
A15: =IF(OR(CommitmentsTable[[#This Row],[Commitment / deliverable]]="",CommitmentsTable[[#This Row],[Immutable Key]]=""),"",SUBSTITUTE(CommitmentsTable[[#This Row],[Immutable Key]],"-K-","-")) -> C90-BG5BKYCB | B15: Develop a customer scorecard and evaluation framework to support customer segmentation, performance monitoring, and account management strategies. | C15: Customer scorecard reporting available for leadership review, with top accounts categorized as Strategic (Grow), Core (Protect), Manage (Fix/Reprice), or Review (Exit if Unfixable). | D15: Tom | E15: 🟢 Met/On Track | F15: New Assigned - Sept 15, 2026 | G15: =IF(CommitmentsTable[[#This Row],[Commitment / deliverable]]="","",IF(CommitmentsTable[[#This Row],[Date record entered]]="",TODAY(),CommitmentsTable[[#This Row],[Date record entered]])) -> 46307 | H15: 46280 | I15: =IF(CommitmentsTable[[#This Row],[Date Assigned if different from entry date]]<>"",CommitmentsTable[[#This Row],[Date Assigned if different from entry date]]+90,IF(CommitmentsTable[[#This Row],[Date record entered]]<>"",CommitmentsTable[[#This Row],[Date record entered]]+90,"")) -> 46370 | J15: =IF(CommitmentsTable[[#This Row],[Date Assigned if different from entry date]]<>"",CommitmentsTable[[#This Row],[Date Assigned if different from entry date]]+30,IF(CommitmentsTable[[#This Row],[Date record entered]]<>"",CommitmentsTable[[#This Row],[Date record entered]]+30,"")) -> 46310 | L15: =IF(CommitmentsTable[[#This Row],[Date Assigned if different from entry date]]<>"",CommitmentsTable[[#This Row],[Date Assigned if different from entry date]]+60,IF(CommitmentsTable[[#This Row],[Date record entered]]<>"",CommitmentsTable[[#This Row],[Date record entered]]+60,"")) -> 46340 | S15: =IF(CommitmentsTable[[#This Row],[Commitment / deliverable]]="","",IF(CommitmentsTable[[#This Row],[Revised due]]<>"",CommitmentsTable[[#This Row],[Revised due]],CommitmentsTable[[#This Row],[Original due]])) -> 46370 | T15: =IF(OR(CommitmentsTable[[#This Row],[Commitment / deliverable]]="",CommitmentsTable[[#This Row],[Owner]]=""),"",IF(CommitmentsTable[[#This Row],[Status2]]="","Open",CommitmentsTable[[#This Row],[Status2]])) -> Open | U15: =IF(B15="","",IF(T15="Closed","",IF(OR(T15="Slipped",T15="At risk",AND(S15<>"",S15<TODAY())),"Slipped / at risk",IF(G15=TODAY(),"New today",IF(S15=TODAY()+1,"Due tomorrow",""))))) | W15: C90-K-BG5BKYCB
A16: =IF(OR(CommitmentsTable[[#This Row],[Commitment / deliverable]]="",CommitmentsTable[[#This Row],[Immutable Key]]=""),"",SUBSTITUTE(CommitmentsTable[[#This Row],[Immutable Key]],"-K-","-")) -> C90-XYCCR2JW | B16: Develop an integrated AGC Business Forecast Model (to include 2027 Budget & Details) Key Improvement Levers Identified During the Session • ASP operational efficiencies • Wax vs. non-wax packaging opportunities • Sanitation standardization across facilities • Waste management savings • Catching and labour optimization opportunities • Work-from-home and office space savings • CO₂ efficiency opportunities • Equipment and asset optimization (i.e. sell Xray machine to ML) • Strategic growth opportunities (Fowl, Custom Kill, cooking/value-added opportunities) • Capital planning and funding optimization initiatives | C16: Forecast model completed and reviewed by SLT, providing visibility into key business drivers, financial performance, and budget scenarios. | D16: Dave | E16: 🟢 Met/On Track | F16: New Assigned - Sept 15, 2026 | G16: =IF(CommitmentsTable[[#This Row],[Commitment / deliverable]]="","",IF(CommitmentsTable[[#This Row],[Date record entered]]="",TODAY(),CommitmentsTable[[#This Row],[Date record entered]])) -> 46307 | H16: 46280 | I16: =IF(CommitmentsTable[[#This Row],[Date Assigned if different from entry date]]<>"",CommitmentsTable[[#This Row],[Date Assigned if different from entry date]]+90,IF(CommitmentsTable[[#This Row],[Date record entered]]<>"",CommitmentsTable[[#This Row],[Date record entered]]+90,"")) -> 46370 | J16: =IF(CommitmentsTable[[#This Row],[Date Assigned if different from entry date]]<>"",CommitmentsTable[[#This Row],[Date Assigned if different from entry date]]+30,IF(CommitmentsTable[[#This Row],[Date record entered]]<>"",CommitmentsTable[[#This Row],[Date record entered]]+30,"")) -> 46310 | L16: =IF(CommitmentsTable[[#This Row],[Date Assigned if different from entry date]]<>"",CommitmentsTable[[#This Row],[Date Assigned if different from entry date]]+60,IF(CommitmentsTable[[#This Row],[Date record entered]]<>"",CommitmentsTable[[#This Row],[Date record entered]]+60,"")) -> 46340 | S16: =IF(CommitmentsTable[[#This Row],[Commitment / deliverable]]="","",IF(CommitmentsTable[[#This Row],[Revised due]]<>"",CommitmentsTable[[#This Row],[Revised due]],CommitmentsTable[[#This Row],[Original due]])) -> 46370 | T16: =IF(OR(CommitmentsTable[[#This Row],[Commitment / deliverable]]="",CommitmentsTable[[#This Row],[Owner]]=""),"",IF(CommitmentsTable[[#This Row],[Status2]]="","Open",CommitmentsTable[[#This Row],[Status2]])) -> Open | U16: =IF(B16="","",IF(T16="Closed","",IF(OR(T16="Slipped",T16="At risk",AND(S16<>"",S16<TODAY())),"Slipped / at risk",IF(G16=TODAY(),"New today",IF(S16=TODAY()+1,"Due tomorrow",""))))) | W16: C90-K-XYCCR2JW
A17: =IF(OR(CommitmentsTable[[#This Row],[Commitment / deliverable]]="",CommitmentsTable[[#This Row],[Immutable Key]]=""),"",SUBSTITUTE(CommitmentsTable[[#This Row],[Immutable Key]],"-K-","-")) -> C90-DLQWV2SZ | B17: Assess, scope, and prioritize automation opportunities with Inecta to reduce manual effort associated with work order closure reporting. Initiate the process the week of September 21. | C17: Proposal received from Inecta, automation opportunities assessed, and implementation roadmap completed. | D17: Adam Champion: Harsha | E17: 🟢 Met/On Track | F17: New Assigned - Sept 15, 2026 | G17: =IF(CommitmentsTable[[#This Row],[Commitment / deliverable]]="","",IF(CommitmentsTable[[#This Row],[Date record entered]]="",TODAY(),CommitmentsTable[[#This Row],[Date record entered]])) -> 46307 | H17: 46280 | I17: =IF(CommitmentsTable[[#This Row],[Date Assigned if different from entry date]]<>"",CommitmentsTable[[#This Row],[Date Assigned if different from entry date]]+90,IF(CommitmentsTable[[#This Row],[Date record entered]]<>"",CommitmentsTable[[#This Row],[Date record entered]]+90,"")) -> 46370 | J17: =IF(CommitmentsTable[[#This Row],[Date Assigned if different from entry date]]<>"",CommitmentsTable[[#This Row],[Date Assigned if different from entry date]]+30,IF(CommitmentsTable[[#This Row],[Date record entered]]<>"",CommitmentsTable[[#This Row],[Date record entered]]+30,"")) -> 46310 | L17: =IF(CommitmentsTable[[#This Row],[Date Assigned if different from entry date]]<>"",CommitmentsTable[[#This Row],[Date Assigned if different from entry date]]+60,IF(CommitmentsTable[[#This Row],[Date record entered]]<>"",CommitmentsTable[[#This Row],[Date record entered]]+60,"")) -> 46340 | S17: =IF(CommitmentsTable[[#This Row],[Commitment / deliverable]]="","",IF(CommitmentsTable[[#This Row],[Revised due]]<>"",CommitmentsTable[[#This Row],[Revised due]],CommitmentsTable[[#This Row],[Original due]])) -> 46370 | T17: =IF(OR(CommitmentsTable[[#This Row],[Commitment / deliverable]]="",CommitmentsTable[[#This Row],[Owner]]=""),"",IF(CommitmentsTable[[#This Row],[Status2]]="","Open",CommitmentsTable[[#This Row],[Status2]])) -> Open | U17: =IF(B17="","",IF(T17="Closed","",IF(OR(T17="Slipped",T17="At risk",AND(S17<>"",S17<TODAY())),"Slipped / at risk",IF(G17=TODAY(),"New today",IF(S17=TODAY()+1,"Due tomorrow",""))))) | W17: C90-K-DLQWV2SZ
A18: =IF(OR(CommitmentsTable[[#This Row],[Commitment / deliverable]]="",CommitmentsTable[[#This Row],[Immutable Key]]=""),"",SUBSTITUTE(CommitmentsTable[[#This Row],[Immutable Key]],"-K-","-")) -> C90-2T29AZH3 | B18: Complete leadership hiring plan and onboarding strategy. Hiring of tranche 2. | C18: Critical positions staffed and transition plan in place. | D18: Maurizio | E18: 🟢 Met/On Track | F18: New Assigned - Sept 15, 2026 | G18: =IF(CommitmentsTable[[#This Row],[Commitment / deliverable]]="","",IF(CommitmentsTable[[#This Row],[Date record entered]]="",TODAY(),CommitmentsTable[[#This Row],[Date record entered]])) -> 46307 | H18: 46280 | I18: =IF(CommitmentsTable[[#This Row],[Date Assigned if different from entry date]]<>"",CommitmentsTable[[#This Row],[Date Assigned if different from entry date]]+90,IF(CommitmentsTable[[#This Row],[Date record entered]]<>"",CommitmentsTable[[#This Row],[Date record entered]]+90,"")) -> 46370 | J18: =IF(CommitmentsTable[[#This Row],[Date Assigned if different from entry date]]<>"",CommitmentsTable[[#This Row],[Date Assigned if different from entry date]]+30,IF(CommitmentsTable[[#This Row],[Date record entered]]<>"",CommitmentsTable[[#This Row],[Date record entered]]+30,"")) -> 46310 | L18: =IF(CommitmentsTable[[#This Row],[Date Assigned if different from entry date]]<>"",CommitmentsTable[[#This Row],[Date Assigned if different from entry date]]+60,IF(CommitmentsTable[[#This Row],[Date record entered]]<>"",CommitmentsTable[[#This Row],[Date record entered]]+60,"")) -> 46340 | S18: =IF(CommitmentsTable[[#This Row],[Commitment / deliverable]]="","",IF(CommitmentsTable[[#This Row],[Revised due]]<>"",CommitmentsTable[[#This Row],[Revised due]],CommitmentsTable[[#This Row],[Original due]])) -> 46370 | T18: =IF(OR(CommitmentsTable[[#This Row],[Commitment / deliverable]]="",CommitmentsTable[[#This Row],[Owner]]=""),"",IF(CommitmentsTable[[#This Row],[Status2]]="","Open",CommitmentsTable[[#This Row],[Status2]])) -> Open | U18: =IF(B18="","",IF(T18="Closed","",IF(OR(T18="Slipped",T18="At risk",AND(S18<>"",S18<TODAY())),"Slipped / at risk",IF(G18=TODAY(),"New today",IF(S18=TODAY()+1,"Due tomorrow",""))))) | W18: C90-K-2T29AZH3
A19: =IF(OR(CommitmentsTable[[#This Row],[Commitment / deliverable]]="",CommitmentsTable[[#This Row],[Immutable Key]]=""),"",SUBSTITUTE(CommitmentsTable[[#This Row],[Immutable Key]],"-K-","-")) -> C90-KJ25SV73 | B19: Weekly Operations Review Meeting. Implement a formal weekly operations review process with Plant Managers. | C19: Weekly review process established and operating consistently. • Weekly yield $ summary and detailed performance reporting reviewed through the process. • Incident reports reviewed and actioned through the process. • FSQA meeting integration approach finalized. | D19: Adam | E19: 🟢 Met/On Track | F19: New Assigned - Sept 15, 2026 | G19: =IF(CommitmentsTable[[#This Row],[Commitment / deliverable]]="","",IF(CommitmentsTable[[#This Row],[Date record entered]]="",TODAY(),CommitmentsTable[[#This Row],[Date record entered]])) -> 46307 | H19: 46280 | I19: =IF(CommitmentsTable[[#This Row],[Date Assigned if different from entry date]]<>"",CommitmentsTable[[#This Row],[Date Assigned if different from entry date]]+90,IF(CommitmentsTable[[#This Row],[Date record entered]]<>"",CommitmentsTable[[#This Row],[Date record entered]]+90,"")) -> 46370 | J19: =IF(CommitmentsTable[[#This Row],[Date Assigned if different from entry date]]<>"",CommitmentsTable[[#This Row],[Date Assigned if different from entry date]]+30,IF(CommitmentsTable[[#This Row],[Date record entered]]<>"",CommitmentsTable[[#This Row],[Date record entered]]+30,"")) -> 46310 | L19: =IF(CommitmentsTable[[#This Row],[Date Assigned if different from entry date]]<>"",CommitmentsTable[[#This Row],[Date Assigned if different from entry date]]+60,IF(CommitmentsTable[[#This Row],[Date record entered]]<>"",CommitmentsTable[[#This Row],[Date record entered]]+60,"")) -> 46340 | S19: =IF(CommitmentsTable[[#This Row],[Commitment / deliverable]]="","",IF(CommitmentsTable[[#This Row],[Revised due]]<>"",CommitmentsTable[[#This Row],[Revised due]],CommitmentsTable[[#This Row],[Original due]])) -> 46370 | T19: =IF(OR(CommitmentsTable[[#This Row],[Commitment / deliverable]]="",CommitmentsTable[[#This Row],[Owner]]=""),"",IF(CommitmentsTable[[#This Row],[Status2]]="","Open",CommitmentsTable[[#This Row],[Status2]])) -> Open | U19: =IF(B19="","",IF(T19="Closed","",IF(OR(T19="Slipped",T19="At risk",AND(S19<>"",S19<TODAY())),"Slipped / at risk",IF(G19=TODAY(),"New today",IF(S19=TODAY()+1,"Due tomorrow",""))))) | W19: C90-K-KJ25SV73
A20: =IF(OR(CommitmentsTable[[#This Row],[Commitment / deliverable]]="",CommitmentsTable[[#This Row],[Immutable Key]]=""),"",SUBSTITUTE(CommitmentsTable[[#This Row],[Immutable Key]],"-K-","-")) -> C90-M67QTYNY | B20: Strengthen the control environment by implementing enhanced financial and operational controls, including: • PO process • approval workflows • authority matrix requirements • reducing the monthly work order closure cycle to less than one week. • Yield Pricing Analysis | C20: • Two phased rollouts of the PO process and authority matrix completed. • Monthly work orders closed within one week of month end. • Expected-cost reporting approach established, with ownership, automation opportunities and implementation plan defined. • Yield pricing analysis incorporated into regular business reviews. | D20: Dave | E20: 🟡 In Progress/Carried Forward | F20: In Progress (Carried Forward) May 21, 2026 | G20: =IF(CommitmentsTable[[#This Row],[Commitment / deliverable]]="","",IF(CommitmentsTable[[#This Row],[Date record entered]]="",TODAY(),CommitmentsTable[[#This Row],[Date record entered]])) -> 46307 | H20: 46280 | I20: =IF(CommitmentsTable[[#This Row],[Date Assigned if different from entry date]]<>"",CommitmentsTable[[#This Row],[Date Assigned if different from entry date]]+90,IF(CommitmentsTable[[#This Row],[Date record entered]]<>"",CommitmentsTable[[#This Row],[Date record entered]]+90,"")) -> 46370 | J20: =IF(CommitmentsTable[[#This Row],[Date Assigned if different from entry date]]<>"",CommitmentsTable[[#This Row],[Date Assigned if different from entry date]]+30,IF(CommitmentsTable[[#This Row],[Date record entered]]<>"",CommitmentsTable[[#This Row],[Date record entered]]+30,"")) -> 46310 | L20: =IF(CommitmentsTable[[#This Row],[Date Assigned if different from entry date]]<>"",CommitmentsTable[[#This Row],[Date Assigned if different from entry date]]+60,IF(CommitmentsTable[[#This Row],[Date record entered]]<>"",CommitmentsTable[[#This Row],[Date record entered]]+60,"")) -> 46340 | S20: =IF(CommitmentsTable[[#This Row],[Commitment / deliverable]]="","",IF(CommitmentsTable[[#This Row],[Revised due]]<>"",CommitmentsTable[[#This Row],[Revised due]],CommitmentsTable[[#This Row],[Original due]])) -> 46370 | T20: =IF(OR(CommitmentsTable[[#This Row],[Commitment / deliverable]]="",CommitmentsTable[[#This Row],[Owner]]=""),"",IF(CommitmentsTable[[#This Row],[Status2]]="","Open",CommitmentsTable[[#This Row],[Status2]])) -> Open | U20: =IF(B20="","",IF(T20="Closed","",IF(OR(T20="Slipped",T20="At risk",AND(S20<>"",S20<TODAY())),"Slipped / at risk",IF(G20=TODAY(),"New today",IF(S20=TODAY()+1,"Due tomorrow",""))))) | W20: C90-K-M67QTYNY
A21: =IF(OR(CommitmentsTable[[#This Row],[Commitment / deliverable]]="",CommitmentsTable[[#This Row],[Immutable Key]]=""),"",SUBSTITUTE(CommitmentsTable[[#This Row],[Immutable Key]],"-K-","-")) -> C90-FUXR9SRL | B21: Supply risk management remains in progress. The team discussed the challenges associated with inconsistent volumes and the need for greater operational flexibility, including the ability to pivot resources and production capacity to meet changing business demands. | D21: Tom | E21: 🟡 In Progress/Carried Forward | F21: In Progress (Carried Forward) May 21, 206 | G21: =IF(CommitmentsTable[[#This Row],[Commitment / deliverable]]="","",IF(CommitmentsTable[[#This Row],[Date record entered]]="",TODAY(),CommitmentsTable[[#This Row],[Date record entered]])) -> 46307 | H21: 46280 | I21: =IF(CommitmentsTable[[#This Row],[Date Assigned if different from entry date]]<>"",CommitmentsTable[[#This Row],[Date Assigned if different from entry date]]+90,IF(CommitmentsTable[[#This Row],[Date record entered]]<>"",CommitmentsTable[[#This Row],[Date record entered]]+90,"")) -> 46370 | J21: =IF(CommitmentsTable[[#This Row],[Date Assigned if different from entry date]]<>"",CommitmentsTable[[#This Row],[Date Assigned if different from entry date]]+30,IF(CommitmentsTable[[#This Row],[Date record entered]]<>"",CommitmentsTable[[#This Row],[Date record entered]]+30,"")) -> 46310 | L21: =IF(CommitmentsTable[[#This Row],[Date Assigned if different from entry date]]<>"",CommitmentsTable[[#This Row],[Date Assigned if different from entry date]]+60,IF(CommitmentsTable[[#This Row],[Date record entered]]<>"",CommitmentsTable[[#This Row],[Date record entered]]+60,"")) -> 46340 | S21: =IF(CommitmentsTable[[#This Row],[Commitment / deliverable]]="","",IF(CommitmentsTable[[#This Row],[Revised due]]<>"",CommitmentsTable[[#This Row],[Revised due]],CommitmentsTable[[#This Row],[Original due]])) -> 46370 | T21: =IF(OR(CommitmentsTable[[#This Row],[Commitment / deliverable]]="",CommitmentsTable[[#This Row],[Owner]]=""),"",IF(CommitmentsTable[[#This Row],[Status2]]="","Open",CommitmentsTable[[#This Row],[Status2]])) -> Open | U21: =IF(B21="","",IF(T21="Closed","",IF(OR(T21="Slipped",T21="At risk",AND(S21<>"",S21<TODAY())),"Slipped / at risk",IF(G21=TODAY(),"New today",IF(S21=TODAY()+1,"Due tomorrow",""))))) | W21: C90-K-FUXR9SRL
A22: =IF(OR(CommitmentsTable[[#This Row],[Commitment / deliverable]]="",CommitmentsTable[[#This Row],[Immutable Key]]=""),"",SUBSTITUTE(CommitmentsTable[[#This Row],[Immutable Key]],"-K-","-")) -> C90-N3R94QSP | B22: Customer profitability. Approximately 50-60% complete. Additional analysis and reporting are required to support customer scorecards, profitability visibility, and commercial decision-making. | D22: Dave | E22: 🟡 In Progress/Carried Forward | F22: In Progress (Carried Forward) May 21, 2026 | G22: =IF(CommitmentsTable[[#This Row],[Commitment / deliverable]]="","",IF(CommitmentsTable[[#This Row],[Date record entered]]="",TODAY(),CommitmentsTable[[#This Row],[Date record entered]])) -> 46307 | H22: 46280 | I22: =IF(CommitmentsTable[[#This Row],[Date Assigned if different from entry date]]<>"",CommitmentsTable[[#This Row],[Date Assigned if different from entry date]]+90,IF(CommitmentsTable[[#This Row],[Date record entered]]<>"",CommitmentsTable[[#This Row],[Date record entered]]+90,"")) -> 46370 | J22: =IF(CommitmentsTable[[#This Row],[Date Assigned if different from entry date]]<>"",CommitmentsTable[[#This Row],[Date Assigned if different from entry date]]+30,IF(CommitmentsTable[[#This Row],[Date record entered]]<>"",CommitmentsTable[[#This Row],[Date record entered]]+30,"")) -> 46310 | L22: =IF(CommitmentsTable[[#This Row],[Date Assigned if different from entry date]]<>"",CommitmentsTable[[#This Row],[Date Assigned if different from entry date]]+60,IF(CommitmentsTable[[#This Row],[Date record entered]]<>"",CommitmentsTable[[#This Row],[Date record entered]]+60,"")) -> 46340 | S22: =IF(CommitmentsTable[[#This Row],[Commitment / deliverable]]="","",IF(CommitmentsTable[[#This Row],[Revised due]]<>"",CommitmentsTable[[#This Row],[Revised due]],CommitmentsTable[[#This Row],[Original due]])) -> 46370 | T22: =IF(OR(CommitmentsTable[[#This Row],[Commitment / deliverable]]="",CommitmentsTable[[#This Row],[Owner]]=""),"",IF(CommitmentsTable[[#This Row],[Status2]]="","Open",CommitmentsTable[[#This Row],[Status2]])) -> Open | U22: =IF(B22="","",IF(T22="Closed","",IF(OR(T22="Slipped",T22="At risk",AND(S22<>"",S22<TODAY())),"Slipped / at risk",IF(G22=TODAY(),"New today",IF(S22=TODAY()+1,"Due tomorrow",""))))) | W22: C90-K-N3R94QSP
A23: =IF(OR(CommitmentsTable[[#This Row],[Commitment / deliverable]]="",CommitmentsTable[[#This Row],[Immutable Key]]=""),"",SUBSTITUTE(CommitmentsTable[[#This Row],[Immutable Key]],"-K-","-")) -> C90-RGAZP8KR | B23: Yield pricing analysis. Approximately 50% complete. AQM has helped advance discussions and improve visibility into yield performance. Further work is required to finalize standards and reporting requirements. | D23: Dave | E23: 🟡 In Progress/Carried Forward | F23: In Progress (Carried Forward) May 21, 2026 | G23: =IF(CommitmentsTable[[#This Row],[Commitment / deliverable]]="","",IF(CommitmentsTable[[#This Row],[Date record entered]]="",TODAY(),CommitmentsTable[[#This Row],[Date record entered]])) -> 46307 | H23: 46280 | I23: =IF(CommitmentsTable[[#This Row],[Date Assigned if different from entry date]]<>"",CommitmentsTable[[#This Row],[Date Assigned if different from entry date]]+90,IF(CommitmentsTable[[#This Row],[Date record entered]]<>"",CommitmentsTable[[#This Row],[Date record entered]]+90,"")) -> 46370 | J23: =IF(CommitmentsTable[[#This Row],[Date Assigned if different from entry date]]<>"",CommitmentsTable[[#This Row],[Date Assigned if different from entry date]]+30,IF(CommitmentsTable[[#This Row],[Date record entered]]<>"",CommitmentsTable[[#This Row],[Date record entered]]+30,"")) -> 46310 | L23: =IF(CommitmentsTable[[#This Row],[Date Assigned if different from entry date]]<>"",CommitmentsTable[[#This Row],[Date Assigned if different from entry date]]+60,IF(CommitmentsTable[[#This Row],[Date record entered]]<>"",CommitmentsTable[[#This Row],[Date record entered]]+60,"")) -> 46340 | S23: =IF(CommitmentsTable[[#This Row],[Commitment / deliverable]]="","",IF(CommitmentsTable[[#This Row],[Revised due]]<>"",CommitmentsTable[[#This Row],[Revised due]],CommitmentsTable[[#This Row],[Original due]])) -> 46370 | T23: =IF(OR(CommitmentsTable[[#This Row],[Commitment / deliverable]]="",CommitmentsTable[[#This Row],[Owner]]=""),"",IF(CommitmentsTable[[#This Row],[Status2]]="","Open",CommitmentsTable[[#This Row],[Status2]])) -> Open | U23: =IF(B23="","",IF(T23="Closed","",IF(OR(T23="Slipped",T23="At risk",AND(S23<>"",S23<TODAY())),"Slipped / at risk",IF(G23=TODAY(),"New today",IF(S23=TODAY()+1,"Due tomorrow",""))))) | W23: C90-K-RGAZP8KR
A24: =IF(OR(CommitmentsTable[[#This Row],[Commitment / deliverable]]="",CommitmentsTable[[#This Row],[Immutable Key]]=""),"",SUBSTITUTE(CommitmentsTable[[#This Row],[Immutable Key]],"-K-","-")) -> C90-4TMMB8FU | B24: Build and secure commitments of 13 new barns, placement schedules with 2027 demand plan. | C24: 13 barn commitments confirmed and placement schedules aligned to support 2027 demand. | D24: Tony | E24: 🟡 In Progress/Carried Forward | F24: In Progress | G24: =IF(CommitmentsTable[[#This Row],[Commitment / deliverable]]="","",IF(CommitmentsTable[[#This Row],[Date record entered]]="",TODAY(),CommitmentsTable[[#This Row],[Date record entered]])) -> 46307 | H24: 46280 | I24: =IF(CommitmentsTable[[#This Row],[Date Assigned if different from entry date]]<>"",CommitmentsTable[[#This Row],[Date Assigned if different from entry date]]+90,IF(CommitmentsTable[[#This Row],[Date record entered]]<>"",CommitmentsTable[[#This Row],[Date record entered]]+90,"")) -> 46370 | J24: =IF(CommitmentsTable[[#This Row],[Date Assigned if different from entry date]]<>"",CommitmentsTable[[#This Row],[Date Assigned if different from entry date]]+30,IF(CommitmentsTable[[#This Row],[Date record entered]]<>"",CommitmentsTable[[#This Row],[Date record entered]]+30,"")) -> 46310 | L24: =IF(CommitmentsTable[[#This Row],[Date Assigned if different from entry date]]<>"",CommitmentsTable[[#This Row],[Date Assigned if different from entry date]]+60,IF(CommitmentsTable[[#This Row],[Date record entered]]<>"",CommitmentsTable[[#This Row],[Date record entered]]+60,"")) -> 46340 | S24: =IF(CommitmentsTable[[#This Row],[Commitment / deliverable]]="","",IF(CommitmentsTable[[#This Row],[Revised due]]<>"",CommitmentsTable[[#This Row],[Revised due]],CommitmentsTable[[#This Row],[Original due]])) -> 46370 | T24: =IF(OR(CommitmentsTable[[#This Row],[Commitment / deliverable]]="",CommitmentsTable[[#This Row],[Owner]]=""),"",IF(CommitmentsTable[[#This Row],[Status2]]="","Open",CommitmentsTable[[#This Row],[Status2]])) -> Open | U24: =IF(B24="","",IF(T24="Closed","",IF(OR(T24="Slipped",T24="At risk",AND(S24<>"",S24<TODAY())),"Slipped / at risk",IF(G24=TODAY(),"New today",IF(S24=TODAY()+1,"Due tomorrow",""))))) | W24: C90-K-4TMMB8FU
A25: =IF(OR(CommitmentsTable[[#This Row],[Commitment / deliverable]]="",CommitmentsTable[[#This Row],[Immutable Key]]=""),"",SUBSTITUTE(CommitmentsTable[[#This Row],[Immutable Key]],"-K-","-")) -> C90-9GV99WKS | B25: Yield Variance Reporting. Template completed, in progress. Time constraints. Could become the SLT Dashboard. | C25: Yield variance reporting framework finalized and available for SLT review. | D25: Adam | E25: 🟡 In Progress/Carried Forward | F25: In Progress (Carried Forward) May 21, 2026 | G25: =IF(CommitmentsTable[[#This Row],[Commitment / deliverable]]="","",IF(CommitmentsTable[[#This Row],[Date record entered]]="",TODAY(),CommitmentsTable[[#This Row],[Date record entered]])) -> 46307 | H25: 46280 | I25: =IF(CommitmentsTable[[#This Row],[Date Assigned if different from entry date]]<>"",CommitmentsTable[[#This Row],[Date Assigned if different from entry date]]+90,IF(CommitmentsTable[[#This Row],[Date record entered]]<>"",CommitmentsTable[[#This Row],[Date record entered]]+90,"")) -> 46370 | J25: =IF(CommitmentsTable[[#This Row],[Date Assigned if different from entry date]]<>"",CommitmentsTable[[#This Row],[Date Assigned if different from entry date]]+30,IF(CommitmentsTable[[#This Row],[Date record entered]]<>"",CommitmentsTable[[#This Row],[Date record entered]]+30,"")) -> 46310 | L25: =IF(CommitmentsTable[[#This Row],[Date Assigned if different from entry date]]<>"",CommitmentsTable[[#This Row],[Date Assigned if different from entry date]]+60,IF(CommitmentsTable[[#This Row],[Date record entered]]<>"",CommitmentsTable[[#This Row],[Date record entered]]+60,"")) -> 46340 | S25: =IF(CommitmentsTable[[#This Row],[Commitment / deliverable]]="","",IF(CommitmentsTable[[#This Row],[Revised due]]<>"",CommitmentsTable[[#This Row],[Revised due]],CommitmentsTable[[#This Row],[Original due]])) -> 46370 | T25: =IF(OR(CommitmentsTable[[#This Row],[Commitment / deliverable]]="",CommitmentsTable[[#This Row],[Owner]]=""),"",IF(CommitmentsTable[[#This Row],[Status2]]="","Open",CommitmentsTable[[#This Row],[Status2]])) -> Open | U25: =IF(B25="","",IF(T25="Closed","",IF(OR(T25="Slipped",T25="At risk",AND(S25<>"",S25<TODAY())),"Slipped / at risk",IF(G25=TODAY(),"New today",IF(S25=TODAY()+1,"Due tomorrow",""))))) | W25: C90-K-9GV99WKS
A26: =IF(OR(CommitmentsTable[[#This Row],[Commitment / deliverable]]="",CommitmentsTable[[#This Row],[Immutable Key]]=""),"",SUBSTITUTE(CommitmentsTable[[#This Row],[Immutable Key]],"-K-","-")) -> C90-H8Z8WF2P | B26: Fowl & Custom Kill Organic (ASP), as part of incremental modeling. | C26: Growth opportunities assessed and incorporated into incremental volume planning, with recommendations and implementation priorities established. | D26: Tony / Tom | E26: 🟢 Met/On Track | F26: New Assigned - Sept 15, 2026 | G26: =IF(CommitmentsTable[[#This Row],[Commitment / deliverable]]="","",IF(CommitmentsTable[[#This Row],[Date record entered]]="",TODAY(),CommitmentsTable[[#This Row],[Date record entered]])) -> 46307 | H26: 46280 | I26: =IF(CommitmentsTable[[#This Row],[Date Assigned if different from entry date]]<>"",CommitmentsTable[[#This Row],[Date Assigned if different from entry date]]+90,IF(CommitmentsTable[[#This Row],[Date record entered]]<>"",CommitmentsTable[[#This Row],[Date record entered]]+90,"")) -> 46370 | J26: =IF(CommitmentsTable[[#This Row],[Date Assigned if different from entry date]]<>"",CommitmentsTable[[#This Row],[Date Assigned if different from entry date]]+30,IF(CommitmentsTable[[#This Row],[Date record entered]]<>"",CommitmentsTable[[#This Row],[Date record entered]]+30,"")) -> 46310 | L26: =IF(CommitmentsTable[[#This Row],[Date Assigned if different from entry date]]<>"",CommitmentsTable[[#This Row],[Date Assigned if different from entry date]]+60,IF(CommitmentsTable[[#This Row],[Date record entered]]<>"",CommitmentsTable[[#This Row],[Date record entered]]+60,"")) -> 46340 | S26: =IF(CommitmentsTable[[#This Row],[Commitment / deliverable]]="","",IF(CommitmentsTable[[#This Row],[Revised due]]<>"",CommitmentsTable[[#This Row],[Revised due]],CommitmentsTable[[#This Row],[Original due]])) -> 46370 | T26: =IF(OR(CommitmentsTable[[#This Row],[Commitment / deliverable]]="",CommitmentsTable[[#This Row],[Owner]]=""),"",IF(CommitmentsTable[[#This Row],[Status2]]="","Open",CommitmentsTable[[#This Row],[Status2]])) -> Open | U26: =IF(B26="","",IF(T26="Closed","",IF(OR(T26="Slipped",T26="At risk",AND(S26<>"",S26<TODAY())),"Slipped / at risk",IF(G26=TODAY(),"New today",IF(S26=TODAY()+1,"Due tomorrow",""))))) | W26: C90-K-H8Z8WF2P
A27: =IF(OR(CommitmentsTable[[#This Row],[Commitment / deliverable]]="",CommitmentsTable[[#This Row],[Immutable Key]]=""),"",SUBSTITUTE(CommitmentsTable[[#This Row],[Immutable Key]],"-K-","-")) -> C90-BU2JXK55 | B27: Improve Specialty Bird profitability through: - Price increases / base - Inventory optimization | C27: Pricing strategy and inventory optimization recommendations completed, with identified margin improvement opportunities and implementation plan established. | D27: Tom | E27: 🟢 Met/On Track | F27: New Assigned - Sept 15, 2026 | G27: =IF(CommitmentsTable[[#This Row],[Commitment / deliverable]]="","",IF(CommitmentsTable[[#This Row],[Date record entered]]="",TODAY(),CommitmentsTable[[#This Row],[Date record entered]])) -> 46307 | H27: 46280 | I27: =IF(CommitmentsTable[[#This Row],[Date Assigned if different from entry date]]<>"",CommitmentsTable[[#This Row],[Date Assigned if different from entry date]]+90,IF(CommitmentsTable[[#This Row],[Date record entered]]<>"",CommitmentsTable[[#This Row],[Date record entered]]+90,"")) -> 46370 | J27: =IF(CommitmentsTable[[#This Row],[Date Assigned if different from entry date]]<>"",CommitmentsTable[[#This Row],[Date Assigned if different from entry date]]+30,IF(CommitmentsTable[[#This Row],[Date record entered]]<>"",CommitmentsTable[[#This Row],[Date record entered]]+30,"")) -> 46310 | L27: =IF(CommitmentsTable[[#This Row],[Date Assigned if different from entry date]]<>"",CommitmentsTable[[#This Row],[Date Assigned if different from entry date]]+60,IF(CommitmentsTable[[#This Row],[Date record entered]]<>"",CommitmentsTable[[#This Row],[Date record entered]]+60,"")) -> 46340 | S27: =IF(CommitmentsTable[[#This Row],[Commitment / deliverable]]="","",IF(CommitmentsTable[[#This Row],[Revised due]]<>"",CommitmentsTable[[#This Row],[Revised due]],CommitmentsTable[[#This Row],[Original due]])) -> 46370 | T27: =IF(OR(CommitmentsTable[[#This Row],[Commitment / deliverable]]="",CommitmentsTable[[#This Row],[Owner]]=""),"",IF(CommitmentsTable[[#This Row],[Status2]]="","Open",CommitmentsTable[[#This Row],[Status2]])) -> Open | U27: =IF(B27="","",IF(T27="Closed","",IF(OR(T27="Slipped",T27="At risk",AND(S27<>"",S27<TODAY())),"Slipped / at risk",IF(G27=TODAY(),"New today",IF(S27=TODAY()+1,"Due tomorrow",""))))) | W27: C90-K-BU2JXK55
A28: =IF(OR(CommitmentsTable[[#This Row],[Commitment / deliverable]]="",CommitmentsTable[[#This Row],[Immutable Key]]=""),"",SUBSTITUTE(CommitmentsTable[[#This Row],[Immutable Key]],"-K-","-")) -> C90-9EWEQ5M3 | B28: Freefield (confirmed) Packaging Options. Explore SIAL exhibitor packaging options. | C28: Packaging options assessed and recommendation completed. | D28: Tom | E28: 🟡 In Progress/Carried Forward | F28: In Progress (Carried Forward) May 21, 2026 | G28: =IF(CommitmentsTable[[#This Row],[Commitment / deliverable]]="","",IF(CommitmentsTable[[#This Row],[Date record entered]]="",TODAY(),CommitmentsTable[[#This Row],[Date record entered]])) -> 46307 | H28: 46280 | I28: =IF(CommitmentsTable[[#This Row],[Date Assigned if different from entry date]]<>"",CommitmentsTable[[#This Row],[Date Assigned if different from entry date]]+90,IF(CommitmentsTable[[#This Row],[Date record entered]]<>"",CommitmentsTable[[#This Row],[Date record entered]]+90,"")) -> 46370 | J28: =IF(CommitmentsTable[[#This Row],[Date Assigned if different from entry date]]<>"",CommitmentsTable[[#This Row],[Date Assigned if different from entry date]]+30,IF(CommitmentsTable[[#This Row],[Date record entered]]<>"",CommitmentsTable[[#This Row],[Date record entered]]+30,"")) -> 46310 | L28: =IF(CommitmentsTable[[#This Row],[Date Assigned if different from entry date]]<>"",CommitmentsTable[[#This Row],[Date Assigned if different from entry date]]+60,IF(CommitmentsTable[[#This Row],[Date record entered]]<>"",CommitmentsTable[[#This Row],[Date record entered]]+60,"")) -> 46340 | S28: =IF(CommitmentsTable[[#This Row],[Commitment / deliverable]]="","",IF(CommitmentsTable[[#This Row],[Revised due]]<>"",CommitmentsTable[[#This Row],[Revised due]],CommitmentsTable[[#This Row],[Original due]])) -> 46370 | T28: =IF(OR(CommitmentsTable[[#This Row],[Commitment / deliverable]]="",CommitmentsTable[[#This Row],[Owner]]=""),"",IF(CommitmentsTable[[#This Row],[Status2]]="","Open",CommitmentsTable[[#This Row],[Status2]])) -> Open | U28: =IF(B28="","",IF(T28="Closed","",IF(OR(T28="Slipped",T28="At risk",AND(S28<>"",S28<TODAY())),"Slipped / at risk",IF(G28=TODAY(),"New today",IF(S28=TODAY()+1,"Due tomorrow",""))))) | W28: C90-K-9EWEQ5M3
A29: =IF(OR(CommitmentsTable[[#This Row],[Commitment / deliverable]]="",CommitmentsTable[[#This Row],[Immutable Key]]=""),"",SUBSTITUTE(CommitmentsTable[[#This Row],[Immutable Key]],"-K-","-")) -> C90-E2WWFWB3 | B29: New Business Development/Project SOP - Develop a standardized stage-gate SOP for new business opportunities and projects. | C29: Three-gate evaluation framework and decision template completed, with approval criteria established for progression between stages. | D29: Tom | E29: 🟢 Met/On Track | F29: New Assigned - Sept 15, 2026 | G29: =IF(CommitmentsTable[[#This Row],[Commitment / deliverable]]="","",IF(CommitmentsTable[[#This Row],[Date record entered]]="",TODAY(),CommitmentsTable[[#This Row],[Date record entered]])) -> 46307 | H29: 46280 | I29: =IF(CommitmentsTable[[#This Row],[Date Assigned if different from entry date]]<>"",CommitmentsTable[[#This Row],[Date Assigned if different from entry date]]+90,IF(CommitmentsTable[[#This Row],[Date record entered]]<>"",CommitmentsTable[[#This Row],[Date record entered]]+90,"")) -> 46370 | J29: =IF(CommitmentsTable[[#This Row],[Date Assigned if different from entry date]]<>"",CommitmentsTable[[#This Row],[Date Assigned if different from entry date]]+30,IF(CommitmentsTable[[#This Row],[Date record entered]]<>"",CommitmentsTable[[#This Row],[Date record entered]]+30,"")) -> 46310 | L29: =IF(CommitmentsTable[[#This Row],[Date Assigned if different from entry date]]<>"",CommitmentsTable[[#This Row],[Date Assigned if different from entry date]]+60,IF(CommitmentsTable[[#This Row],[Date record entered]]<>"",CommitmentsTable[[#This Row],[Date record entered]]+60,"")) -> 46340 | S29: =IF(CommitmentsTable[[#This Row],[Commitment / deliverable]]="","",IF(CommitmentsTable[[#This Row],[Revised due]]<>"",CommitmentsTable[[#This Row],[Revised due]],CommitmentsTable[[#This Row],[Original due]])) -> 46370 | T29: =IF(OR(CommitmentsTable[[#This Row],[Commitment / deliverable]]="",CommitmentsTable[[#This Row],[Owner]]=""),"",IF(CommitmentsTable[[#This Row],[Status2]]="","Open",CommitmentsTable[[#This Row],[Status2]])) -> Open | U29: =IF(B29="","",IF(T29="Closed","",IF(OR(T29="Slipped",T29="At risk",AND(S29<>"",S29<TODAY())),"Slipped / at risk",IF(G29=TODAY(),"New today",IF(S29=TODAY()+1,"Due tomorrow",""))))) | W29: C90-K-E2WWFWB3
A30: =IF(OR(CommitmentsTable[[#This Row],[Commitment / deliverable]]="",CommitmentsTable[[#This Row],[Immutable Key]]=""),"",SUBSTITUTE(CommitmentsTable[[#This Row],[Immutable Key]],"-K-","-")) -> C90-977HDW2G | B30: Identify leaders requiring training and leadership support, to address their development needs. Q2 Matrix identified: 37% A players 50% B Players 13% C Players What is the AGC target? Remained open. | C30: Individuals requiring training and leadership support are identified, assessed, and prioritized, with development plans established to support their growth and effectiveness. | D30: Gene | E30: 🟢 Met/On Track | F30: New Assigned - Sept 15, 2026 | G30: =IF(CommitmentsTable[[#This Row],[Commitment / deliverable]]="","",IF(CommitmentsTable[[#This Row],[Date record entered]]="",TODAY(),CommitmentsTable[[#This Row],[Date record entered]])) -> 46307 | H30: 46280 | I30: =IF(CommitmentsTable[[#This Row],[Date Assigned if different from entry date]]<>"",CommitmentsTable[[#This Row],[Date Assigned if different from entry date]]+90,IF(CommitmentsTable[[#This Row],[Date record entered]]<>"",CommitmentsTable[[#This Row],[Date record entered]]+90,"")) -> 46370 | J30: =IF(CommitmentsTable[[#This Row],[Date Assigned if different from entry date]]<>"",CommitmentsTable[[#This Row],[Date Assigned if different from entry date]]+30,IF(CommitmentsTable[[#This Row],[Date record entered]]<>"",CommitmentsTable[[#This Row],[Date record entered]]+30,"")) -> 46310 | L30: =IF(CommitmentsTable[[#This Row],[Date Assigned if different from entry date]]<>"",CommitmentsTable[[#This Row],[Date Assigned if different from entry date]]+60,IF(CommitmentsTable[[#This Row],[Date record entered]]<>"",CommitmentsTable[[#This Row],[Date record entered]]+60,"")) -> 46340 | S30: =IF(CommitmentsTable[[#This Row],[Commitment / deliverable]]="","",IF(CommitmentsTable[[#This Row],[Revised due]]<>"",CommitmentsTable[[#This Row],[Revised due]],CommitmentsTable[[#This Row],[Original due]])) -> 46370 | T30: =IF(OR(CommitmentsTable[[#This Row],[Commitment / deliverable]]="",CommitmentsTable[[#This Row],[Owner]]=""),"",IF(CommitmentsTable[[#This Row],[Status2]]="","Open",CommitmentsTable[[#This Row],[Status2]])) -> Open | U30: =IF(B30="","",IF(T30="Closed","",IF(OR(T30="Slipped",T30="At risk",AND(S30<>"",S30<TODAY())),"Slipped / at risk",IF(G30=TODAY(),"New today",IF(S30=TODAY()+1,"Due tomorrow",""))))) | W30: C90-K-977HDW2G
A31: =IF(OR(CommitmentsTable[[#This Row],[Commitment / deliverable]]="",CommitmentsTable[[#This Row],[Immutable Key]]=""),"",SUBSTITUTE(CommitmentsTable[[#This Row],[Immutable Key]],"-K-","-")) -> C90-XW97BLKA | B31: Formalize and document the annual performance review process, including review workflows, salary band alignment, and leadership visibility. | C31: Annual review SOP documented and communicated, with defined review workflows, salary band alignment, and leadership visibility and automated review notifications established. | D31: Gene | E31: 🟡 In Progress/Carried Forward | F31: In Progress (Carried Forward) May 21, 2026 | G31: =IF(CommitmentsTable[[#This Row],[Commitment / deliverable]]="","",IF(CommitmentsTable[[#This Row],[Date record entered]]="",TODAY(),CommitmentsTable[[#This Row],[Date record entered]])) -> 46307 | H31: 46280 | I31: =IF(CommitmentsTable[[#This Row],[Date Assigned if different from entry date]]<>"",CommitmentsTable[[#This Row],[Date Assigned if different from entry date]]+90,IF(CommitmentsTable[[#This Row],[Date record entered]]<>"",CommitmentsTable[[#This Row],[Date record entered]]+90,"")) -> 46370 | J31: =IF(CommitmentsTable[[#This Row],[Date Assigned if different from entry date]]<>"",CommitmentsTable[[#This Row],[Date Assigned if different from entry date]]+30,IF(CommitmentsTable[[#This Row],[Date record entered]]<>"",CommitmentsTable[[#This Row],[Date record entered]]+30,"")) -> 46310 | L31: =IF(CommitmentsTable[[#This Row],[Date Assigned if different from entry date]]<>"",CommitmentsTable[[#This Row],[Date Assigned if different from entry date]]+60,IF(CommitmentsTable[[#This Row],[Date record entered]]<>"",CommitmentsTable[[#This Row],[Date record entered]]+60,"")) -> 46340 | S31: =IF(CommitmentsTable[[#This Row],[Commitment / deliverable]]="","",IF(CommitmentsTable[[#This Row],[Revised due]]<>"",CommitmentsTable[[#This Row],[Revised due]],CommitmentsTable[[#This Row],[Original due]])) -> 46370 | T31: =IF(OR(CommitmentsTable[[#This Row],[Commitment / deliverable]]="",CommitmentsTable[[#This Row],[Owner]]=""),"",IF(CommitmentsTable[[#This Row],[Status2]]="","Open",CommitmentsTable[[#This Row],[Status2]])) -> Open | U31: =IF(B31="","",IF(T31="Closed","",IF(OR(T31="Slipped",T31="At risk",AND(S31<>"",S31<TODAY())),"Slipped / at risk",IF(G31=TODAY(),"New today",IF(S31=TODAY()+1,"Due tomorrow",""))))) | W31: C90-K-XW97BLKA
A32: =IF(OR(CommitmentsTable[[#This Row],[Commitment / deliverable]]="",CommitmentsTable[[#This Row],[Immutable Key]]=""),"",SUBSTITUTE(CommitmentsTable[[#This Row],[Immutable Key]],"-K-","-")) | G32: =IF(CommitmentsTable[[#This Row],[Commitment / deliverable]]="","",IF(CommitmentsTable[[#This Row],[Date record entered]]="",TODAY(),CommitmentsTable[[#This Row],[Date record entered]])) | I32: =IF(CommitmentsTable[[#This Row],[Date Assigned if different from entry date]]<>"",CommitmentsTable[[#This Row],[Date Assigned if different from entry date]]+90,IF(CommitmentsTable[[#This Row],[Date record entered]]<>"",CommitmentsTable[[#This Row],[Date record entered]]+90,"")) | J32: =IF(CommitmentsTable[[#This Row],[Date Assigned if different from entry date]]<>"",CommitmentsTable[[#This Row],[Date Assigned if different from entry date]]+30,IF(CommitmentsTable[[#This Row],[Date record entered]]<>"",CommitmentsTable[[#This Row],[Date record entered]]+30,"")) | L32: =IF(CommitmentsTable[[#This Row],[Date Assigned if different from entry date]]<>"",CommitmentsTable[[#This Row],[Date Assigned if different from entry date]]+60,IF(CommitmentsTable[[#This Row],[Date record entered]]<>"",CommitmentsTable[[#This Row],[Date record entered]]+60,"")) | S32: =IF(CommitmentsTable[[#This Row],[Commitment / deliverable]]="","",IF(CommitmentsTable[[#This Row],[Revised due]]<>"",CommitmentsTable[[#This Row],[Revised due]],CommitmentsTable[[#This Row],[Original due]])) | T32: =IF(OR(CommitmentsTable[[#This Row],[Commitment / deliverable]]="",CommitmentsTable[[#This Row],[Owner]]=""),"",IF(CommitmentsTable[[#This Row],[Status2]]="","Open",CommitmentsTable[[#This Row],[Status2]])) | U32: =IF(B32="","",IF(T32="Closed","",IF(OR(T32="Slipped",T32="At risk",AND(S32<>"",S32<TODAY())),"Slipped / at risk",IF(G32=TODAY(),"New today",IF(S32=TODAY()+1,"Due tomorrow",""))))) | W32: C90-K-726WBDFF
A33: =IF(OR(CommitmentsTable[[#This Row],[Commitment / deliverable]]="",CommitmentsTable[[#This Row],[Immutable Key]]=""),"",SUBSTITUTE(CommitmentsTable[[#This Row],[Immutable Key]],"-K-","-")) | G33: =IF(CommitmentsTable[[#This Row],[Commitment / deliverable]]="","",IF(CommitmentsTable[[#This Row],[Date record entered]]="",TODAY(),CommitmentsTable[[#This Row],[Date record entered]])) | I33: =IF(CommitmentsTable[[#This Row],[Date Assigned if different from entry date]]<>"",CommitmentsTable[[#This Row],[Date Assigned if different from entry date]]+90,IF(CommitmentsTable[[#This Row],[Date record entered]]<>"",CommitmentsTable[[#This Row],[Date record entered]]+90,"")) | J33: =IF(CommitmentsTable[[#This Row],[Date Assigned if different from entry date]]<>"",CommitmentsTable[[#This Row],[Date Assigned if different from entry date]]+30,IF(CommitmentsTable[[#This Row],[Date record entered]]<>"",CommitmentsTable[[#This Row],[Date record entered]]+30,"")) | L33: =IF(CommitmentsTable[[#This Row],[Date Assigned if different from entry date]]<>"",CommitmentsTable[[#This Row],[Date Assigned if different from entry date]]+60,IF(CommitmentsTable[[#This Row],[Date record entered]]<>"",CommitmentsTable[[#This Row],[Date record entered]]+60,"")) | S33: =IF(CommitmentsTable[[#This Row],[Commitment / deliverable]]="","",IF(CommitmentsTable[[#This Row],[Revised due]]<>"",CommitmentsTable[[#This Row],[Revised due]],CommitmentsTable[[#This Row],[Original due]])) | T33: =IF(OR(CommitmentsTable[[#This Row],[Commitment / deliverable]]="",CommitmentsTable[[#This Row],[Owner]]=""),"",IF(CommitmentsTable[[#This Row],[Status2]]="","Open",CommitmentsTable[[#This Row],[Status2]])) | U33: =IF(B33="","",IF(T33="Closed","",IF(OR(T33="Slipped",T33="At risk",AND(S33<>"",S33<TODAY())),"Slipped / at risk",IF(G33=TODAY(),"New today",IF(S33=TODAY()+1,"Due tomorrow",""))))) | W33: C90-K-KG7A2K6K
A34: =IF(OR(CommitmentsTable[[#This Row],[Commitment / deliverable]]="",CommitmentsTable[[#This Row],[Immutable Key]]=""),"",SUBSTITUTE(CommitmentsTable[[#This Row],[Immutable Key]],"-K-","-")) | G34: =IF(CommitmentsTable[[#This Row],[Commitment / deliverable]]="","",IF(CommitmentsTable[[#This Row],[Date record entered]]="",TODAY(),CommitmentsTable[[#This Row],[Date record entered]])) | I34: =IF(CommitmentsTable[[#This Row],[Date Assigned if different from entry date]]<>"",CommitmentsTable[[#This Row],[Date Assigned if different from entry date]]+90,IF(CommitmentsTable[[#This Row],[Date record entered]]<>"",CommitmentsTable[[#This Row],[Date record entered]]+90,"")) | J34: =IF(CommitmentsTable[[#This Row],[Date Assigned if different from entry date]]<>"",CommitmentsTable[[#This Row],[Date Assigned if different from entry date]]+30,IF(CommitmentsTable[[#This Row],[Date record entered]]<>"",CommitmentsTable[[#This Row],[Date record entered]]+30,"")) | L34: =IF(CommitmentsTable[[#This Row],[Date Assigned if different from entry date]]<>"",CommitmentsTable[[#This Row],[Date Assigned if different from entry date]]+60,IF(CommitmentsTable[[#This Row],[Date record entered]]<>"",CommitmentsTable[[#This Row],[Date record entered]]+60,"")) | S34: =IF(CommitmentsTable[[#This Row],[Commitment / deliverable]]="","",IF(CommitmentsTable[[#This Row],[Revised due]]<>"",CommitmentsTable[[#This Row],[Revised due]],CommitmentsTable[[#This Row],[Original due]])) | T34: =IF(OR(CommitmentsTable[[#This Row],[Commitment / deliverable]]="",CommitmentsTable[[#This Row],[Owner]]=""),"",IF(CommitmentsTable[[#This Row],[Status2]]="","Open",CommitmentsTable[[#This Row],[Status2]])) | U34: =IF(B34="","",IF(T34="Closed","",IF(OR(T34="Slipped",T34="At risk",AND(S34<>"",S34<TODAY())),"Slipped / at risk",IF(G34=TODAY(),"New today",IF(S34=TODAY()+1,"Due tomorrow",""))))) | W34: C90-K-MY4ERCYG
